Workbook

Sheet Guide
A1: Randori Geopolitical-Macro Risk Desk
A2: A spreadsheet build of the Randori Geopolitical Risk VaR methodology (draft of October 15, 2026) for 18 countries. It scores macro, political and event risk, turns the scores into probabilities and signals, maps each signal to trades, and runs a sample book through a Monte Carlo loss model.
A3: Status: the methodology is an untested draft and most inputs are seed estimates. No figure here should be quoted to a client or traded on before the data feeds are connected and the thresholds are fitted on the backtest.
A5: How the engine flows
A6: 1. Inputs and Country Profile | B6: 83 indicators across the seven pillars, plus market data, flags and tradable instruments for each country.
A7: 2. Stress Inputs | B7: Randori combined shock (depreciation, growth, rates, commodity or tourism export shock) applied to the eight stress-path indicators.
A8: 3. Base, Stress and Indicator Scores | B8: Each indicator scored 0-100 by straight-line interpolation between Rulebook thresholds; the worse of baseline and stress is kept.
A9: 4. Adjustments and Pillar Scores | B9: Weighted average blended with the worst indicator, plus trigger add-ons, capped analyst adjustments and override floors. Composite uses standard or small-state weights; grade = MIN(10, INT(score/10)+1).
A10: 5. Risk Engine | B10: Rule-based regime state (calm, stressed, crisis), 12-month default PD from rating prior + scorecard + market spread + text index in log-odds, and PDs for transfer and convertibility, expropriation, political violence and sanctions.
A11: 6. Signals | B11: 21 macro and event signals scored 0-100 per country.
A12: 7. Playbook and Trade Activation | B12: 22 strategies, each tied to a signal, a minimum strength, an optional second condition and the instrument it needs. A trade fires where all three hold; its conviction is the signal strength.
A13: 8. Portfolio VaR and MC | B13: Sample book through a Student-t copula with global and regional factors (loadings rise with the regime), 2,000 scenarios with a fixed seed. Expected loss, VaR 95/99, expected shortfall and each country's share of the tail.
A14: 9. Dashboard | B14: One row per country: score, grade, regime, PDs, top signals, the highest-conviction trade and a suggested size.
A16: Cell colors
A17: Blue text | B17: Inputs you can change (data, flags, weights, thresholds, book).
A18: Green fill | B18: IMF WEO October 2026 values pulled on October 19, 2026 (each carries a source note).
A19: Black text | B19: Formulas. Do not overwrite; change the inputs that feed them.
A21: Connecting the data feeds
A22: Where each indicator comes from | B22: Rulebook column P names the API or dataset for every indicator (IMF DataMapper codes, World Bank WDI/IDS codes, V-Dem, WGI, ACLED, UCDP and so on). Write pulls into the matching Inputs row; nothing else needs to change.
A23: Market data | B23: Country Profile rows P10-P13 (rating, spread, FX and reserve changes) should come from a market data feed; they drive the regime state and the market-implied PD.
A24: Scenario selector | B24: Assumptions B74: Model, All stressed or All crisis. It moves every country's regime, PD and LGD multipliers and copula loadings.
A26: Known limits of this version
A27: Regime state | B27: A threshold rule on spreads, FX and reserves stands in for the layer 3 hidden Markov model.
A28: Default PD | B28: Rating priors and the scorecard weight are starting values; layer 1 hazard model and layer 2 weights are not fitted yet.
A29: Monte Carlo | B29: 2,000 scenarios in-sheet (the methodology targets 100,000+ in code). The pseudo-random draws come from a deterministic hash of the seed, so results repeat exactly.
A30: Methodology fixes applied | B30: Worst-indicator blend 0.2 on indicators weighted 10%+ (fix 1), reserve stress only for pegs and dollarized economies (fix 2), both conditions for the boom trigger (fix 5), peg break kept out of the scorecard stress (fix 8). Change them on Assumptions.
A31: Advanced economies | B31: Thresholds are set for emerging and frontier sovereigns, so Japan and Singapore score high on debt ratios that their asset positions offset.
A32: Momentum | B32: The momentum signal stays at 0 until a prior composite is pasted into Country Profile row P27.
A33: Text stress index | B33: Placeholder zeros until the layer 2 language-model index is built.

Sheet Dashboard
A1: Geopolitical-Macro Risk Desk
A2: {="Highest composite risk: "&INDEX(A6:A23,MATCH(MAX(D6:D23),D6:D23,0))&" ("&TEXT(MAX(D6:D23),"0.0")&"). Lowest: "&INDEX(A6:A23,MATCH(MIN(D6:D23),D6:D23,0))&" ("&TEXT(MIN(D6:D23),"0.0")&"). Countries in the crisis regime: "&COUNTIF(F6:F23,"Crisis")&" of 18."} -> Highest composite risk: Venezuela (84.5). Lowest: Singapore (21.6). Countries in the crisis regime: 3 of 18.
A3: ="Sample book: $"&TEXT('Portfolio VaR'!E18,"#,##0")&"mm exposure, expected loss $"&TEXT('Portfolio VaR'!E20,"0.0")&"mm, 99% VaR $"&TEXT('Portfolio VaR'!E22,"0.0")&"mm, 99% expected shortfall $"&TEXT('Portfolio VaR'!E24,"0.0")&"mm. Scenario override: "&Assumptions!B74&"." -> Sample book: $305mm exposure, expected loss $12.2mm, 99% VaR $44.8mm, 99% expected shortfall $56.4mm. Scenario override: Model.
A5: Country | B5: Column (helper) | C5: Region | D5: Composite score | E5: Grade | F5: Regime | G5: Rating | H5: Default PD (12m) | I5: Market-implied PD | J5: Any loss event PD | K5: Top three risk signals | L5: Trades firing | M5: Highest-conviction trade | N5: Conviction | O5: Suggested notional ($mm) | P5: All trades firing
A6: Vietnam | B6: =MATCH(A6,'Risk Engine'!$E$4:$V$4,0) -> 1 | C6: {=INDEX('Country Profile'!$E$6:$V$6,$B6)} -> Asia | D6: {=INDEX('Risk Engine'!$E$5:$V$5,$B6)} -> 29.120279 | E6: {=INDEX('Risk Engine'!$E$6:$V$6,$B6)} -> 3 | F6: {=INDEX('Risk Engine'!$E$8:$V$8,$B6)} -> Calm | G6: {=INDEX('Risk Engine'!$E$11:$V$11,$B6)} -> BB+ | H6: {=INDEX('Risk Engine'!$E$19:$V$19,$B6)} -> 0.0043255458 | I6: {=INDEX('Risk Engine'!$E$14:$V$14,$B6)} -> 0.016666667 | J6: {=INDEX('Risk Engine'!$E$29:$V$29,$B6)} -> 0.036404391 | K6: =IFERROR(__xludf.DUMMYFUNCTION("IFERROR(TEXTJOIN("", "",TRUE,SORTN(FILTER(Signals!$B$5:$B$22,INDEX(Signals!$E$5:$V$22,0,$B6)>=Assumptions!$B$65),3,0,FILTER(INDEX(Signals!$E$5:$V$22,0,$B6),INDEX(Signals!$E$5:$V$22,0,$B6)>=Assumptions!$B$65),FALSE)),""None above threshold"")"),"None above threshold") -> None above threshold | L6: {=COUNT(INDEX('Trade Activation'!$E$5:$V$26,0,$B6))} -> 1 | M6: {=IF(L6=0,"None",INDEX(Playbook!$B$5:$B$26,MATCH(MAX(INDEX('Trade Activation'!$E$5:$V$26,0,$B6)),INDEX('Trade Activation'!$E$5:$V$26,0,$B6),0)))} -> Overweight equities in low-risk calm markets | N6: {=MAX(INDEX('Trade Activation'!$E$5:$V$26,0,$B6))} -> 71 | O6: {=Assumptions!$B$68*N6/100*INDEX(Assumptions!$E$52:$E$54,MATCH(F6,Assumptions!$A$52:$A$54,0))} -> 7.1 | P6: =IFERROR(__xludf.DUMMYFUNCTION("IF(L6=0,"""",TEXTJOIN("", "",TRUE,FILTER(Playbook!$A$5:$A$26,INDEX('Trade Activation'!$E$5:$V$26,0,$B6)<>"""")))"),"T20") -> T20
A7: Philippines | B7: =MATCH(A7,'Risk Engine'!$E$4:$V$4,0) -> 2 | C7: {=INDEX('Country Profile'!$E$6:$V$6,$B7)} -> Asia | D7: {=INDEX('Risk Engine'!$E$5:$V$5,$B7)} -> 36.499095 | E7: {=INDEX('Risk Engine'!$E$6:$V$6,$B7)} -> 4 | F7: {=INDEX('Risk Engine'!$E$8:$V$8,$B7)} -> Calm | G7: {=INDEX('Risk Engine'!$E$11:$V$11,$B7)} -> BBB+ | H7: {=INDEX('Risk Engine'!$E$19:$V$19,$B7)} -> 0.002599347 | I7: {=INDEX('Risk Engine'!$E$14:$V$14,$B7)} -> 0.010833333 | J7: {=INDEX('Risk Engine'!$E$29:$V$29,$B7)} -> 0.02833332 | K7: =IFERROR(__xludf.DUMMYFUNCTION("IFERROR(TEXTJOIN("", "",TRUE,SORTN(FILTER(Signals!$B$5:$B$22,INDEX(Signals!$E$5:$V$22,0,$B7)>=Assumptions!$B$65),3,0,FILTER(INDEX(Signals!$E$5:$V$22,0,$B7),INDEX(Signals!$E$5:$V$22,0,$B7)>=Assumptions!$B$65),FALSE)),""None above threshold"")"),"Debt payment wall") -> Debt payment wall | L7: {=COUNT(INDEX('Trade Activation'!$E$5:$V$26,0,$B7))} -> 1 | M7: {=IF(L7=0,"None",INDEX(Playbook!$B$5:$B$26,MATCH(MAX(INDEX('Trade Activation'!$E$5:$V$26,0,$B7)),INDEX('Trade Activation'!$E$5:$V$26,0,$B7),0)))} -> FX carry in calm regimes | N7: {=MAX(INDEX('Trade Activation'!$E$5:$V$26,0,$B7))} -> 64 | O7: {=Assumptions!$B$68*N7/100*INDEX(Assumptions!$E$52:$E$54,MATCH(F7,Assumptions!$A$52:$A$54,0))} -> 6.4 | P7: =IFERROR(__xludf.DUMMYFUNCTION("IF(L7=0,"""",TEXTJOIN("", "",TRUE,FILTER(Playbook!$A$5:$A$26,INDEX('Trade Activation'!$E$5:$V$26,0,$B7)<>"""")))"),"T19") -> T19
A8: China | B8: =MATCH(A8,'Risk Engine'!$E$4:$V$4,0) -> 3 | C8: {=INDEX('Country Profile'!$E$6:$V$6,$B8)} -> Asia | D8: {=INDEX('Risk Engine'!$E$5:$V$5,$B8)} -> 40.318022 | E8: {=INDEX('Risk Engine'!$E$6:$V$6,$B8)} -> 5 | F8: {=INDEX('Risk Engine'!$E$8:$V$8,$B8)} -> Calm | G8: {=INDEX('Risk Engine'!$E$11:$V$11,$B8)} -> A+ | H8: {=INDEX('Risk Engine'!$E$19:$V$19,$B8)} -> 0.0018043773 | I8: {=INDEX('Risk Engine'!$E$14:$V$14,$B8)} -> 0.01 | J8: {=INDEX('Risk Engine'!$E$29:$V$29,$B8)} -> 0.037334729 | K8: =IFERROR(__xludf.DUMMYFUNCTION("IFERROR(TEXTJOIN("", "",TRUE,SORTN(FILTER(Signals!$B$5:$B$22,INDEX(Signals!$E$5:$V$22,0,$B8)>=Assumptions!$B$65),3,0,FILTER(INDEX(Signals!$E$5:$V$22,0,$B8),INDEX(Signals!$E$5:$V$22,0,$B8)>=Assumptions!$B$65),FALSE)),""None above threshold"")"),"Sanctions and geopolitics") -> Sanctions and geopolitics | L8: {=COUNT(INDEX('Trade Activation'!$E$5:$V$26,0,$B8))} -> 2 | M8: {=IF(L8=0,"None",INDEX(Playbook!$B$5:$B$26,MATCH(MAX(INDEX('Trade Activation'!$E$5:$V$26,0,$B8)),INDEX('Trade Activation'!$E$5:$V$26,0,$B8),0)))} -> Sanctions and tariff screen with safe-haven hedge | N8: {=MAX(INDEX('Trade Activation'!$E$5:$V$26,0,$B8))} -> 75 | O8: {=Assumptions!$B$68*N8/100*INDEX(Assumptions!$E$52:$E$54,MATCH(F8,Assumptions!$A$52:$A$54,0))} -> 7.5 | P8: =IFERROR(__xludf.DUMMYFUNCTION("IF(L8=0,"""",TEXTJOIN("", "",TRUE,FILTER(Playbook!$A$5:$A$26,INDEX('Trade Activation'!$E$5:$V$26,0,$B8)<>"""")))"),"T07, T15") -> T07, T15
A9: Malaysia | B9: =MATCH(A9,'Risk Engine'!$E$4:$V$4,0) -> 4 | C9: {=INDEX('Country Profile'!$E$6:$V$6,$B9)} -> Asia | D9: {=INDEX('Risk Engine'!$E$5:$V$5,$B9)} -> 30.992372 | E9: {=INDEX('Risk Engine'!$E$6:$V$6,$B9)} -> 4 | F9: {=INDEX('Risk Engine'!$E$8:$V$8,$B9)} -> Calm | G9: {=INDEX('Risk Engine'!$E$11:$V$11,$B9)} -> A- | H9: {=INDEX('Risk Engine'!$E$19:$V$19,$B9)} -> 0.0014427387 | I9: {=INDEX('Risk Engine'!$E$14:$V$14,$B9)} -> 0.0075 | J9: {=INDEX('Risk Engine'!$E$29:$V$29,$B9)} -> 0.020036742 | K9: =IFERROR(__xludf.DUMMYFUNCTION("IFERROR(TEXTJOIN("", "",TRUE,SORTN(FILTER(Signals!$B$5:$B$22,INDEX(Signals!$E$5:$V$22,0,$B9)>=Assumptions!$B$65),3,0,FILTER(INDEX(Signals!$E$5:$V$22,0,$B9),INDEX(Signals!$E$5:$V$22,0,$B9)>=Assumptions!$B$65),FALSE)),""None above threshold"")"),"None above threshold") -> None above threshold | L9: {=COUNT(INDEX('Trade Activation'!$E$5:$V$26,0,$B9))} -> 1 | M9: {=IF(L9=0,"None",INDEX(Playbook!$B$5:$B$26,MATCH(MAX(INDEX('Trade Activation'!$E$5:$V$26,0,$B9)),INDEX('Trade Activation'!$E$5:$V$26,0,$B9),0)))} -> Overweight equities in low-risk calm markets | N9: {=MAX(INDEX('Trade Activation'!$E$5:$V$26,0,$B9))} -> 69 | O9: {=Assumptions!$B$68*N9/100*INDEX(Assumptions!$E$52:$E$54,MATCH(F9,Assumptions!$A$52:$A$54,0))} -> 6.9 | P9: =IFERROR(__xludf.DUMMYFUNCTION("IF(L9=0,"""",TEXTJOIN("", "",TRUE,FILTER(Playbook!$A$5:$A$26,INDEX('Trade Activation'!$E$5:$V$26,0,$B9)<>"""")))"),"T20") -> T20
A10: Singapore | B10: =MATCH(A10,'Risk Engine'!$E$4:$V$4,0) -> 5 | C10: {=INDEX('Country Profile'!$E$6:$V$6,$B10)} -> Asia | D10: {=INDEX('Risk Engine'!$E$5:$V$5,$B10)} -> 21.569474 | E10: {=INDEX('Risk Engine'!$E$6:$V$6,$B10)} -> 3 | F10: {=INDEX('Risk Engine'!$E$8:$V$8,$B10)} -> Calm | G10: {=INDEX('Risk Engine'!$E$11:$V$11,$B10)} -> AAA | H10: {=INDEX('Risk Engine'!$E$19:$V$19,$B10)} -> 0.00019014843 | I10: {=INDEX('Risk Engine'!$E$14:$V$14,$B10)} -> 0.0025 | J10: {=INDEX('Risk Engine'!$E$29:$V$29,$B10)} -> 0.010216231 | K10: =IFERROR(__xludf.DUMMYFUNCTION("IFERROR(TEXTJOIN("", "",TRUE,SORTN(FILTER(Signals!$B$5:$B$22,INDEX(Signals!$E$5:$V$22,0,$B10)>=Assumptions!$B$65),3,0,FILTER(INDEX(Signals!$E$5:$V$22,0,$B10),INDEX(Signals!$E$5:$V$22,0,$B10)>=Assumptions!$B$65),FALSE)),""None above threshold"")"),"Growth slowdown") -> Growth slowdown | L10: {=COUNT(INDEX('Trade Activation'!$E$5:$V$26,0,$B10))} -> 2 | M10: {=IF(L10=0,"None",INDEX(Playbook!$B$5:$B$26,MATCH(MAX(INDEX('Trade Activation'!$E$5:$V$26,0,$B10)),INDEX('Trade Activation'!$E$5:$V$26,0,$B10),0)))} -> Overweight equities in low-risk calm markets | N10: {=MAX(INDEX('Trade Activation'!$E$5:$V$26,0,$B10))} -> 78 | O10: {=Assumptions!$B$68*N10/100*INDEX(Assumptions!$E$52:$E$54,MATCH(F10,Assumptions!$A$52:$A$54,0))} -> 7.8 | P10: =IFERROR(__xludf.DUMMYFUNCTION("IF(L10=0,"""",TEXTJOIN("", "",TRUE,FILTER(Playbook!$A$5:$A$26,INDEX('Trade Activation'!$E$5:$V$26,0,$B10)<>"""")))"),"T07, T20") -> T07, T20
A11: Japan | B11: =MATCH(A11,'Risk Engine'!$E$4:$V$4,0) -> 6 | C11: {=INDEX('Country Profile'!$E$6:$V$6,$B11)} -> Asia | D11: {=INDEX('Risk Engine'!$E$5:$V$5,$B11)} -> 23.857281 | E11: {=INDEX('Risk Engine'!$E$6:$V$6,$B11)} -> 3 | F11: {=INDEX('Risk Engine'!$E$8:$V$8,$B11)} -> Calm | G11: {=INDEX('Risk Engine'!$E$11:$V$11,$B11)} -> A+ | H11: {=INDEX('Risk Engine'!$E$19:$V$19,$B11)} -> 0.00053815523 | I11: {=INDEX('Risk Engine'!$E$14:$V$14,$B11)} -> 0.0033333333 | J11: {=INDEX('Risk Engine'!$E$29:$V$29,$B11)} -> 0.0096306509 | K11: =IFERROR(__xludf.DUMMYFUNCTION("IFERROR(TEXTJOIN("", "",TRUE,SORTN(FILTER(Signals!$B$5:$B$22,INDEX(Signals!$E$5:$V$22,0,$B11)>=Assumptions!$B$65),3,0,FILTER(INDEX(Signals!$E$5:$V$22,0,$B11),INDEX(Signals!$E$5:$V$22,0,$B11)>=Assumptions!$B$65),FALSE)),""None above threshold"")"),"Growth slowdown") -> Growth slowdown | L11: {=COUNT(INDEX('Trade Activation'!$E$5:$V$26,0,$B11))} -> 2 | M11: {=IF(L11=0,"None",INDEX(Playbook!$B$5:$B$26,MATCH(MAX(INDEX('Trade Activation'!$E$5:$V$26,0,$B11)),INDEX('Trade Activation'!$E$5:$V$26,0,$B11),0)))} -> Receive local duration on a growth slowdown | N11: {=MAX(INDEX('Trade Activation'!$E$5:$V$26,0,$B11))} -> 93 | O11: {=Assumptions!$B$68*N11/100*INDEX(Assumptions!$E$52:$E$54,MATCH(F11,Assumptions!$A$52:$A$54,0))} -> 9.3 | P11: =IFERROR(__xludf.DUMMYFUNCTION("IF(L11=0,"""",TEXTJOIN("", "",TRUE,FILTER(Playbook!$A$5:$A$26,INDEX('Trade Activation'!$E$5:$V$26,0,$B11)<>"""")))"),"T07, T20") -> T07, T20
A12: South Korea | B12: =MATCH(A12,'Risk Engine'!$E$4:$V$4,0) -> 7 | C12: {=INDEX('Country Profile'!$E$6:$V$6,$B12)} -> Asia | D12: {=INDEX('Risk Engine'!$E$5:$V$5,$B12)} -> 21.968328 | E12: {=INDEX('Risk Engine'!$E$6:$V$6,$B12)} -> 3 | F12: {=INDEX('Risk Engine'!$E$8:$V$8,$B12)} -> Calm | G12: {=INDEX('Risk Engine'!$E$11:$V$11,$B12)} -> AA | H12: {=INDEX('Risk Engine'!$E$19:$V$19,$B12)} -> 0.00043232257 | I12: {=INDEX('Risk Engine'!$E$14:$V$14,$B12)} -> 0.0041666667 | J12: {=INDEX('Risk Engine'!$E$29:$V$29,$B12)} -> 0.014902246 | K12: =IFERROR(__xludf.DUMMYFUNCTION("IFERROR(TEXTJOIN("", "",TRUE,SORTN(FILTER(Signals!$B$5:$B$22,INDEX(Signals!$E$5:$V$22,0,$B12)>=Assumptions!$B$65),3,0,FILTER(INDEX(Signals!$E$5:$V$22,0,$B12),INDEX(Signals!$E$5:$V$22,0,$B12)>=Assumptions!$B$65),FALSE)),""None above threshold"")"),"Growth slowdown") -> Growth slowdown | L12: {=COUNT(INDEX('Trade Activation'!$E$5:$V$26,0,$B12))} -> 2 | M12: {=IF(L12=0,"None",INDEX(Playbook!$B$5:$B$26,MATCH(MAX(INDEX('Trade Activation'!$E$5:$V$26,0,$B12)),INDEX('Trade Activation'!$E$5:$V$26,0,$B12),0)))} -> Overweight equities in low-risk calm markets | N12: {=MAX(INDEX('Trade Activation'!$E$5:$V$26,0,$B12))} -> 78 | O12: {=Assumptions!$B$68*N12/100*INDEX(Assumptions!$E$52:$E$54,MATCH(F12,Assumptions!$A$52:$A$54,0))} -> 7.8 | P12: =IFERROR(__xludf.DUMMYFUNCTION("IF(L12=0,"""",TEXTJOIN("", "",TRUE,FILTER(Playbook!$A$5:$A$26,INDEX('Trade Activation'!$E$5:$V$26,0,$B12)<>"""")))"),"T07, T20") -> T07, T20
A13: India | B13: =MATCH(A13,'Risk Engine'!$E$4:$V$4,0) -> 8 | C13: {=INDEX('Country Profile'!$E$6:$V$6,$B13)} -> Asia | D13: {=INDEX('Risk Engine'!$E$5:$V$5,$B13)} -> 36.361175 | E13: {=INDEX('Risk Engine'!$E$6:$V$6,$B13)} -> 4 | F13: {=INDEX('Risk Engine'!$E$8:$V$8,$B13)} -> Calm | G13: {=INDEX('Risk Engine'!$E$11:$V$11,$B13)} -> BBB | H13: {=INDEX('Risk Engine'!$E$19:$V$19,$B13)} -> 0.0032433872 | I13: {=INDEX('Risk Engine'!$E$14:$V$14,$B13)} -> 0.011666667 | J13: {=INDEX('Risk Engine'!$E$29:$V$29,$B13)} -> 0.030951389 | K13: =IFERROR(__xludf.DUMMYFUNCTION("IFERROR(TEXTJOIN("", "",TRUE,SORTN(FILTER(Signals!$B$5:$B$22,INDEX(Signals!$E$5:$V$22,0,$B13)>=Assumptions!$B$65),3,0,FILTER(INDEX(Signals!$E$5:$V$22,0,$B13),INDEX(Signals!$E$5:$V$22,0,$B13)>=Assumptions!$B$65),FALSE)),""None above threshold"")"),"Debt payment wall, Sanctions and geopolitics") -> Debt payment wall, Sanctions and geopolitics | L13: {=COUNT(INDEX('Trade Activation'!$E$5:$V$26,0,$B13))} -> 3 | M13: {=IF(L13=0,"None",INDEX(Playbook!$B$5:$B$26,MATCH(MAX(INDEX('Trade Activation'!$E$5:$V$26,0,$B13)),INDEX('Trade Activation'!$E$5:$V$26,0,$B13),0)))} -> Sanctions and tariff screen with safe-haven hedge | N13: {=MAX(INDEX('Trade Activation'!$E$5:$V$26,0,$B13))} -> 75 | O13: {=Assumptions!$B$68*N13/100*INDEX(Assumptions!$E$52:$E$54,MATCH(F13,Assumptions!$A$52:$A$54,0))} -> 7.5 | P13: =IFERROR(__xludf.DUMMYFUNCTION("IF(L13=0,"""",TEXTJOIN("", "",TRUE,FILTER(Playbook!$A$5:$A$26,INDEX('Trade Activation'!$E$5:$V$26,0,$B13)<>"""")))"),"T15, T19, T20") -> T15, T19, T20
A14: Pakistan | B14: =MATCH(A14,'Risk Engine'!$E$4:$V$4,0) -> 9 | C14: {=INDEX('Country Profile'!$E$6:$V$6,$B14)} -> Asia | D14: {=INDEX('Risk Engine'!$E$5:$V$5,$B14)} -> 66.910129 | E14: {=INDEX('Risk Engine'!$E$6:$V$6,$B14)} -> 7 | F14: {=INDEX('Risk Engine'!$E$8:$V$8,$B14)} -> Stressed | G14: {=INDEX('Risk Engine'!$E$11:$V$11,$B14)} -> B- | H14: {=INDEX('Risk Engine'!$E$19:$V$19,$B14)} -> 0.16510446 | I14: {=INDEX('Risk Engine'!$E$14:$V$14,$B14)} -> 0.075 | J14: {=INDEX('Risk Engine'!$E$29:$V$29,$B14)} -> 0.29463078 | K14: =IFERROR(__xludf.DUMMYFUNCTION("IFERROR(TEXTJOIN("", "",TRUE,SORTN(FILTER(Signals!$B$5:$B$22,INDEX(Signals!$E$5:$V$22,0,$B14)>=Assumptions!$B$65),3,0,FILTER(INDEX(Signals!$E$5:$V$22,0,$B14),INDEX(Signals!$E$5:$V$22,0,$B14)>=Assumptions!$B$65),FALSE)),""None above threshold"")"),"Debt payment wall, Market complacency, Security and violence") -> Debt payment wall, Market complacency, Security and violence | L14: {=COUNT(INDEX('Trade Activation'!$E$5:$V$26,0,$B14))} -> 9 | M14: {=IF(L14=0,"None",INDEX(Playbook!$B$5:$B$26,MATCH(MAX(INDEX('Trade Activation'!$E$5:$V$26,0,$B14)),INDEX('Trade Activation'!$E$5:$V$26,0,$B14),0)))} -> CDS curve flattener into a payment wall | N14: {=MAX(INDEX('Trade Activation'!$E$5:$V$26,0,$B14))} -> 100 | O14: {=Assumptions!$B$68*N14/100*INDEX(Assumptions!$E$52:$E$54,MATCH(F14,Assumptions!$A$52:$A$54,0))} -> 7.5 | P14: =IFERROR(__xludf.DUMMYFUNCTION("IF(L14=0,"""",TEXTJOIN("", "",TRUE,FILTER(Playbook!$A$5:$A$26,INDEX('Trade Activation'!$E$5:$V$26,0,$B14)<>"""")))"),"T01, T02, T03, T11, T12, T14, T15, T16, T22") -> T01, T02, T03, T11, T12, T14, T15, T16, T22
A15: Belize | B15: =MATCH(A15,'Risk Engine'!$E$4:$V$4,0) -> 10 | C15: {=INDEX('Country Profile'!$E$6:$V$6,$B15)} -> LatAm | D15: {=INDEX('Risk Engine'!$E$5:$V$5,$B15)} -> 48.850579 | E15: {=INDEX('Risk Engine'!$E$6:$V$6,$B15)} -> 5 | F15: {=INDEX('Risk Engine'!$E$8:$V$8,$B15)} -> Stressed | G15: {=INDEX('Risk Engine'!$E$11:$V$11,$B15)} -> B- | H15: {=INDEX('Risk Engine'!$E$19:$V$19,$B15)} -> 0.10369648 | I15: {=INDEX('Risk Engine'!$E$14:$V$14,$B15)} -> 0.10833333 | J15: {=INDEX('Risk Engine'!$E$29:$V$29,$B15)} -> 0.16635742 | K15: =IFERROR(__xludf.DUMMYFUNCTION("IFERROR(TEXTJOIN("", "",TRUE,SORTN(FILTER(Signals!$B$5:$B$22,INDEX(Signals!$E$5:$V$22,0,$B15)>=Assumptions!$B$65),3,0,FILTER(INDEX(Signals!$E$5:$V$22,0,$B15),INDEX(Signals!$E$5:$V$22,0,$B15)>=Assumptions!$B$65),FALSE)),""None above threshold"")"),"Growth slowdown, Climate and disaster, Expropriation and contract risk") -> Growth slowdown, Climate and disaster, Expropriation and contract risk | L15: {=COUNT(INDEX('Trade Activation'!$E$5:$V$26,0,$B15))} -> 2 | M15: {=IF(L15=0,"None",INDEX(Playbook!$B$5:$B$26,MATCH(MAX(INDEX('Trade Activation'!$E$5:$V$26,0,$B15)),INDEX('Trade Activation'!$E$5:$V$26,0,$B15),0)))} -> Pre-season climate and disaster hedge | N15: {=MAX(INDEX('Trade Activation'!$E$5:$V$26,0,$B15))} -> 70 | O15: {=Assumptions!$B$68*N15/100*INDEX(Assumptions!$E$52:$E$54,MATCH(F15,Assumptions!$A$52:$A$54,0))} -> 5.25 | P15: =IFERROR(__xludf.DUMMYFUNCTION("IF(L15=0,"""",TEXTJOIN("", "",TRUE,FILTER(Playbook!$A$5:$A$26,INDEX('Trade Activation'!$E$5:$V$26,0,$B15)<>"""")))"),"T11, T14") -> T11, T14
A16: Brazil | B16: =MATCH(A16,'Risk Engine'!$E$4:$V$4,0) -> 11 | C16: {=INDEX('Country Profile'!$E$6:$V$6,$B16)} -> LatAm | D16: {=INDEX('Risk Engine'!$E$5:$V$5,$B16)} -> 42.978174 | E16: {=INDEX('Risk Engine'!$E$6:$V$6,$B16)} -> 5 | F16: {=INDEX('Risk Engine'!$E$8:$V$8,$B16)} -> Calm | G16: {=INDEX('Risk Engine'!$E$11:$V$11,$B16)} -> BB | H16: {=INDEX('Risk Engine'!$E$19:$V$19,$B16)} -> 0.011833244 | I16: {=INDEX('Risk Engine'!$E$14:$V$14,$B16)} -> 0.026666667 | J16: {=INDEX('Risk Engine'!$E$29:$V$29,$B16)} -> 0.046446681 | K16: =IFERROR(__xludf.DUMMYFUNCTION("IFERROR(TEXTJOIN("", "",TRUE,SORTN(FILTER(Signals!$B$5:$B$22,INDEX(Signals!$E$5:$V$22,0,$B16)>=Assumptions!$B$65),3,0,FILTER(INDEX(Signals!$E$5:$V$22,0,$B16),INDEX(Signals!$E$5:$V$22,0,$B16)>=Assumptions!$B$65),FALSE)),""None above threshold"")"),"Growth slowdown, Sanctions and geopolitics, Debt payment wall") -> Growth slowdown, Sanctions and geopolitics, Debt payment wall | L16: {=COUNT(INDEX('Trade Activation'!$E$5:$V$26,0,$B16))} -> 5 | M16: {=IF(L16=0,"None",INDEX(Playbook!$B$5:$B$26,MATCH(MAX(INDEX('Trade Activation'!$E$5:$V$26,0,$B16)),INDEX('Trade Activation'!$E$5:$V$26,0,$B16),0)))} -> Sell protection or buy bonds where spreads overprice risk | N16: {=MAX(INDEX('Trade Activation'!$E$5:$V$26,0,$B16))} -> 100 | O16: {=Assumptions!$B$68*N16/100*INDEX(Assumptions!$E$52:$E$54,MATCH(F16,Assumptions!$A$52:$A$54,0))} -> 10 | P16: =IFERROR(__xludf.DUMMYFUNCTION("IF(L16=0,"""",TEXTJOIN("", "",TRUE,FILTER(Playbook!$A$5:$A$26,INDEX('Trade Activation'!$E$5:$V$26,0,$B16)<>"""")))"),"T06, T09, T15, T17, T19") -> T06, T09, T15, T17, T19
A17: Argentina | B17: =MATCH(A17,'Risk Engine'!$E$4:$V$4,0) -> 12 | C17: {=INDEX('Country Profile'!$E$6:$V$6,$B17)} -> LatAm | D17: {=INDEX('Risk Engine'!$E$5:$V$5,$B17)} -> 56.432417 | E17: {=INDEX('Risk Engine'!$E$6:$V$6,$B17)} -> 6 | F17: {=INDEX('Risk Engine'!$E$8:$V$8,$B17)} -> Stressed | G17: {=INDEX('Risk Engine'!$E$11:$V$11,$B17)} -> B- | H17: {=INDEX('Risk Engine'!$E$19:$V$19,$B17)} -> 0.13642498 | I17: {=INDEX('Risk Engine'!$E$14:$V$14,$B17)} -> 0.10833333 | J17: {=INDEX('Risk Engine'!$E$29:$V$29,$B17)} -> 0.23185988 | K17: =IFERROR(__xludf.DUMMYFUNCTION("IFERROR(TEXTJOIN("", "",TRUE,SORTN(FILTER(Signals!$B$5:$B$22,INDEX(Signals!$E$5:$V$22,0,$B17)>=Assumptions!$B$65),3,0,FILTER(INDEX(Signals!$E$5:$V$22,0,$B17),INDEX(Signals!$E$5:$V$22,0,$B17)>=Assumptions!$B$65),FALSE)),""None above threshold"")"),"Inflation pressure, Debt payment wall, Devaluation pressure") -> Inflation pressure, Debt payment wall, Devaluation pressure | L17: {=COUNT(INDEX('Trade Activation'!$E$5:$V$26,0,$B17))} -> 6 | M17: {=IF(L17=0,"None",INDEX(Playbook!$B$5:$B$26,MATCH(MAX(INDEX('Trade Activation'!$E$5:$V$26,0,$B17)),INDEX('Trade Activation'!$E$5:$V$26,0,$B17),0)))} -> Pay short-dated local rates | N17: {=MAX(INDEX('Trade Activation'!$E$5:$V$26,0,$B17))} -> 96 | O17: {=Assumptions!$B$68*N17/100*INDEX(Assumptions!$E$52:$E$54,MATCH(F17,Assumptions!$A$52:$A$54,0))} -> 7.2 | P17: =IFERROR(__xludf.DUMMYFUNCTION("IF(L17=0,"""",TEXTJOIN("", "",TRUE,FILTER(Playbook!$A$5:$A$26,INDEX('Trade Activation'!$E$5:$V$26,0,$B17)<>"""")))"),"T01, T02, T03, T04, T06, T22") -> T01, T02, T03, T04, T06, T22
A18: Colombia | B18: =MATCH(A18,'Risk Engine'!$E$4:$V$4,0) -> 13 | C18: {=INDEX('Country Profile'!$E$6:$V$6,$B18)} -> LatAm | D18: {=INDEX('Risk Engine'!$E$5:$V$5,$B18)} -> 40.737128 | E18: {=INDEX('Risk Engine'!$E$6:$V$6,$B18)} -> 5 | F18: {=INDEX('Risk Engine'!$E$8:$V$8,$B18)} -> Calm | G18: {=INDEX('Risk Engine'!$E$11:$V$11,$B18)} -> BB | H18: {=INDEX('Risk Engine'!$E$19:$V$19,$B18)} -> 0.012739959 | I18: {=INDEX('Risk Engine'!$E$14:$V$14,$B18)} -> 0.036666667 | J18: {=INDEX('Risk Engine'!$E$29:$V$29,$B18)} -> 0.050629163 | K18: =IFERROR(__xludf.DUMMYFUNCTION("IFERROR(TEXTJOIN("", "",TRUE,SORTN(FILTER(Signals!$B$5:$B$22,INDEX(Signals!$E$5:$V$22,0,$B18)>=Assumptions!$B$65),3,0,FILTER(INDEX(Signals!$E$5:$V$22,0,$B18),INDEX(Signals!$E$5:$V$22,0,$B18)>=Assumptions!$B$65),FALSE)),""None above threshold"")"),"Growth slowdown, Security and violence") -> Growth slowdown, Security and violence | L18: {=COUNT(INDEX('Trade Activation'!$E$5:$V$26,0,$B18))} -> 4 | M18: {=IF(L18=0,"None",INDEX(Playbook!$B$5:$B$26,MATCH(MAX(INDEX('Trade Activation'!$E$5:$V$26,0,$B18)),INDEX('Trade Activation'!$E$5:$V$26,0,$B18),0)))} -> Sell protection or buy bonds where spreads overprice risk | N18: {=MAX(INDEX('Trade Activation'!$E$5:$V$26,0,$B18))} -> 100 | O18: {=Assumptions!$B$68*N18/100*INDEX(Assumptions!$E$52:$E$54,MATCH(F18,Assumptions!$A$52:$A$54,0))} -> 10 | P18: =IFERROR(__xludf.DUMMYFUNCTION("IF(L18=0,"""",TEXTJOIN("", "",TRUE,FILTER(Playbook!$A$5:$A$26,INDEX('Trade Activation'!$E$5:$V$26,0,$B18)<>"""")))"),"T06, T12, T17, T19") -> T06, T12, T17, T19
A19: Venezuela | B19: =MATCH(A19,'Risk Engine'!$E$4:$V$4,0) -> 14 | C19: {=INDEX('Country Profile'!$E$6:$V$6,$B19)} -> LatAm | D19: {=INDEX('Risk Engine'!$E$5:$V$5,$B19)} -> 84.483114 | E19: {=INDEX('Risk Engine'!$E$6:$V$6,$B19)} -> 9 | F19: {=INDEX('Risk Engine'!$E$8:$V$8,$B19)} -> Crisis | G19: {=INDEX('Risk Engine'!$E$11:$V$11,$B19)} -> SD | H19: {=INDEX('Risk Engine'!$E$19:$V$19,$B19)} -> 0.99 | I19: {=INDEX('Risk Engine'!$E$14:$V$14,$B19)} -> 0.95 | J19: {=INDEX('Risk Engine'!$E$29:$V$29,$B19)} -> 0.99471269 | K19: =IFERROR(__xludf.DUMMYFUNCTION("IFERROR(TEXTJOIN("", "",TRUE,SORTN(FILTER(Signals!$B$5:$B$22,INDEX(Signals!$E$5:$V$22,0,$B19)>=Assumptions!$B$65),3,0,FILTER(INDEX(Signals!$E$5:$V$22,0,$B19),INDEX(Signals!$E$5:$V$22,0,$B19)>=Assumptions!$B$65),FALSE)),""None above threshold"")"),"Debt payment wall, Devaluation pressure, Inflation pressure") -> Debt payment wall, Devaluation pressure, Inflation pressure | L19: {=COUNT(INDEX('Trade Activation'!$E$5:$V$26,0,$B19))} -> 6 | M19: {=IF(L19=0,"None",INDEX(Playbook!$B$5:$B$26,MATCH(MAX(INDEX('Trade Activation'!$E$5:$V$26,0,$B19)),INDEX('Trade Activation'!$E$5:$V$26,0,$B19),0)))} -> Commodity-linked downside hedge | N19: {=MAX(INDEX('Trade Activation'!$E$5:$V$26,0,$B19))} -> 100 | O19: {=Assumptions!$B$68*N19/100*INDEX(Assumptions!$E$52:$E$54,MATCH(F19,Assumptions!$A$52:$A$54,0))} -> 5 | P19: =IFERROR(__xludf.DUMMYFUNCTION("IF(L19=0,"""",TEXTJOIN("", "",TRUE,FILTER(Playbook!$A$5:$A$26,INDEX('Trade Activation'!$E$5:$V$26,0,$B19)<>"""")))"),"T03, T11, T13, T15, T18, T22") -> T03, T11, T13, T15, T18, T22
A20: Nigeria | B20: =MATCH(A20,'Risk Engine'!$E$4:$V$4,0) -> 15 | C20: {=INDEX('Country Profile'!$E$6:$V$6,$B20)} -> Africa | D20: {=INDEX('Risk Engine'!$E$5:$V$5,$B20)} -> 58.853407 | E20: {=INDEX('Risk Engine'!$E$6:$V$6,$B20)} -> 6 | F20: {=INDEX('Risk Engine'!$E$8:$V$8,$B20)} -> Stressed | G20: {=INDEX('Risk Engine'!$E$11:$V$11,$B20)} -> B | H20: {=INDEX('Risk Engine'!$E$19:$V$19,$B20)} -> 0.09187444 | I20: {=INDEX('Risk Engine'!$E$14:$V$14,$B20)} -> 0.066666667 | J20: {=INDEX('Risk Engine'!$E$29:$V$29,$B20)} -> 0.18556769 | K20: =IFERROR(__xludf.DUMMYFUNCTION("IFERROR(TEXTJOIN("", "",TRUE,SORTN(FILTER(Signals!$B$5:$B$22,INDEX(Signals!$E$5:$V$22,0,$B20)>=Assumptions!$B$65),3,0,FILTER(INDEX(Signals!$E$5:$V$22,0,$B20),INDEX(Signals!$E$5:$V$22,0,$B20)>=Assumptions!$B$65),FALSE)),""None above threshold"")"),"Debt payment wall, Commodity dependence, Inflation pressure") -> Debt payment wall, Commodity dependence, Inflation pressure | L20: {=COUNT(INDEX('Trade Activation'!$E$5:$V$26,0,$B20))} -> 7 | M20: {=IF(L20=0,"None",INDEX(Playbook!$B$5:$B$26,MATCH(MAX(INDEX('Trade Activation'!$E$5:$V$26,0,$B20)),INDEX('Trade Activation'!$E$5:$V$26,0,$B20),0)))} -> CDS curve flattener into a payment wall | N20: {=MAX(INDEX('Trade Activation'!$E$5:$V$26,0,$B20))} -> 100 | O20: {=Assumptions!$B$68*N20/100*INDEX(Assumptions!$E$52:$E$54,MATCH(F20,Assumptions!$A$52:$A$54,0))} -> 7.5 | P20: =IFERROR(__xludf.DUMMYFUNCTION("IF(L20=0,"""",TEXTJOIN("", "",TRUE,FILTER(Playbook!$A$5:$A$26,INDEX('Trade Activation'!$E$5:$V$26,0,$B20)<>"""")))"),"T01, T02, T06, T11, T12, T13, T16") -> T01, T02, T06, T11, T12, T13, T16
A21: Senegal | B21: =MATCH(A21,'Risk Engine'!$E$4:$V$4,0) -> 16 | C21: {=INDEX('Country Profile'!$E$6:$V$6,$B21)} -> Africa | D21: {=INDEX('Risk Engine'!$E$5:$V$5,$B21)} -> 56.4525 | E21: {=INDEX('Risk Engine'!$E$6:$V$6,$B21)} -> 6 | F21: {=INDEX('Risk Engine'!$E$8:$V$8,$B21)} -> Crisis | G21: {=INDEX('Risk Engine'!$E$11:$V$11,$B21)} -> CCC+ | H21: {=INDEX('Risk Engine'!$E$19:$V$19,$B21)} -> 0.35301985 | I21: {=INDEX('Risk Engine'!$E$14:$V$14,$B21)} -> 0.2 | J21: {=INDEX('Risk Engine'!$E$29:$V$29,$B21)} -> 0.42619828 | K21: =IFERROR(__xludf.DUMMYFUNCTION("IFERROR(TEXTJOIN("", "",TRUE,SORTN(FILTER(Signals!$B$5:$B$22,INDEX(Signals!$E$5:$V$22,0,$B21)>=Assumptions!$B$65),3,0,FILTER(INDEX(Signals!$E$5:$V$22,0,$B21),INDEX(Signals!$E$5:$V$22,0,$B21)>=Assumptions!$B$65),FALSE)),""None above threshold"")"),"Distress and restructuring, Official backstop stress, Market complacency") -> Distress and restructuring, Official backstop stress, Market complacency | L21: {=COUNT(INDEX('Trade Activation'!$E$5:$V$26,0,$B21))} -> 4 | M21: {=IF(L21=0,"None",INDEX(Playbook!$B$5:$B$26,MATCH(MAX(INDEX('Trade Activation'!$E$5:$V$26,0,$B21)),INDEX('Trade Activation'!$E$5:$V$26,0,$B21),0)))} -> Distressed recovery trade | N21: {=MAX(INDEX('Trade Activation'!$E$5:$V$26,0,$B21))} -> 100 | O21: {=Assumptions!$B$68*N21/100*INDEX(Assumptions!$E$52:$E$54,MATCH(F21,Assumptions!$A$52:$A$54,0))} -> 5 | P21: =IFERROR(__xludf.DUMMYFUNCTION("IF(L21=0,"""",TEXTJOIN("", "",TRUE,FILTER(Playbook!$A$5:$A$26,INDEX('Trade Activation'!$E$5:$V$26,0,$B21)<>"""")))"),"T03, T11, T18, T22") -> T03, T11, T18, T22
A22: Zambia | B22: =MATCH(A22,'Risk Engine'!$E$4:$V$4,0) -> 17 | C22: {=INDEX('Country Profile'!$E$6:$V$6,$B22)} -> Africa | D22: {=INDEX('Risk Engine'!$E$5:$V$5,$B22)} -> 52.46386 | E22: {=INDEX('Risk Engine'!$E$6:$V$6,$B22)} -> 6 | F22: {=INDEX('Risk Engine'!$E$8:$V$8,$B22)} -> Stressed | G22: {=INDEX('Risk Engine'!$E$11:$V$11,$B22)} -> CCC+ | H22: {=INDEX('Risk Engine'!$E$19:$V$19,$B22)} -> 0.15104901 | I22: {=INDEX('Risk Engine'!$E$14:$V$14,$B22)} -> 0.075 | J22: {=INDEX('Risk Engine'!$E$29:$V$29,$B22)} -> 0.20388021 | K22: =IFERROR(__xludf.DUMMYFUNCTION("IFERROR(TEXTJOIN("", "",TRUE,SORTN(FILTER(Signals!$B$5:$B$22,INDEX(Signals!$E$5:$V$22,0,$B22)>=Assumptions!$B$65),3,0,FILTER(INDEX(Signals!$E$5:$V$22,0,$B22),INDEX(Signals!$E$5:$V$22,0,$B22)>=Assumptions!$B$65),FALSE)),""None above threshold"")"),"Market complacency, Distress and restructuring, Commodity dependence") -> Market complacency, Distress and restructuring, Commodity dependence | L22: {=COUNT(INDEX('Trade Activation'!$E$5:$V$26,0,$B22))} -> 4 | M22: {=IF(L22=0,"None",INDEX(Playbook!$B$5:$B$26,MATCH(MAX(INDEX('Trade Activation'!$E$5:$V$26,0,$B22)),INDEX('Trade Activation'!$E$5:$V$26,0,$B22),0)))} -> Distressed recovery trade | N22: {=MAX(INDEX('Trade Activation'!$E$5:$V$26,0,$B22))} -> 100 | O22: {=Assumptions!$B$68*N22/100*INDEX(Assumptions!$E$52:$E$54,MATCH(F22,Assumptions!$A$52:$A$54,0))} -> 7.5 | P22: =IFERROR(__xludf.DUMMYFUNCTION("IF(L22=0,"""",TEXTJOIN("", "",TRUE,FILTER(Playbook!$A$5:$A$26,INDEX('Trade Activation'!$E$5:$V$26,0,$B22)<>"""")))"),"T06, T11, T13, T18") -> T06, T11, T13, T18
A23: Zimbabwe | B23: =MATCH(A23,'Risk Engine'!$E$4:$V$4,0) -> 18 | C23: {=INDEX('Country Profile'!$E$6:$V$6,$B23)} -> Africa | D23: {=INDEX('Risk Engine'!$E$5:$V$5,$B23)} -> 74.964737 | E23: {=INDEX('Risk Engine'!$E$6:$V$6,$B23)} -> 8 | F23: {=INDEX('Risk Engine'!$E$8:$V$8,$B23)} -> Crisis | G23: {=INDEX('Risk Engine'!$E$11:$V$11,$B23)} -> SD | H23: {=INDEX('Risk Engine'!$E$19:$V$19,$B23)} -> 0.99 | I23: {=INDEX('Risk Engine'!$E$14:$V$14,$B23)} -> 0.5 | J23: {=INDEX('Risk Engine'!$E$29:$V$29,$B23)} -> 0.9931702 | K23: =IFERROR(__xludf.DUMMYFUNCTION("IFERROR(TEXTJOIN("", "",TRUE,SORTN(FILTER(Signals!$B$5:$B$22,INDEX(Signals!$E$5:$V$22,0,$B23)>=Assumptions!$B$65),3,0,FILTER(INDEX(Signals!$E$5:$V$22,0,$B23),INDEX(Signals!$E$5:$V$22,0,$B23)>=Assumptions!$B$65),FALSE)),""None above threshold"")"),"Debt payment wall, Distress and restructuring, Market complacency") -> Debt payment wall, Distress and restructuring, Market complacency | L23: {=COUNT(INDEX('Trade Activation'!$E$5:$V$26,0,$B23))} -> 3 | M23: {=IF(L23=0,"None",INDEX(Playbook!$B$5:$B$26,MATCH(MAX(INDEX('Trade Activation'!$E$5:$V$26,0,$B23)),INDEX('Trade Activation'!$E$5:$V$26,0,$B23),0)))} -> Political risk insurance and concession underweight | N23: {=MAX(INDEX('Trade Activation'!$E$5:$V$26,0,$B23))} -> 90 | O23: {=Assumptions!$B$68*N23/100*INDEX(Assumptions!$E$52:$E$54,MATCH(F23,Assumptions!$A$52:$A$54,0))} -> 4.5 | P23: =IFERROR(__xludf.DUMMYFUNCTION("IF(L23=0,"""",TEXTJOIN("", "",TRUE,FILTER(Playbook!$A$5:$A$26,INDEX('Trade Activation'!$E$5:$V$26,0,$B23)<>"""")))"),"T11, T14, T15") -> T11, T14, T15

Sheet Assumptions
A1: Assumptions
A2: Blue cells are inputs. Values marked 'starting value' are first guesses to be fitted in the backtest.
A3: Scorecard aggregation | B3: Value | C3: Unit | D3: Source
A4: Worst-indicator blend weight | B4: 0.2 | C4: share | D4: Methodology fix 1 (base rule is 0.3)
A5: Minimum indicator weight for the worst-indicator term | B5: 0.1 | C5: weight in pillar | D5: Methodology fix 1 (base rule is 0)
A6: Maximum analyst adjustment | B6: 10 | C6: points | D6: Methodology rulebook
A7: Trigger add-on cap, pillars 3 and 4 | B7: 15 | C7: points | D7: Methodology rulebook
A8: Trigger add-on cap, pillar 7 | B8: 10 | C8: points | D8: Methodology rulebook
A9: Small-state test: population below | B9: 1.5 | C9: millions | D9: Methodology rulebook
A10: Small-state test: 1-in-100-year loss at or above | B10: 25 | C10: % of GDP | D10: Methodology rulebook
A11: Small-state climate pillar weight | B11: 0.15 | C11: weight | D11: Methodology rulebook
A13: Pillar | B13: Name | C13: Standard weight | D13: Small-state weight
A14: 1 | B14: Fiscal and debt | C14: 0.25 | D14: =IF(A14=7,$B$11,C14*(1-$B$11)/(1-$C$20)) -> 0.22368421
A15: 2 | B15: External | C15: 0.2 | D15: =IF(A15=7,$B$11,C15*(1-$B$11)/(1-$C$20)) -> 0.17894737
A16: 3 | B16: Institutions and governance | C16: 0.15 | D16: =IF(A16=7,$B$11,C16*(1-$B$11)/(1-$C$20)) -> 0.13421053
A17: 4 | B17: Political and policy | C17: 0.15 | D17: =IF(A17=7,$B$11,C17*(1-$B$11)/(1-$C$20)) -> 0.13421053
A18: 5 | B18: Macro and financial | C18: 0.1 | D18: =IF(A18=7,$B$11,C18*(1-$B$11)/(1-$C$20)) -> 0.089473684
A19: 6 | B19: Security and social | C19: 0.1 | D19: =IF(A19=7,$B$11,C19*(1-$B$11)/(1-$C$20)) -> 0.089473684
A20: 7 | B20: Climate and disaster | C20: 0.05 | D20: =IF(A20=7,$B$11,C20*(1-$B$11)/(1-$C$20)) -> 0.15
A21: Total | C21: =SUM(C14:C20) -> 1 | D21: =SUM(D14:D20) -> 1
A23: Stress path | B23: Value | C23: Unit | D23: Source
A24: Stress depreciation, floating currency | B24: 20 | C24: % | D24: Starting value
A25: Stress depreciation, managed float | B25: 15 | C25: % | D25: Starting value
A26: Stress depreciation, peg or dollarized | B26: 0 | C26: % (peg break sits in the Monte Carlo, per methodology fix) | D26: Methodology fix
A27: Growth shock | B27: -2 | C27: pp | D27: Starting value
A28: Interest rate shock | B28: 2 | C28: pp | D28: Starting value
A29: Share of debt repricing within a year | B29: 0.25 | C29: share | D29: Starting value
A30: Primary balance loss per 1pp of growth shock | B30: 0.3 | C30: pp of GDP | D30: Starting value
A31: Commodity export price shock | B31: -30 | C31: % | D31: Methodology (pillar 2 stress path)
A32: Tourism receipts shock | B32: -25 | C32: % | D32: Methodology (pillar 2 stress path)
A33: Manufacturing and services export shock | B33: -10 | C33: % | D33: Starting value
A34: Inflation pass-through from depreciation | B34: 0.3 | C34: share | D34: Methodology (pillar 5 stress path)
A36: Probability layer | B36: Value | C36: Unit | D36: Source
A37: Scorecard centre (universe average composite) | B37: =AVERAGE('Pillar Scores'!E46:V46) -> 45.767337 | C37: points | D37: Calculated
A38: Scorecard weight w_s | B38: 0.04 | C38: log-odds per point | D38: Starting value; fit on history (layer 2)
A39: Market signal weight w_m | B39: 0.5 | C39: share of market vs rating log-odds gap | D39: Starting value
A40: Text stress weight w_t | B40: 0.25 | C40: log-odds per z | D40: Starting value
A41: Loss given default used to back out market-implied PD | B41: 0.6 | C41: share | D41: Starting value
A42: Distress threshold: rating-implied PD at or above | B42: 0.12 | C42: probability | D42: Starting value (CCC+ and below)
A43: Minimum market-implied PD for mispricing signals | B43: 0.02 | C43: probability | D43: Starting value: below this, spreads are mostly risk and liquidity premium
A44: Regime state rules (proxy for layer 3 hidden Markov model) | B44: Value | C44: Unit | D44: Source
A45: Stressed: spread at or above | B45: 400 | C45: bps | D45: Starting value
A46: Crisis: spread at or above | B46: 1000 | C46: bps | D46: Methodology market flag (1,000 bps)
A47: Stressed: 3-month depreciation at or above | B47: 5 | C47: % | D47: Starting value
A48: Crisis: 3-month depreciation at or above | B48: 15 | C48: % | D48: Starting value
A49: Stressed: 3-month reserve change at or below | B49: -10 | C49: % | D49: Starting value
A51: Regime | B51: PD multiplier | C51: LGD multiplier | D51: Global factor loading | E51: Position size scalar
A52: Calm | B52: 1 | C52: 1 | D52: 0.15 | E52: 1
A53: Stressed | B53: 1.25 | C53: 1.1 | D53: 0.25 | E53: 0.75
A54: Crisis | B54: 1.6 | C54: 1.25 | D54: 0.35 | E54: 0.5
A55: Regional factor loading | B55: 0.1 | D55: Starting value
A57: Peril | B57: Driver | C57: Base 12m probability at driver score 50 | D57: Log-odds slope per 10 points | E57: Loss given event
A58: Sovereign default | B58: Rating prior + scorecard + market + text | E58: 0.45
A59: Transfer and convertibility | B59: Pillar 2 | C59: 0.02 | D59: 0.5 | E59: 0.3
A60: Expropriation | B60: Pillar 3 | C60: 0.01 | D60: 0.5 | E60: 0.7
A61: Political violence | B61: Average of pillars 4 and 6 | C61: 0.02 | D61: 0.5 | E61: 0.4
A62: Sanctions | B62: Average of indicators 2.7 and 4.10 | C62: 0.01 | D62: 0.5 | E62: 0.5
A64: Signals and sizing | B64: Value | C64: Unit | D64: Source
A65: Signal threshold (default minimum strength) | B65: 60 | C65: points | D65: Starting value
A66: Election window | B66: 12 | C66: months | D66: Methodology (pillar 4 election scenarios)
A67: Momentum scale | B67: 10 | C67: strength points per score point | D67: Starting value
A68: Risk budget per trade at full conviction | B68: 10 | C68: $mm notional | D68: User to set
A69: Minimum real policy rate for carry | B69: 1.5 | C69: % | D69: Starting value
A70: Monte Carlo | B70: Value | C70: Unit | D70: Source
A71: Scenarios | B71: 2000 | C71: fixed by the MC tab layout | D71: Methodology targets 100,000+ in code
A72: Random seed | B72: 7 | C72: integer | D72: Fixed for repeatability
A73: Student-t degrees of freedom | B73: 5 | C73: df | D73: Starting value (layer 5)
A74: Scenario override | B74: Model | C74: Model / All stressed / All crisis | D74: Stress selector
A76: Rating | B76: Rating-implied 1-year PD | D76: Source
A77: AAA | B77: 0.0001 | D77: Smoothed starting values, to be fitted to agency 17g-7 histories
A78: AA+ | B78: 0.0002
A79: AA | B79: 0.0003
A80: AA- | B80: 0.0004
A81: A+ | B81: 0.0005
A82: A | B82: 0.0007
A83: A- | B83: 0.0009
A84: BBB+ | B84: 0.0013
A85: BBB | B85: 0.0019
A86: BBB- | B86: 0.0028
A87: BB+ | B87: 0.0042
A88: BB | B88: 0.0065
A89: BB- | B89: 0.01
... A98: D | B98: 0.6
A100: Override floors | B100: Value | C100: Unit | D100: Source
A101: Pillar 1 floor: in default or distressed exchange | B101: 90 | C101: points | D101: Methodology rulebook
A102: Pillar 2 floor: external arrears, premium above threshold, or black list | B102: 85 | C102: points | D102: Methodology rulebook
A103: Pillar 2: parallel premium threshold | B103: 100 | C103: % | D103: Methodology rulebook
A104: Pillar 3 floor: expropriation without compensation, past 3 years | B104: 80 | C104: points | D104: Methodology rulebook
A105: Pillar 4 floor: coup within 12 months | B105: 85 | C105: points | D105: Methodology rulebook
A106: Pillar 4 floor: stated intent not to pay | B106: 90 | C106: points | D106: Methodology rulebook
A107: Pillar 5: hyperinflation threshold | B107: 100 | C107: % | D107: Methodology rulebook
A108: Pillar 5 floor: hyperinflation | B108: 90 | C108: points | D108: Methodology rulebook
A109: Pillar 5 floor: banking crisis under way | B109: 85 | C109: points | D109: Methodology rulebook
A110: Pillar 6 floor: war on national territory | B110: 85 | C110: points | D110: Methodology rulebook
A111: Pillar 6 floor: nationwide state of emergency | B111: 70 | C111: points | D111: Methodology rulebook
A112: Pillar 7 floor: disaster loss of 10% of GDP or more | B112: 80 | C112: points | D112: Methodology rulebook
... A116: Boom trigger points | B116: 10 | C116: points | D116: Methodology

Sheet Rulebook
A1: Rulebook: indicator thresholds and weights
A2: Each indicator is scored 0 to 100 by straight-line interpolation between its five threshold points. Level indicators take values 0 to 4, so each level maps to 0, 25, 50, 75 or 100. Thresholds are the methodology's first draft, to be fitted on the backtest.
A4: ID | B4: Pillar | C4: Indicator | D4: Unit | E4: Weight in pillar | F4: Type | G4: Scores 0 at | H4: Scores 25 at | I4: Scores 50 at | J4: Scores 75 at | K4: Scores 100 at | L4: Direction | M4: Stress path | N4: Level guide | O4: Source | P4: API or dataset for hookup | Q4: Low side 0 | R4: Low side 25 | S4: Low side 50 | T4: Low side 75 | U4: Low side 100
A5: 1.1 | B5: 1 | C5: Debt service (interest plus principal) | D5: % of revenue | E5: 0.2 | F5: Numeric | G5: 10 | H5: 20 | I5: 30 | J5: 45 | K5: 60 | L5: =SIGN(K5-G5) -> 1 | M5: N | O5: IMF Article IV DSA, budget documents | P5: Manual: IMF Article IV DSA tables
A6: 1.2 | B6: 1 | C6: FX debt service due in next 24 months | D6: % of FX reserves | E6: 0.15 | F6: Numeric | G6: 10 | H6: 25 | I6: 50 | J6: 75 | K6: 100 | L6: =SIGN(K6-G6) -> 1 | M6: N | O6: World Bank IDS projected debt service, Eurobond schedules, IMF reserves | P6: World Bank IDS API (DT.TDS.DPPG.CD) + IMF IRFCL
A7: 1.3 | B7: 1 | C7: Gross government debt | D7: % of GDP | E7: 0.15 | F7: Numeric | G7: 30 | H7: 45 | I7: 60 | J7: 80 | K7: 100 | L7: =SIGN(K7-G7) -> 1 | M7: Y | O7: IMF WEO; Randori stress path | P7: IMF DataMapper GGXWDG_NGDP
A8: 1.4 | B8: 1 | C8: Gross financing need | D8: % of GDP | E8: 0.1 | F8: Numeric | G8: 5 | H8: 10 | I8: 15 | J8: 20 | K8: 25 | L8: =SIGN(K8-G8) -> 1 | M8: Y | O8: IMF Article IV DSA / Fiscal Monitor; Randori stress path | P8: Manual: IMF Fiscal Monitor GFN table
A9: 1.5 | B9: 1 | C9: Foreign-currency share of government debt | D9: % of debt | E9: 0.1 | F9: Numeric | G9: 20 | H9: 35 | I9: 50 | J9: 65 | K9: 80 | L9: =SIGN(K9-G9) -> 1 | M9: N | O9: Article IV DSA, World Bank IDS | P9: World Bank IDS API
A10: 1.6 | B10: 1 | C10: Primary balance gap (actual minus debt-stabilizing) | D10: pp of GDP | E10: 0.05 | F10: Numeric | G10: 0 | H10: -1 | I10: -2 | J10: -3.5 | K10: -5 | L10: =SIGN(K10-G10) -> -1 | M10: Y | O10: Computed from WEO growth, rates and debt | P10: IMF DataMapper GGXONLB_G01_GDP_PT, NGDP_RPCH
A11: 1.7 | B11: 1 | C11: Change in debt/GDP over five years | D11: pp of GDP | E11: 0.05 | F11: Numeric | G11: -5 | H11: 0 | I11: 5 | J11: 10 | K11: 15 | L11: =SIGN(K11-G11) -> 1 | M11: Y | O11: IMF WEO; Randori stress path | P11: IMF DataMapper GGXWDG_NGDP (t minus t-5)
A12: 1.8 | B12: 1 | C12: Default record: restructurings or defaults, past 20 years | D12: count | E12: 0.1 | F12: Numeric | G12: 0 | H12: 0.5 | I12: 1 | J12: 2 | K12: 3 | L12: =SIGN(K12-G12) -> 1 | M12: N | O12: BoC-BoE sovereign default database | P12: Bank of Canada CRAG database (annual file)
A13: 1.9 | B13: 1 | C13: Contingent liabilities and arrears | D13: level | E13: 0.1 | F13: Level 0-4 | G13: 0 | H13: 1 | I13: 2 | J13: 3 | K13: 4 | L13: =SIGN(K13-G13) -> 1 | M13: N | N13: 0 none known | 1 small, disclosed | 2 guarantees >10% GDP or minor arrears | 3 arrears building or large SOE losses | 4 arrears >5% GDP or bank/SOE bailout under way | O13: Article IV, budget documents | P13: Manual: analyst
A14: 2.1 | B14: 2 | C14: Net usable reserves | D14: % of IMF ARA metric | E14: 0.15 | F14: Numeric | G14: 150 | H14: 125 | I14: 100 | J14: 75 | K14: 50 | L14: =SIGN(K14-G14) -> -1 | M14: Y | O14: IMF reserves template, IMF ARA data, central bank | P14: IMF ARA dataset (annual) + IMF IRFCL
A15: 2.2 | B15: 2 | C15: External financing need (CA deficit + external debt due in 12m) | D15: % of net reserves | E15: 0.15 | F15: Numeric | G15: 50 | H15: 75 | I15: 100 | J15: 150 | K15: 200 | L15: =SIGN(K15-G15) -> 1 | M15: N | O15: IMF BoP, World Bank IDS, BIS | P15: IMF BOP API + World Bank IDS API
A16: 2.3 | B16: 2 | C16: Hot money (non-resident local debt + portfolio due in 1y) | D16: % of net reserves | E16: 0.1 | F16: Numeric | G16: 10 | H16: 25 | I16: 50 | J16: 75 | K16: 100 | L16: =SIGN(K16-G16) -> 1 | M16: N | O16: Central bank, IMF sovereign investor base (Arslanalp-Tsuda) | P16: IMF Sovereign Investor Base dataset
A17: 2.4 | B17: 2 | C17: Dollarized banks: FX deposits | D17: % of deposits | E17: 0.1 | F17: Numeric | G17: 10 | H17: 25 | I17: 40 | J17: 55 | K17: 70 | L17: =SIGN(K17-G17) -> 1 | M17: N | O17: IMF Financial Soundness Indicators, central bank | P17: IMF FSI API
A18: 2.5 | B18: 2 | C18: Exchange regime and convertibility | D18: level | E18: 0.1 | F18: Level 0-4 | G18: 0 | H18: 1 | I18: 2 | J18: 3 | K18: 4 | L18: =SIGN(K18-G18) -> 1 | M18: N | N18: 0 free float, no controls | 1 managed float | 2 peg/dollarized with ample reserves, or parallel premium <10% | 3 peg below adequacy, multiple rates, or premium 10-50% | 4 premium >50%, FX rationing or active capital controls | O18: IMF AREAER, central bank, market reports | P18: Manual: IMF AREAER annual
A19: 2.6 | B19: 2 | C19: Official backstop: support available vs reliance | D19: level | E19: 0.1 | F19: Level 0-4 | G19: 0 | H19: 1 | I19: 2 | J19: 3 | K19: 4 | L19: =SIGN(K19-G19) -> 1 | M19: N | N19: 0 large precautionary line or major swap line unused | 1 IMF program on track or swaps undrawn | 2 no program, ordinary access | 3 program off track or drawn swaps/rolled deposits >25% reserves | 4 program suspended and drawn swaps/deposits >50% reserves | O19: IMF country pages, central bank, press | P19: Manual: IMF lending arrangements (MONA)
A20: 2.7 | B20: 2 | C20: Access to the dollar banking system | D20: level | E20: 0.05 | F20: Level 0-4 | G20: 0 | H20: 1 | I20: 2 | J20: 3 | K20: 4 | L20: =SIGN(K20-G20) -> 1 | M20: N | N20: 0 no issues | 1 some loss of correspondents | 2 FATF grey list | 3 grey list plus loss of major USD correspondents, or targeted sanctions | 4 FATF black list or sanctions blocking USD clearing | O20: FATF lists (Feb/Jun/Oct), World Bank/IMF correspondent banking reports | P20: Manual: FATF plenary lists
A21: 2.8 | B21: 2 | C21: Current account balance | D21: % of GDP | E21: 0.05 | F21: Numeric | G21: 0 | H21: -2 | I21: -4 | J21: -6 | K21: -8 | L21: =SIGN(K21-G21) -> -1 | M21: Y | O21: IMF WEO; Randori stress path | P21: IMF DataMapper BCA_NGDPD
A22: 2.9 | B22: 2 | C22: Short-term external debt | D22: % of net reserves | E22: 0.05 | F22: Numeric | G22: 10 | H22: 25 | I22: 50 | J22: 75 | K22: 100 | L22: =SIGN(K22-G22) -> 1 | M22: N | O22: World Bank IDS, BIS | P22: World Bank IDS API (DT.DOD.DSTC.IR.ZS)
A23: 2.10 | B23: 2 | C23: External debt | D23: % of exports of goods and services | E23: 0.05 | F23: Numeric | G23: 100 | H23: 150 | I23: 200 | J23: 250 | K23: 300 | L23: =SIGN(K23-G23) -> 1 | M23: N | O23: World Bank IDS | P23: World Bank IDS API (DT.DOD.DECT.EX.ZS)
A24: 2.11 | B24: 2 | C24: Export concentration: largest commodity or sector | D24: % of exports | E24: 0.05 | F24: Numeric | G24: 20 | H24: 35 | I24: 50 | J24: 65 | K24: 80 | L24: =SIGN(K24-G24) -> 1 | M24: N | O24: UN Comtrade, IMF BoP | P24: UN Comtrade API
A25: 2.12 | B25: 2 | C25: Real exchange rate vs 10-year average | D25: % above average | E25: 0.05 | F25: Numeric | G25: 0 | H25: 5 | I25: 10 | J25: 18 | K25: 25 | L25: =SIGN(K25-G25) -> 1 | M25: N | O25: BIS or IMF REER | P25: BIS REER API (broad)
A26: 3.1 | B26: 3 | C26: Record on investor treatment, past 20 years | D26: level | E26: 0.15 | F26: Level 0-4 | G26: 0 | H26: 1 | I26: 2 | J26: 3 | K26: 4 | L26: =SIGN(K26-G26) -> 1 | M26: N | N26: 0 none | 1 one case, negotiated and compensated | 2 one contested case or sector-wide renegotiation | 3 several cases or one without fair compensation | 4 nationalization program under way | O26: UNCTAD investment dispute database, Randori notes, press | P26: UNCTAD ISDS Navigator (manual)
A27: 3.2 | B27: 3 | C27: Arbitration award compliance | D27: level | E27: 0.15 | F27: Level 0-4 | G27: 0 | H27: 1 | I27: 2 | J27: 3 | K27: 4 | L27: =SIGN(K27-G27) -> 1 | M27: N | N27: 0 no awards or paid promptly | 1 paid within two years | 2 paid only after enforcement, or partly | 3 unpaid for over two years | 4 open refusal, asset seizures, or ICSID exit | O27: ICSID and UNCTAD case records, court filings | P27: ICSID case database (manual)
A28: 3.3 | B28: 3 | C28: Treaty protection | D28: level | E28: 0.1 | F28: Level 0-4 | G28: 0 | H28: 1 | I28: 2 | J28: 3 | K28: 4 | L28: =SIGN(K28-G28) -> 1 | M28: N | N28: 0 ICSID member, BITs in force with major investors | 1 ICSID member, few treaties | 2 not ICSID member, thin cover, or treaties under review | 3 treaties ended or consent withdrawn in past 10 years | 4 left ICSID or ended all BITs | O28: UNCTAD IIA Navigator, ICSID member list | P28: UNCTAD IIA Navigator (manual)
A29: 3.4 | B29: 3 | C29: Direction of change: 3-year change in WGI composite | D29: percentile points | E29: 0.1 | F29: Numeric | G29: 5 | H29: 0 | I29: -3 | J29: -6 | K29: -10 | L29: =SIGN(K29-G29) -> -1 | M29: N | O29: World Bank WGI | P29: World Bank WGI API (RL/CC/RQ .PER.RNK)
A30: 3.5 | B30: 3 | C30: WGI composite (rule of law, corruption, regulatory quality) | D30: percentile | E30: 0.1 | F30: Numeric | G30: 80 | H30: 60 | I30: 40 | J30: 25 | K30: 10 | L30: =SIGN(K30-G30) -> -1 | M30: N | O30: World Bank WGI | P30: World Bank WGI API (RL/CC/RQ .PER.RNK)
A31: 3.6 | B31: 3 | C31: Courts and legislature constrain the executive (V-Dem) | D31: index 0-1 | E31: 0.1 | F31: Numeric | G31: 0.85 | H31: 0.7 | I31: 0.5 | J31: 0.3 | K31: 0.15 | L31: =SIGN(K31-G31) -> -1 | M31: N | O31: V-Dem | P31: V-Dem dataset (v2x_jucon, v2xlg_legcon)
A32: 3.7 | B32: 3 | C32: Civil justice and contract enforcement (WJP) | D32: index 0-1 | E32: 0.1 | F32: Numeric | G32: 0.7 | H32: 0.6 | I32: 0.5 | J32: 0.4 | K32: 0.3 | L32: =SIGN(K32-G32) -> -1 | M32: N | O32: World Justice Project Rule of Law Index | P32: WJP Rule of Law Index (factor 7)
A33: 3.8 | B33: 3 | C33: Budget and data credibility | D33: level | E33: 0.1 | F33: Level 0-4 | G33: 0 | H33: 1 | I33: 2 | J33: 3 | K33: 4 | L33: =SIGN(K33-G33) -> 1 | M33: N | N33: 0 meets SDDS, no misreporting | 1 SDDS with gaps or e-GDDS met | 2 e-GDDS with gaps or weak open budget | 3 misreporting within 10 years or large unexplained revisions | 4 data suppressed, falsification, or hidden debt found | O33: IMF data standards, Open Budget Survey, PEFA, Article IV | P33: Manual: IMF DSBB
A34: 3.9 | B34: 3 | C34: State's growing role in strategic sectors | D34: level | E34: 0.05 | F34: Level 0-4 | G34: 0 | H34: 1 | I34: 2 | J34: 3 | K34: 4 | L34: =SIGN(K34-G34) -> 1 | M34: N | N34: 0 privatizing or stable private role | 1 state role stable | 2 larger stake in one sector, negotiated | 3 control in several sectors or local ownership mandates | 4 sector-wide nationalization policy | O34: Randori notes, press, OECD SOE data | P34: Manual: analyst
A35: 3.10 | B35: 3 | C35: Central bank independence in practice | D35: level | E35: 0.05 | F35: Level 0-4 | G35: 0 | H35: 1 | I35: 2 | J35: 3 | K35: 4 | L35: =SIGN(K35-G35) -> 1 | M35: N | N35: 0 independent, no monetary financing | 1 minor lapses | 2 governor replaced early or occasional monetary financing | 3 regular monetary financing | 4 financing the budget at scale or quasi-fiscal losses | O35: Article IV, central bank law and accounts, Garriga CBI index | P35: Manual: analyst
A36: 4.1 | B36: 4 | C36: Street pressure against promised adjustment | D36: level | E36: 0.15 | F36: Level 0-4 | G36: 0 | H36: 1 | I36: 2 | J36: 3 | K36: 4 | L36: =SIGN(K36-G36) -> 1 | M36: N | N36: 0 little adjustment or normal protests | 1 adjustment <1.5% GDP, protests slightly above normal | 2 adjustment >=1.5% GDP with protests above normal | 3 protests forced a reversal or turned deadly | 4 government fell or dropped IMF measures under street pressure | O36: Pillar 1 gap, ACLED/GDELT protest counts vs 5-year average | P36: ACLED API (protests) + analyst
A37: 4.2 | B37: 4 | C37: Military and elite cohesion | D37: level | E37: 0.1 | F37: Level 0-4 | G37: 0 | H37: 1 | I37: 2 | J37: 3 | K37: 4 | L37: =SIGN(K37-G37) -> 1 | M37: N | N37: 0 professional, paid, no purges | 1 minor grievances | 2 pay arrears or top commanders reshuffled | 3 purges, mutinies or rival armed units | 4 open split or mutiny | O37: Press, ACLED, Crisis Group, IISS | P37: Manual: analyst
A38: 4.3 | B38: 4 | C38: Regime type and factionalism | D38: level | E38: 0.1 | F38: Level 0-4 | G38: 0 | H38: 1 | I38: 2 | J38: 3 | K38: 4 | L38: =SIGN(K38-G38) -> 1 | M38: N | N38: 0 full democracy | 1 stable full autocracy | 2 partial autocracy | 3 partial democracy | 4 partial democracy with polarized, exclusionary factions | O38: V-Dem regime classification and polarization | P38: V-Dem dataset (v2x_regime, v2cacamps)
A39: 4.4 | B39: 4 | C39: Coup and irregular transfer of power | D39: level | E39: 0.1 | F39: Level 0-4 | G39: 0 | H39: 1 | I39: 2 | J39: 3 | K39: 4 | L39: =SIGN(K39-G39) -> 1 | M39: N | N39: 0 no attempt in 50 years | 1 last attempt >20 years ago | 2 attempt within 20 years or military active in politics | 3 attempt within 5 years or coup in a neighbor within 3 years | 4 successful coup within 5 years or military government | O39: Powell-Thyne coup data, Cline Center | P39: Powell-Thyne dataset (monthly file)
A40: 4.5 | B40: 4 | C40: Election timing and contestation | D40: level | E40: 0.1 | F40: Level 0-4 | G40: 0 | H40: 1 | I40: 2 | J40: 3 | K40: 4 | L40: =SIGN(K40-G40) -> 1 | M40: N | N40: 0 no national election within 24m, results accepted | 1 election within 24m, competitive | 2 election within 12m, polarized or strong anti-establishment challenger | 3 last result disputed or term-limit evasion | 4 election postponed/cancelled or results rejected with unrest | O40: IFES ElectionGuide, NELDA, V-Dem | P40: IFES ElectionGuide (manual)
A41: 4.6 | B41: 4 | C41: Policy predictability: abrupt changes by decree, past 5 years | D41: level | E41: 0.1 | F41: Level 0-4 | G41: 0 | H41: 1 | I41: 2 | J41: 3 | K41: 4 | L41: =SIGN(K41-G41) -> 1 | M41: N | N41: 0 none | 1 one, consulted and phased | 2 two or three, or one sudden and large | 3 frequent reversals | 4 rule by decree is routine | O41: Randori event log, Article IV, press | P41: Manual: analyst event log
A42: 4.7 | B42: 4 | C42: Government's ability to pass what it needs | D42: level | E42: 0.1 | F42: Level 0-4 | G42: 0 | H42: 1 | I42: 2 | J42: 3 | K42: 4 | L42: =SIGN(K42-G42) -> 1 | M42: N | N42: 0 stable majority | 1 working majority with friction | 2 minority or fragile coalition | 3 repeated failure to pass budgets or program measures | 4 deadlock, or president removed in past 2 years | O42: IDB Database of Political Institutions, legislative records | P42: Manual: analyst
A43: 4.8 | B43: 4 | C43: Stance toward creditors and investors | D43: level | E43: 0.1 | F43: Level 0-4 | G43: 0 | H43: 1 | I43: 2 | J43: 3 | K43: 4 | L43: =SIGN(K43-G43) -> 1 | M43: N | N43: 0 committed to paying and contracts | 1 mild criticism | 2 calls for debt audits or contract reviews | 3 official plan to renegotiate on state's terms | 4 intent not to pay 'illegitimate' debt or nationalization pledges | O43: Platforms, speeches, press | P43: Manual: analyst
A44: 4.9 | B44: 4 | C44: Outside patrons | D44: level | E44: 0.05 | F44: Level 0-4 | G44: 0 | H44: 1 | I44: 2 | J44: 3 | K44: 4 | L44: =SIGN(K44-G44) -> 1 | M44: N | N44: 0 diverse partners | 1 one major partner, stable | 2 relies on one patron's money or security | 3 patron wavering or under pressure | 4 survival depends on foreign forces or patron withdrawing | O44: Press, SIPRI, AidData, central bank | P44: Manual: analyst
... A46: 4.11 | B46: 4 | C46: Leader and succession risk | D46: level | E46: 0.05 | F46: Level 0-4 | G46: 0 | H46: 1 | I46: 2 | J46: 3 | K46: 4 | L46: =SIGN(K46-G46) -> 1 | M46: N | N46: 0 institutionalized succession | 1 clear succession, some personal rule | 2 personalist leader, unclear successor | 3 past term limits or poor health, contested succession | 4 succession crisis under way | O46: V-Dem, Geddes-Wright-Frantz, press | P46: Manual: analyst
A47: 5.1 | B47: 5 | C47: Banks' claims on government | D47: % of bank assets | E47: 0.1 | F47: Numeric | G47: 10 | H47: 15 | I47: 25 | J47: 35 | K47: 45 | L47: =SIGN(K47-G47) -> 1 | M47: N | O47: IMF monetary and financial statistics, central bank | P47: IMF MFS API
A48: 5.2 | B48: 5 | C48: Currency mismatch: FX loans | D48: % of loans | E48: 0.1 | F48: Numeric | G48: 10 | H48: 20 | I48: 35 | J48: 50 | K48: 65 | L48: =SIGN(K48-G48) -> 1 | M48: N | O48: IMF FSI, BIS, central bank | P48: IMF FSI API
A49: 5.3 | B49: 5 | C49: Concentration and the weakest large bank | D49: level | E49: 0.1 | F49: Level 0-4 | G49: 0 | H49: 1 | I49: 2 | J49: 3 | K49: 4 | L49: =SIGN(K49-G49) -> 1 | M49: N | N49: 0 top-3 <50% of assets, all large banks sound | 1 top-3 50-70%, all sound | 2 one large bank with weak capital or NPLs 8-12% | 3 one large bank below minimum capital, NPLs >12%, or under watch | 4 large bank failed or rescued in past year | O49: Bank reports, central bank FSRs, ratings | P49: Manual: analyst
A50: 5.4 | B50: 5 | C50: Commodity link: real credit growth vs main export price | D50: correlation | E50: 0.1 | F50: Numeric | G50: 0.1 | H50: 0.25 | I50: 0.4 | J50: 0.55 | K50: 0.7 | L50: =SIGN(K50-G50) -> 1 | M50: N | O50: World Bank Pink Sheet, IMF credit data | P50: Computed: WB Pink Sheet + IMF IFS credit
A51: 5.5 | B51: 5 | C51: Inflation, 12 months | D51: % | E51: 0.1 | F51: Numeric | G51: 3 | H51: 6 | I51: 10 | J51: 20 | K51: 40 | L51: =SIGN(K51-G51) -> 1 | M51: Y | O51: National statistics, IMF WEO; Randori stress path | P51: IMF DataMapper PCPIPCH
A52: 5.6 | B52: 5 | C52: Real GDP growth next year | D52: % | E52: 0.1 | F52: Numeric | G52: 5 | H52: 3.5 | I52: 2 | J52: 0 | K52: -2 | L52: =SIGN(K52-G52) -> -1 | M52: Y | O52: IMF WEO; Randori stress path | P52: IMF DataMapper NGDP_RPCH
A53: 5.7 | B53: 5 | C53: State-owned banks | D53: % of bank assets | E53: 0.05 | F53: Numeric | G53: 10 | H53: 20 | I53: 35 | J53: 50 | K53: 65 | L53: =SIGN(K53-G53) -> 1 | M53: N | O53: World Bank regulation and supervision survey, central bank | P53: World Bank BRSS (manual)
A54: 5.8 | B54: 5 | C54: Lenders outside the banks | D54: level | E54: 0.05 | F54: Level 0-4 | G54: 0 | H54: 1 | I54: 2 | J54: 3 | K54: 4 | L54: =SIGN(K54-G54) -> 1 | M54: N | N54: 0 small and supervised | 1 growing, supervised | 2 >10% of credit or >20% growth with light supervision | 3 large and unsupervised or recent failures | 4 non-bank collapse spreading to banks | O54: Central bank FSRs, IMF FSAP, GSMA | P54: Manual: analyst
A55: 5.9 | B55: 5 | C55: Credit-to-GDP gap | D55: pp of GDP | E55: 0.05 | F55: Numeric | G55: 0 | H55: 2 | I55: 5 | J55: 10 | K55: 15 | L55: =SIGN(K55-G55) -> 1 | M55: N | O55: BIS credit gaps, or computed from IMF data | P55: BIS credit-to-GDP gaps API
A56: 5.10 | B56: 5 | C56: Non-performing loans, system-wide | D56: % of loans | E56: 0.05 | F56: Numeric | G56: 3 | H56: 5 | I56: 8 | J56: 12 | K56: 18 | L56: =SIGN(K56-G56) -> 1 | M56: N | O56: IMF FSI | P56: World Bank WDI FB.AST.NPER.ZS / IMF FSI
A57: 5.11 | B57: 5 | C57: Real deposit growth, 12 months | D57: % | E57: 0.05 | F57: Numeric | G57: 5 | H57: 0 | I57: -5 | J57: -10 | K57: -15 | L57: =SIGN(K57-G57) -> -1 | M57: N | O57: Central bank monthly monetary data | P57: IMF IFS API (deposits) deflated by CPI
A58: 5.12 | B58: 5 | C58: Growth volatility: SD of real GDP growth, 15y (ex 2020-21) | D58: pp | E58: 0.05 | F58: Numeric | G58: 1.5 | H58: 2.5 | I58: 3.5 | J58: 5 | K58: 7 | L58: =SIGN(K58-G58) -> 1 | M58: N | O58: IMF WEO | P58: Computed: IMF DataMapper NGDP_RPCH history
A59: 5.13 | B59: 5 | C59: Real policy rate (two-sided: 0 to +4 scores 0) | D59: % | E59: 0.05 | F59: Numeric | G59: 4 | H59: 6 | I59: 8 | J59: 10 | K59: 12 | L59: =SIGN(K59-G59) -> 1 | M59: N | N59: High side in G:K; low side thresholds in Q:U. Score is the higher of the two. | O59: Central bank, CPI | P59: Central bank policy rate (BIS CBPOL API) less CPI | Q59: 0 | R59: -1.5 | S59: -3 | T59: -5 | U59: -8
A60: 5.14 | B60: 5 | C60: GDP per person | D60: US$ | E60: 0.05 | F60: Numeric | G60: 30000 | H60: 15000 | I60: 6000 | J60: 2500 | K60: 1000 | L60: =SIGN(K60-G60) -> -1 | M60: N | O60: IMF WEO | P60: IMF DataMapper NGDPDPC
A61: 6.1 | B61: 6 | C61: Armed conflict on national territory, past 12 months | D61: level | E61: 0.1 | F61: Level 0-4 | G61: 0 | H61: 1 | I61: 2 | J61: 3 | K61: 4 | L61: =SIGN(K61-G61) -> 1 | M61: N | N61: 0 none | 1 <25 battle deaths | 2 25-999 battle deaths | 3 1,000+ contained to a region | 4 1,000+ and spreading, or territory lost | O61: UCDP | P61: UCDP API (GED)
A62: 6.2 | B62: 6 | C62: Homicide rate | D62: per 100,000 | E62: 0.1 | F62: Numeric | G62: 2 | H62: 5 | I62: 10 | J62: 20 | K62: 40 | L62: =SIGN(K62-G62) -> 1 | M62: N | O62: UNODC, national police, InSight Crime | P62: World Bank WDI VC.IHR.PSRC.P5
A63: 6.3 | B63: 6 | C63: Gang control and extortion | D63: level | E63: 0.1 | F63: Level 0-4 | G63: 0 | H63: 1 | I63: 2 | J63: 3 | K63: 4 | L63: =SIGN(K63-G63) -> 1 | M63: N | N63: 0 none | 1 petty extortion | 2 systematic extortion in major cities | 3 gangs control prisons/neighborhoods and tax businesses | 4 gangs openly challenge the state | O63: InSight Crime, Global Organized Crime Index, press | P63: Manual: analyst
A64: 6.4 | B64: 6 | C64: Attacks on business and staff | D64: level | E64: 0.1 | F64: Level 0-4 | G64: 0 | H64: 1 | I64: 2 | J64: 3 | K64: 4 | L64: =SIGN(K64-G64) -> 1 | M64: N | N64: 0 rare | 1 isolated | 2 regular kidnappings or infrastructure attacks in some regions | 3 frequent attacks on mines, pipelines, power lines or staff | 4 attacks forcing major sites to shut or staff to leave | O64: ACLED, press | P64: ACLED API (strategic developments, abductions)
A65: 6.5 | B65: 6 | C65: State control of territory | D65: level | E65: 0.1 | F65: Level 0-4 | G65: 0 | H65: 1 | I65: 2 | J65: 3 | K65: 4 | L65: =SIGN(K65-G65) -> 1 | M65: N | N65: 0 full control | 1 isolated pockets | 2 regions with frequent armed incursions | 3 large areas contested or run by armed groups | 4 capital or key zones threatened | O65: ACLED, Crisis Group, press | P65: Manual: analyst
A66: 6.6 | B66: 6 | C66: Youth unemployment (15-24) | D66: % | E66: 0.1 | F66: Numeric | G66: 8 | H66: 12 | I66: 18 | J66: 25 | K66: 35 | L66: =SIGN(K66-G66) -> 1 | M66: N | O66: ILOSTAT modeled estimates | P66: World Bank WDI SL.UEM.1524.ZS
A67: 6.7 | B67: 6 | C67: Illegal economy: criminal markets score (GOCI) | D67: score 1-10 | E67: 0.05 | F67: Numeric | G67: 3 | H67: 4 | I67: 5.5 | J67: 7 | K67: 8 | L67: =SIGN(K67-G67) -> 1 | M67: N | O67: Global Initiative Against Transnational Organized Crime | P67: GOCI dataset (biennial)
A68: 6.8 | B68: 6 | C68: Cyber attacks on state systems | D68: level | E68: 0.05 | F68: Level 0-4 | G68: 0 | H68: 1 | I68: 2 | J68: 3 | K68: 4 | L68: =SIGN(K68-G68) -> 1 | M68: N | N68: 0 none known, strong capacity | 1 minor incidents | 2 significant breach in 3 years or weak capacity | 3 attack disrupted tax, customs or payments | 4 prolonged shutdown of state finances | O68: ITU GCI, CSIS cyber incidents, press | P68: Manual: analyst
A69: 6.9 | B69: 6 | C69: Political violence trend (ACLED, 12m vs 5y average) | D69: ratio | E69: 0.05 | F69: Numeric | G69: 0.8 | H69: 1 | I69: 1.5 | J69: 2 | K69: 3 | L69: =SIGN(K69-G69) -> 1 | M69: N | O69: ACLED | P69: ACLED API
A70: 6.10 | B70: 6 | C70: Inequality and excluded groups | D70: level | E70: 0.05 | F70: Level 0-4 | G70: 0 | H70: 1 | I70: 2 | J70: 3 | K70: 4 | L70: =SIGN(K70-G70) -> 1 | M70: N | N70: 0 Gini <35, no excluded groups | 1 Gini 35-40 | 2 Gini ~45 or large group excluded | 3 Gini ~50 or excluded groups with active grievances | 4 Gini >=55 or excluded groups >20% in open conflict | O70: World Bank Gini, ETH Ethnic Power Relations | P70: World Bank WDI SI.POV.GINI + EPR
A71: 6.11 | B71: 6 | C71: Food insecurity: population in IPC phase 3+ | D71: % | E71: 0.05 | F71: Numeric | G71: 2 | H71: 5 | I71: 10 | J71: 20 | K71: 30 | L71: =SIGN(K71-G71) -> 1 | M71: N | O71: IPC, FEWS NET, WFP | P71: IPC API
A72: 6.12 | B72: 6 | C72: Spillover from neighbors | D72: level | E72: 0.05 | F72: Level 0-4 | G72: 0 | H72: 1 | I72: 2 | J72: 3 | K72: 4 | L72: =SIGN(K72-G72) -> 1 | M72: N | N72: 0 no neighbor in conflict | 1 neighbor in minor conflict | 2 neighbor at war or refugees >1% of population | 3 cross-border attacks | 4 active cross-border war | O72: UCDP, UNHCR | P72: UCDP API + UNHCR API
A73: 6.13 | B73: 6 | C73: Terrorism (Global Terrorism Index) | D73: score 0-10 | E73: 0.05 | F73: Numeric | G73: 1 | H73: 2.5 | I73: 4 | J73: 6 | K73: 8 | L73: =SIGN(K73-G73) -> 1 | M73: N | O73: Institute for Economics and Peace | P73: GTI dataset (annual)
A74: 6.14 | B74: 6 | C74: Security forces: capacity and conduct | D74: level | E74: 0.05 | F74: Level 0-4 | G74: 0 | H74: 1 | I74: 2 | J74: 3 | K74: 4 | L74: =SIGN(K74-G74) -> 1 | M74: N | N74: 0 capable and rule-bound | 1 some gaps | 2 repeated emergencies or military in routine policing | 3 widespread abuses or mass detention | 4 collapse or mass atrocities | O74: US State Dept human rights reports, HRW, Amnesty | P74: Manual: analyst
A75: 7.1 | B75: 7 | C75: Expected annual disaster loss | D75: % of GDP | E75: 0.15 | F75: Numeric | G75: 0.1 | H75: 0.3 | I75: 0.7 | J75: 1.5 | K75: 3 | L75: =SIGN(K75-G75) -> 1 | M75: N | O75: UNDRR GAR, EM-DAT, World Bank risk profiles | P75: UNDRR GAR risk data (manual)
A76: 7.2 | B76: 7 | C76: Tail loss: 1-in-100-year disaster | D76: % of GDP | E76: 0.1 | F76: Numeric | G76: 2 | H76: 5 | I76: 10 | J76: 25 | K76: 50 | L76: =SIGN(K76-G76) -> 1 | M76: N | O76: UNDRR PML, CCRIF, World Bank | P76: UNDRR GAR PML (manual)
A77: 7.3 | B77: 7 | C77: Back-to-back disasters: chance of major disaster within 3 years | D77: % | E77: 0.1 | F77: Numeric | G77: 5 | H77: 10 | I77: 20 | J77: 35 | K77: 50 | L77: =SIGN(K77-G77) -> 1 | M77: N | O77: EM-DAT, UNDRR, cat models | P77: EM-DAT (licensed) + analyst
A78: 7.4 | B78: 7 | C78: Loss to the main earner: exports from most hazard-exposed sector | D78: % | E78: 0.1 | F78: Numeric | G78: 10 | H78: 20 | I78: 35 | J78: 50 | K78: 65 | L78: =SIGN(K78-G78) -> 1 | M78: N | O78: National accounts, WTTC, FAO, ports | P78: Manual: analyst
A79: 7.5 | B79: 7 | C79: Insurance protection gap: uninsured share of expected losses | D79: % | E79: 0.1 | F79: Numeric | G79: 40 | H79: 60 | I79: 75 | J79: 88 | K79: 95 | L79: =SIGN(K79-G79) -> 1 | M79: N | O79: Swiss Re, Munich Re, regulators | P79: Swiss Re sigma (annual, manual)
A80: 7.6 | B80: 7 | C80: Financial protection | D80: level | E80: 0.1 | F80: Level 0-4 | G80: 0 | H80: 1 | I80: 2 | J80: 3 | K80: 4 | L80: =SIGN(K80-G80) -> 1 | M80: N | N80: 0 layered: reserve fund, contingent credit, parametric cover, disaster clauses | 1 two of these | 2 one of these | 3 none, but emergency IMF/WB financing likely | 4 none and no fiscal room | O80: CCRIF, ARC, World Bank Cat DDO, bond documents | P80: Manual: analyst
A81: 7.7 | B81: 7 | C81: Basis risk in parametric cover (blank if no cover) | D81: level | E81: 0.05 | F81: Level 0-4 | G81: 0 | H81: 1 | I81: 2 | J81: 3 | K81: 4 | L81: =SIGN(K81-G81) -> 1 | M81: N | N81: 0 triggers well matched | 1 minor gaps | 2 known gaps | 3 past event with large loss and small payout | 4 cover dropped after missed payout | O81: CCRIF and ARC payout histories | P81: Manual: analyst
A82: 7.8 | B82: 7 | C82: Exposure concentration: low-lying coast or single hazard zone | D82: % | E82: 0.05 | F82: Numeric | G82: 5 | H82: 10 | I82: 20 | J82: 35 | K82: 50 | L82: =SIGN(K82-G82) -> 1 | M82: N | O82: CIESIN LECZ, World Bank | P82: CIESIN LECZ dataset
A83: 7.9 | B83: 7 | C83: Climate-driven conflict | D83: level | E83: 0.05 | F83: Level 0-4 | G83: 0 | H83: 1 | I83: 2 | J83: 3 | K83: 4 | L83: =SIGN(K83-G83) -> 1 | M83: N | N83: 0 none | 1 occasional land or water disputes | 2 recurring herder-farmer or water conflict in drought years | 3 deadly climate-linked conflict in several regions | 4 drought-driven conflict displacing large populations | O83: ACLED communal violence, SPEI, FEWS NET | P83: ACLED API + SPEI
A84: 7.10 | B84: 7 | C84: Transition risk: fossil fuels, % of exports or revenue | D84: % | E84: 0.05 | F84: Numeric | G84: 5 | H84: 15 | I84: 30 | J84: 50 | K84: 70 | L84: =SIGN(K84-G84) -> 1 | M84: N | O84: UN Comtrade, Article IV, EITI | P84: UN Comtrade API (HS 27)
A85: 7.11 | B85: 7 | C85: Climate vulnerability (ND-GAIN) | D85: score 0-1 | E85: 0.05 | F85: Numeric | G85: 0.35 | H85: 0.4 | I85: 0.45 | J85: 0.52 | K85: 0.58 | L85: =SIGN(K85-G85) -> 1 | M85: N | O85: Notre Dame Global Adaptation Initiative | P85: ND-GAIN dataset (annual)
A86: 7.12 | B86: 7 | C86: Water stress (WRI Aqueduct) | D86: level | E86: 0.05 | F86: Level 0-4 | G86: 0 | H86: 1 | I86: 2 | J86: 3 | K86: 4 | L86: =SIGN(K86-G86) -> 1 | M86: N | N86: 0 low | 1 low-medium | 2 medium-high | 3 high | 4 extremely high | O86: WRI Aqueduct | P86: WRI Aqueduct country rankings
A87: 7.13 | B87: 7 | C87: Recovery speed: years for GDP to regain level after last major disaster | D87: years | E87: 0.05 | F87: Numeric | G87: 1 | H87: 2 | I87: 3 | J87: 4.5 | K87: 6 | L87: =SIGN(K87-G87) -> 1 | M87: N | O87: IMF post-disaster reviews, PDNAs, WEO | P87: Manual: analyst

Sheet Country Profile
A1: Country Profile: market data, flags and tradable instruments
A2: Blue values are inputs (seed estimates as of October 2026; replace with live feeds). Yes/No flags drive the override floors and the regime state. Instrument rows decide which trades in the Playbook can be expressed.
A4: ID | B4: Key | C4: Field | D4: Unit or source | E4: Vietnam | F4: Philippines | G4: China | H4: Malaysia | I4: Singapore | J4: Japan | K4: South Korea | L4: India | M4: Pakistan | N4: Belize | O4: Brazil | P4: Argentina | Q4: Colombia | R4: Venezuela | S4: Nigeria | T4: Senegal | U4: Zambia | V4: Zimbabwe
A5: P1 | B5: iso | C5: ISO code | E5: VNM | F5: PHL | G5: CHN | H5: MYS | I5: SGP | J5: JPN | K5: KOR | L5: IND | M5: PAK | N5: BLZ | O5: BRA | P5: ARG | Q5: COL | R5: VEN | S5: NGA | T5: SEN | U5: ZMB | V5: ZWE
A6: P2 | B6: region | C6: Region block (copula factor) | D6: Asia / LatAm / Africa | E6: Asia | F6: Asia | G6: Asia | H6: Asia | I6: Asia | J6: Asia | K6: Asia | L6: Asia | M6: Asia | N6: LatAm | O6: LatAm | P6: LatAm | Q6: LatAm | R6: LatAm | S6: Africa | T6: Africa | U6: Africa | V6: Africa
A7: P3 | B7: pop | C7: Population | D7: millions; World Bank SP.POP.TOTL | E7: 101 | F7: 115 | G7: 1408 | H7: 35.5 | I7: 6 | J7: 123.5 | K7: 51.7 | L7: 1460 | M7: 250 | N7: 0.42 | O7: 213 | P7: 46 | Q7: 53 | R7: 28 | S7: 235 | T7: 18.9 | U7: 21.5 | V7: 16.9
A8: P4 | B8: exports | C8: Exports of goods and services | D8: % of GDP; World Bank NE.EXP.GNFS.ZS | E8: 90 | F8: 27 | G8: 19 | H8: 68 | I8: 175 | J8: 22 | K8: 44 | L8: 21 | M8: 10 | N8: 50 | O8: 17 | P8: 14 | Q8: 15 | R8: 25 | S8: 15 | T8: 25 | U8: 40 | V8: 25
A9: P5 | B9: reserves | C9: Gross FX reserves | D9: % of GDP; IMF IRFCL | E9: 17 | F9: 22 | G9: 17 | H9: 27 | I9: 150 | J9: 28 | K9: 22 | L9: 17 | M9: 4 | N9: 14 | O9: 15 | P9: 6 | Q9: 15 | R9: 4 | S9: 8 | T9: 12 | U9: 13 | V9: 2
A10: P6 | B10: mainexp | C10: Main export | D10: UN Comtrade | E10: Electronics | F10: Electronics | G10: Manufactures | H10: Electrical and electronics | I10: Electronics and refined fuels | J10: Vehicles | K10: Semiconductors | L10: Refined fuels and IT services | M10: Textiles | N10: Tourism | O10: Soybeans, iron ore, oil | P10: Soy complex | Q10: Crude oil | R10: Crude oil | S10: Crude oil | T10: Gold and oil | U10: Copper | V10: Gold
A11: P7 | B11: exptype | C11: Main export type | D11: Commodity / Tourism / Manufacturing / Services | E11: Manufacturing | F11: Manufacturing | G11: Manufacturing | H11: Manufacturing | I11: Manufacturing | J11: Manufacturing | K11: Manufacturing | L11: Services | M11: Manufacturing | N11: Tourism | O11: Commodity | P11: Commodity | Q11: Commodity | R11: Commodity | S11: Commodity | T11: Commodity | U11: Commodity | V11: Commodity
A12: P8 | B12: commgap | C12: Main export price vs 10-year real average | D12: %; World Bank Pink Sheet | E12: 0 | F12: 0 | G12: 0 | H12: 0 | I12: 0 | J12: 0 | K12: 0 | L12: 0 | M12: 0 | N12: 0 | O12: -5 | P12: -10 | Q12: -15 | R12: -15 | S12: -15 | T12: 60 | U12: 35 | V12: 60
A13: P9 | B13: fxregime | C13: Exchange regime type | D13: Float / Managed / Peg / Dollarized | E13: Managed | F13: Float | G13: Managed | H13: Float | I13: Managed | J13: Float | K13: Float | L13: Managed | M13: Managed | N13: Peg | O13: Float | P13: Managed | Q13: Float | R13: Managed | S13: Float | T13: Peg | U13: Float | V13: Managed
A14: P10 | B14: rating | C14: S&P long-term FX rating | D14: S&P; estimate | E14: BB+ | F14: BBB+ | G14: A+ | H14: A- | I14: AAA | J14: A+ | K14: AA | L14: BBB | M14: B- | N14: B- | O14: BB | P14: B- | Q14: BB | R14: SD | S14: B | T14: CCC+ | U14: CCC+ | V14: SD
A15: P11 | B15: spread | C15: 5Y CDS or EMBI spread | D15: bps; Bloomberg/LSEG or JPM EMBI | E15: 100 | F15: 65 | G15: 60 | H15: 45 | I15: 15 | J15: 20 | K15: 25 | L15: 70 | M15: 450 | N15: 650 | O15: 160 | P15: 650 | Q15: 220 | R15: 6000 | S15: 400 | T15: 1200 | U15: 450 | V15: 3000
A16: P12 | B16: fx3m | C16: FX change vs USD, past 3 months | D16: % depreciation (+); FRED or central bank | E16: 0.5 | F16: 1 | G16: -0.5 | H16: -1 | I16: -0.5 | J16: 1 | K16: 0.5 | L16: 1.5 | M16: 0.5 | N16: 0 | O16: 0 | P16: 6 | Q16: -1 | R16: 35 | S16: 1 | T16: 0 | U16: -2 | V16: 8
A17: P13 | B17: res3m | C17: Reserves change, past 3 months | D17: %; IMF IRFCL | E17: -2 | F17: 1 | G17: 0 | H17: 1 | I17: 1 | J17: 0 | K17: 0 | L17: 1 | M17: 5 | N17: -3 | O17: 1 | P17: 6 | Q17: 0 | R17: -5 | S17: 2 | T17: -8 | U17: 3 | V17: -2
A18: P14 | B18: policy | C18: Policy rate | D18: %; BIS CBPOL | E18: 4.5 | F18: 4.5 | G18: 1.4 | H18: 2.75 | J18: 0.75 | K18: 2.5 | L18: 5.5 | M18: 11 | O18: 15 | Q18: 9.25 | R18: 59 | S18: 27 | T18: 3.25 | U18: 14.5 | V18: 35
A19: P15 | B19: election | C19: Next national election | D19: IFES ElectionGuide | E19: 2031 (National Assembly) | F19: May 2028 (general) | G19: None (NPC) | H19: By early 2028 (general) | I19: 2030 (general) | J19: 2028 (upper house) | K19: Apr 2028 (legislative) | L19: 2029 (general) | M19: 2029 (general) | N19: 2030 (general) | O19: Oct 2026 runoff | P19: Oct 2027 (presidential) | Q19: 2030 (presidential) | R19: Disputed 2024 result | S19: Feb 2027 (general) | T19: 2029 (presidential) | U19: 2031 (general) | V19: 2028 (general)
A20: P16 | B20: elmonths | C20: Months to next national election | D20: months | E20: 56 | F20: 19 | G20: 99 | H20: 16 | I20: 48 | J20: 21 | K20: 18 | L20: 31 | M20: 34 | N20: 45 | O20: 1 | P20: 12 | Q20: 43 | R20: 48 | S20: 4 | T20: 29 | U20: 58 | V20: 22
A21: P17 | B21: default | C21: In default or arrears to creditors | D21: Yes / No | E21: No | F21: No | G21: No | H21: No | I21: No | J21: No | K21: No | L21: No | M21: No | N21: No | O21: No | P21: No | Q21: No | R21: Yes | S21: No | T21: No | U21: No | V21: Yes
A22: P18 | B22: extarrears | C22: External arrears to commercial creditors | D22: Yes / No | E22: No | F22: No | G22: No | H22: No | I22: No | J22: No | K22: No | L22: No | M22: No | N22: No | O22: No | P22: No | Q22: No | R22: Yes | S22: No | T22: No | U22: No | V22: Yes
A23: P19 | B23: parallel | C23: Parallel market premium | D23: % | E23: 1 | F23: 0 | G23: 0 | H23: 0 | I23: 0 | J23: 0 | K23: 0 | L23: 0 | M23: 1 | N23: 2 | O23: 0 | P23: 3 | Q23: 0 | R23: 60 | S23: 2 | T23: 0 | U23: 0 | V23: 40
A24: P20 | B24: exprop | C24: Expropriation without compensation or asset seizure, past 3 years | D24: Yes / No | E24: No | F24: No | G24: No | H24: No | I24: No | J24: No | K24: No | L24: No | M24: No | N24: No | O24: No | P24: No | Q24: No | R24: Yes | S24: No | T24: No | U24: No | V24: No
A25: P21 | B25: coup | C25: Coup or unconstitutional change, past 12 months | D25: Yes / No | E25: No | F25: No | G25: No | H25: No | I25: No | J25: No | K25: No | L25: No | M25: No | N25: No | O25: No | P25: No | Q25: No | R25: No | S25: No | T25: No | U25: No | V25: No
A26: P22 | B26: nopay | C26: Stated intent not to pay debt | D26: Yes / No | E26: No | F26: No | G26: No | H26: No | I26: No | J26: No | K26: No | L26: No | M26: No | N26: No | O26: No | P26: No | Q26: No | R26: No | S26: No | T26: No | U26: No | V26: No
A27: P23 | B27: bankcrisis | C27: Banking crisis under way | D27: Yes / No | E27: No | F27: No | G27: No | H27: No | I27: No | J27: No | K27: No | L27: No | M27: No | N27: No | O27: No | P27: No | Q27: No | R27: No | S27: No | T27: No | U27: No | V27: No
A28: P24 | B28: emergency | C28: Nationwide state of emergency for armed violence | D28: Yes / No | E28: No | F28: No | G28: No | H28: No | I28: No | J28: No | K28: No | L28: No | M28: No | N28: No | O28: No | P28: No | Q28: No | R28: No | S28: No | T28: No | U28: No | V28: No
A29: P25 | B29: disaster | C29: Disaster loss of 10% of GDP or more, past 12 months | D29: Yes / No | E29: No | F29: No | G29: No | H29: No | I29: No | J29: No | K29: No | L29: No | M29: No | N29: No | O29: No | P29: No | Q29: No | R29: No | S29: No | T29: No | U29: No | V29: No
A30: P26 | B30: textz | C30: Text stress index | D30: z-score; layer 2 language-model index (not built yet) | E30: 0 | F30: 0 | G30: 0 | H30: 0 | I30: 0 | J30: 0 | K30: 0 | L30: 0 | M30: 0 | N30: 0 | O30: 0 | P30: 0 | Q30: 0 | R30: 0 | S30: 0 | T30: 0 | U30: 0 | V30: 0
A31: P27 | B31: prior | C31: Prior composite score (last run) | D31: points; paste last run's composite here
A32: P28 | B32: CDS | C32: Liquid sovereign CDS | D32: Yes / No | E32: No | F32: Yes | G32: Yes | H32: Yes | I32: No | J32: Yes | K32: Yes | L32: No | M32: Yes | N32: No | O32: Yes | P32: Yes | Q32: Yes | R32: No | S32: Yes | T32: No | U32: No | V32: No
A33: P29 | B33: Eurobond | C33: Hard-currency sovereign bonds outstanding | D33: Yes / No | E33: Yes | F33: Yes | G33: Yes | H33: Yes | I33: No | J33: No | K33: Yes | L33: No | M33: Yes | N33: Yes | O33: Yes | P33: Yes | Q33: Yes | R33: Yes | S33: Yes | T33: Yes | U33: Yes | V33: No
A34: P30 | B34: FX | C34: Tradable FX (deliverable or NDF) | D34: Yes / No | E34: Yes | F34: Yes | G34: Yes | H34: Yes | I34: Yes | J34: Yes | K34: Yes | L34: Yes | M34: Yes | N34: No | O34: Yes | P34: Yes | Q34: Yes | R34: No | S34: Yes | T34: Yes | U34: Yes | V34: No
A35: P31 | B35: FX options | C35: FX options market | D35: Yes / No | E35: No | F35: Yes | G35: Yes | H35: Yes | I35: Yes | J35: Yes | K35: Yes | L35: Yes | M35: No | N35: No | O35: Yes | P35: No | Q35: Yes | R35: No | S35: No | T35: No | U35: No | V35: No
A36: P32 | B36: Local rates | C36: Local bonds or rates swaps accessible | D36: Yes / No | E36: No | F36: Yes | G36: Yes | H36: Yes | I36: Yes | J36: Yes | K36: Yes | L36: Yes | M36: No | N36: No | O36: Yes | P36: Yes | Q36: Yes | R36: No | S36: Yes | T36: No | U36: Yes | V36: No
A37: P33 | B37: Equity | C37: Country equity ETF or liquid index | D37: Yes / No | E37: Yes | F37: Yes | G37: Yes | H37: Yes | I37: Yes | J37: Yes | K37: Yes | L37: Yes | M37: No | N37: No | O37: Yes | P37: Yes | Q37: No | R37: No | S37: No | T37: No | U37: No | V37: No
A38: P34 | B38: etf | C38: Equity vehicle | D38: ticker | E38: VNM | F38: EPHE | G38: MCHI | H38: EWM | I38: EWS | J38: EWJ | K38: EWY | L38: INDA | O38: EWZ | P38: ARGT

Sheet Inputs
A1: Inputs: indicator values by country (baseline)
A2: Blue values are inputs. Green-shaded cells are IMF WEO October 2026 values; all other values are seed estimates to be replaced by the API in Rulebook column P. Level indicators use 0-4 (see Rulebook column N).
A4: {=Rulebook!A4:D87} -> ID | B4: Pillar | C4: Indicator | D4: Unit | E4: Vietnam | F4: Philippines | G4: China | H4: Malaysia | I4: Singapore | J4: Japan | K4: South Korea | L4: India | M4: Pakistan | N4: Belize | O4: Brazil | P4: Argentina | Q4: Colombia | R4: Venezuela | S4: Nigeria | T4: Senegal | U4: Zambia | V4: Zimbabwe
A5: 1.1 | B5: 1 | C5: Debt service (interest plus principal) | D5: % of revenue | E5: 15 | F5: 40 | G5: 12 | H5: 30 | I5: 2 | J5: 30 | K5: 8 | L5: 45 | M5: 80 | N5: 20 | O5: 40 | P5: 30 | Q5: 35 | R5: 60 | S5: 70 | T5: 45 | U5: 40 | V5: 35
A6: 1.2 | B6: 1 | C6: FX debt service due in next 24 months | D6: % of FX reserves | E6: 10 | F6: 15 | G6: 2 | H6: 10 | I6: 1 | J6: 1 | K6: 3 | L6: 8 | M6: 200 | N6: 30 | O6: 8 | P6: 90 | Q6: 25 | R6: 300 | S6: 30 | T6: 80 | U6: 40 | V6: 150
A7: 1.3 | B7: 1 | C7: Gross government debt | D7: % of GDP | E7: 33 | F7: 60 | G7: 104.4 | H7: 69.2 | I7: 175 | J7: 199.4 | K7: 47.3 | L7: 83.1 | M7: 72 | N7: 64.6 | O7: 97 | P7: 69.3 | Q7: 59.5 | R7: 150 | S7: 52 | T7: 120 | U7: 105 | V7: 75
A8: 1.4 | B8: 1 | C8: Gross financing need | D8: % of GDP | E8: 6 | F8: 10 | G8: 18 | H8: 12 | I8: 2 | J8: 40 | K8: 5 | L8: 14 | M8: 22 | N8: 7 | O8: 20 | P8: 12 | Q8: 9 | R8: 25 | S8: 10 | T8: 18 | U8: 10 | V8: 8
A9: 1.5 | B9: 1 | C9: Foreign-currency share of government debt | D9: % of debt | E9: 35 | F9: 31 | G9: 2 | H9: 3 | I9: 0 | J9: 0 | K9: 3 | L9: 5 | M9: 38 | N9: 63.8 | O9: 4 | P9: 60 | Q9: 35 | R9: 90 | S9: 45 | T9: 70 | U9: 60 | V9: 80
A10: 1.6 | B10: 1 | C10: Primary balance gap (actual minus debt-stabilizing) | D10: pp of GDP | E10: 0.5 | F10: -1 | G10: -4.5 | H10: -0.5 | I10: 2 | J10: -2 | K10: -0.5 | L10: -1.5 | M10: 1 | N10: 0.5 | O10: -1.5 | P10: 1 | Q10: -2.5 | R10: -5 | S10: -2 | T10: -3 | U10: 0.5 | V10: -1
A11: 1.7 | B11: 1 | C11: Change in debt/GDP over five years | D11: pp of GDP | E11: -6 | F11: 2 | G11: 33.8 | H11: 1.5 | I11: 25 | J11: -29.4 | K11: 1.4 | L11: -7.3 | M11: -5 | N11: -38 | O11: 1 | P11: -34.5 | Q11: -5.8 | R11: 0 | S11: 15 | T11: 45 | U11: -20 | V11: -20
A12: 1.8 | B12: 1 | C12: Default record: restructurings or defaults, past 20 years | D12: count | E12: 0 | F12: 0 | G12: 0 | H12: 0 | I12: 0 | J12: 0 | K12: 0 | L12: 0 | M12: 0 | N12: 4 | O12: 0 | P12: 3 | Q12: 0 | R12: 1 | S12: 0 | T12: 0 | U12: 1 | V12: 1
A13: 1.9 | B13: 1 | C13: Contingent liabilities and arrears | D13: level | E13: 2 | F13: 1 | G13: 4 | H13: 2 | I13: 0 | J13: 1 | K13: 2 | L13: 2 | M13: 3 | N13: 1 | O13: 2 | P13: 2 | Q13: 2 | R13: 4 | S13: 3 | T13: 4 | U13: 3 | V13: 4
A14: 2.1 | B14: 2 | C14: Net usable reserves | D14: % of IMF ARA metric | E14: 75 | F14: 160 | G14: 120 | H14: 110 | I14: 250 | J14: 300 | K14: 100 | L14: 150 | M14: 40 | N14: 60 | O14: 140 | P14: 30 | Q14: 120 | R14: 20 | S14: 90 | T14: 60 | U14: 70 | V14: 15
A15: 2.2 | B15: 2 | C15: External financing need (CA deficit + external debt due in 12m) | D15: % of net reserves | E15: 40 | F15: 40 | G15: 10 | H15: 60 | I15: 5 | J15: 5 | K15: 40 | L15: 50 | M15: 200 | N15: 120 | O15: 50 | P15: 250 | Q15: 90 | R15: 300 | S15: 60 | T15: 200 | U15: 110 | V15: 250
A16: 2.3 | B16: 2 | C16: Hot money (non-resident local debt + portfolio due in 1y) | D16: % of net reserves | E16: 5 | F16: 15 | G16: 10 | H16: 60 | I16: 10 | J16: 15 | K16: 40 | L16: 20 | M16: 20 | N16: 5 | O16: 60 | P16: 80 | Q16: 50 | R16: 10 | S16: 60 | T16: 20 | U16: 25 | V16: 10
... A80: 7.6 | B80: 7 | C80: Financial protection | D80: level | E80: 3 | F80: 1 | G80: 2 | H80: 2 | I80: 0 | J80: 1 | K80: 1 | L80: 2 | M80: 3 | N80: 1 | O80: 3 | P80: 3 | Q80: 1 | R80: 4 | S80: 3 | T80: 2 | U80: 3 | V80: 3
A81: 7.7 | B81: 7 | C81: Basis risk in parametric cover (blank if no cover) | D81: level | F81: 2 | N81: 2 | Q81: 1 | T81: 3
A82: 7.8 | B82: 7 | C82: Exposure concentration: low-lying coast or single hazard zone | D82: % | E82: 35 | F82: 25 | G82: 10 | H82: 15 | I82: 30 | J82: 15 | K82: 5 | L82: 5 | M82: 10 | N82: 45 | O82: 5 | P82: 5 | Q82: 5 | R82: 5 | S82: 10 | T82: 25 | U82: 5 | V82: 5
A83: 7.9 | B83: 7 | C83: Climate-driven conflict | D83: level | E83: 0 | F83: 0 | G83: 0 | H83: 0 | I83: 0 | J83: 0 | K83: 0 | L83: 1 | M83: 1 | N83: 0 | O83: 1 | P83: 0 | Q83: 1 | R83: 0 | S83: 3 | T83: 1 | U83: 1 | V83: 1
A84: 7.10 | B84: 7 | C84: Transition risk: fossil fuels, % of exports or revenue | D84: % | E84: 3 | F84: 3 | G84: 2 | H84: 20 | I84: 15 | J84: 1 | K84: 10 | L84: 12 | M84: 2 | N84: 2 | O84: 15 | P84: 10 | Q84: 50 | R84: 90 | S84: 85 | T84: 20 | U84: 1 | V84: 5
A85: 7.11 | B85: 7 | C85: Climate vulnerability (ND-GAIN) | D85: score 0-1 | E85: 0.41 | F85: 0.45 | G85: 0.36 | H85: 0.37 | I85: 0.3 | J85: 0.33 | K85: 0.32 | L85: 0.48 | M85: 0.5 | N85: 0.45 | O85: 0.38 | P85: 0.36 | Q85: 0.39 | R85: 0.42 | S85: 0.53 | T85: 0.52 | U85: 0.53 | V85: 0.52
A86: 7.12 | B86: 7 | C86: Water stress (WRI Aqueduct) | D86: level | E86: 1 | F86: 1 | G86: 3 | H86: 0 | I86: 4 | J86: 2 | K86: 2 | L86: 4 | M86: 4 | N86: 0 | O86: 0 | P86: 1 | Q86: 0 | R86: 1 | S86: 1 | T86: 2 | U86: 0 | V86: 2
A87: 7.13 | B87: 7 | C87: Recovery speed: years for GDP to regain level after last major disaster | D87: years | E87: 1 | F87: 1 | G87: 1 | H87: 1 | I87: 1 | J87: 2 | K87: 1 | L87: 1 | M87: 2 | N87: 2 | O87: 1 | P87: 1 | Q87: 1 | R87: 6 | S87: 1 | T87: 1 | U87: 2 | V87: 3

Sheet Stress Inputs
A1: Stress Inputs: Randori combined shock on the eight stress-path indicators
A2: All cells are formulas built from Inputs, Country Profile and the stress parameters on Assumptions. Blank rows are not stress-path indicators. The scorecard uses the worse of the baseline and stress scores.
A4: {=Rulebook!A4:D87} -> ID | B4: Pillar | C4: Indicator | D4: Unit | E4: =Inputs!E4 -> Vietnam | F4: =Inputs!F4 -> Philippines | G4: =Inputs!G4 -> China | H4: =Inputs!H4 -> Malaysia | I4: =Inputs!I4 -> Singapore | J4: =Inputs!J4 -> Japan | K4: =Inputs!K4 -> South Korea | L4: =Inputs!L4 -> India | ... V4: =Inputs!V4 -> Zimbabwe
A5: 1.1 | B5: 1 | C5: Debt service (interest plus principal) | D5: % of revenue
A6: 1.2 | B6: 1 | C6: FX debt service due in next 24 months | D6: % of FX reserves
A7: 1.3 | B7: 1 | C7: Gross government debt | D7: % of GDP | E7: =Inputs!E7*(1+Inputs!E9/100*E$90/100)/(1+E$92/100)+Assumptions!$B$30*ABS(E$92) -> 36.041327 | F7: =Inputs!F7*(1+Inputs!F9/100*F$90/100)/(1+F$92/100)+Assumptions!$B$30*ABS(F$92) -> 65.620408 | G7: =Inputs!G7*(1+Inputs!G9/100*G$90/100)/(1+G$92/100)+Assumptions!$B$30*ABS(G$92) -> 107.4502 | H7: =Inputs!H7*(1+Inputs!H9/100*H$90/100)/(1+H$92/100)+Assumptions!$B$30*ABS(H$92) -> 71.635918 | I7: =Inputs!I7*(1+Inputs!I9/100*I$90/100)/(1+I$92/100)+Assumptions!$B$30*ABS(I$92) -> 179.17143 | J7: =Inputs!J7*(1+Inputs!J9/100*J$90/100)/(1+J$92/100)+Assumptions!$B$30*ABS(J$92) -> 204.06939 | K7: =Inputs!K7*(1+Inputs!K9/100*K$90/100)/(1+K$92/100)+Assumptions!$B$30*ABS(K$92) -> 49.154898 | L7: =Inputs!L7*(1+Inputs!L9/100*L$90/100)/(1+L$92/100)+Assumptions!$B$30*ABS(L$92) -> 86.031888 | ... V7: =Inputs!V7*(1+Inputs!V9/100*V$90/100)/(1+V$92/100)+Assumptions!$B$30*ABS(V$92) -> 86.314286
A8: 1.4 | B8: 1 | C8: Gross financing need | D8: % of GDP | E8: =Inputs!E8+Assumptions!$B$30*ABS(E$92)+Inputs!E7*Assumptions!$B$28*Assumptions!$B$29/100 -> 6.765 | F8: =Inputs!F8+Assumptions!$B$30*ABS(F$92)+Inputs!F7*Assumptions!$B$28*Assumptions!$B$29/100 -> 10.9 | G8: =Inputs!G8+Assumptions!$B$30*ABS(G$92)+Inputs!G7*Assumptions!$B$28*Assumptions!$B$29/100 -> 19.122 | H8: =Inputs!H8+Assumptions!$B$30*ABS(H$92)+Inputs!H7*Assumptions!$B$28*Assumptions!$B$29/100 -> 12.946 | I8: =Inputs!I8+Assumptions!$B$30*ABS(I$92)+Inputs!I7*Assumptions!$B$28*Assumptions!$B$29/100 -> 3.475 | J8: =Inputs!J8+Assumptions!$B$30*ABS(J$92)+Inputs!J7*Assumptions!$B$28*Assumptions!$B$29/100 -> 41.597 | K8: =Inputs!K8+Assumptions!$B$30*ABS(K$92)+Inputs!K7*Assumptions!$B$28*Assumptions!$B$29/100 -> 5.8365 | L8: =Inputs!L8+Assumptions!$B$30*ABS(L$92)+Inputs!L7*Assumptions!$B$28*Assumptions!$B$29/100 -> 15.0155 | ... V8: =Inputs!V8+Assumptions!$B$30*ABS(V$92)+Inputs!V7*Assumptions!$B$28*Assumptions!$B$29/100 -> 8.975
A9: 1.5 | B9: 1 | C9: Foreign-currency share of government debt | D9: % of debt
A10: 1.6 | B10: 1 | C10: Primary balance gap (actual minus debt-stabilizing) | D10: pp of GDP | E10: =Inputs!E10-Assumptions!$B$30*ABS(E$92)-Inputs!E7/100*(Assumptions!$B$28*Assumptions!$B$29+ABS(E$92)) -> -0.925 | F10: =Inputs!F10-Assumptions!$B$30*ABS(F$92)-Inputs!F7/100*(Assumptions!$B$28*Assumptions!$B$29+ABS(F$92)) -> -3.1 | G10: =Inputs!G10-Assumptions!$B$30*ABS(G$92)-Inputs!G7/100*(Assumptions!$B$28*Assumptions!$B$29+ABS(G$92)) -> -7.71 | H10: =Inputs!H10-Assumptions!$B$30*ABS(H$92)-Inputs!H7/100*(Assumptions!$B$28*Assumptions!$B$29+ABS(H$92)) -> -2.83 | I10: =Inputs!I10-Assumptions!$B$30*ABS(I$92)-Inputs!I7/100*(Assumptions!$B$28*Assumptions!$B$29+ABS(I$92)) -> -2.975 | J10: =Inputs!J10-Assumptions!$B$30*ABS(J$92)-Inputs!J7/100*(Assumptions!$B$28*Assumptions!$B$29+ABS(J$92)) -> -7.585 | K10: =Inputs!K10-Assumptions!$B$30*ABS(K$92)-Inputs!K7/100*(Assumptions!$B$28*Assumptions!$B$29+ABS(K$92)) -> -2.2825 | L10: =Inputs!L10-Assumptions!$B$30*ABS(L$92)-Inputs!L7/100*(Assumptions!$B$28*Assumptions!$B$29+ABS(L$92)) -> -4.1775 | ... V10: =Inputs!V10-Assumptions!$B$30*ABS(V$92)-Inputs!V7/100*(Assumptions!$B$28*Assumptions!$B$29+ABS(V$92)) -> -3.475
A11: 1.7 | B11: 1 | C11: Change in debt/GDP over five years | D11: pp of GDP | E11: =Inputs!E11+(E7-Inputs!E7) -> -2.9586735 | F11: =Inputs!F11+(F7-Inputs!F7) -> 7.6204082 | G11: =Inputs!G11+(G7-Inputs!G7) -> 36.850204 | H11: =Inputs!H11+(H7-Inputs!H7) -> 3.9359184 | I11: =Inputs!I11+(I7-Inputs!I7) -> 29.171429 | J11: =Inputs!J11+(J7-Inputs!J7) -> -24.730612 | K11: =Inputs!K11+(K7-Inputs!K7) -> 3.254898 | L11: =Inputs!L11+(L7-Inputs!L7) -> -4.3681122 | ... V11: =Inputs!V11+(V7-Inputs!V7) -> -8.6857143
A12: 1.8 | B12: 1 | C12: Default record: restructurings or defaults, past 20 years | D12: count
A13: 1.9 | B13: 1 | C13: Contingent liabilities and arrears | D13: level
A14: 2.1 | B14: 2 | C14: Net usable reserves | D14: % of IMF ARA metric | E14: =IF(OR('Country Profile'!E13="Peg",'Country Profile'!E13="Dollarized"),Inputs!E14*MAX(0,1-E$91/'Country Profile'!E9),Inputs!E14) -> 75 | F14: =IF(OR('Country Profile'!F13="Peg",'Country Profile'!F13="Dollarized"),Inputs!F14*MAX(0,1-F$91/'Country Profile'!F9),Inputs!F14) -> 160 | G14: =IF(OR('Country Profile'!G13="Peg",'Country Profile'!G13="Dollarized"),Inputs!G14*MAX(0,1-G$91/'Country Profile'!G9),Inputs!G14) -> 120 | H14: =IF(OR('Country Profile'!H13="Peg",'Country Profile'!H13="Dollarized"),Inputs!H14*MAX(0,1-H$91/'Country Profile'!H9),Inputs!H14) -> 110 | I14: =IF(OR('Country Profile'!I13="Peg",'Country Profile'!I13="Dollarized"),Inputs!I14*MAX(0,1-I$91/'Country Profile'!I9),Inputs!I14) -> 250 | J14: =IF(OR('Country Profile'!J13="Peg",'Country Profile'!J13="Dollarized"),Inputs!J14*MAX(0,1-J$91/'Country Profile'!J9),Inputs!J14) -> 300 | K14: =IF(OR('Country Profile'!K13="Peg",'Country Profile'!K13="Dollarized"),Inputs!K14*MAX(0,1-K$91/'Country Profile'!K9),Inputs!K14) -> 100 | L14: =IF(OR('Country Profile'!L13="Peg",'Country Profile'!L13="Dollarized"),Inputs!L14*MAX(0,1-L$91/'Country Profile'!L9),Inputs!L14) -> 150 | ... V14: =IF(OR('Country Profile'!V13="Peg",'Country Profile'!V13="Dollarized"),Inputs!V14*MAX(0,1-V$91/'Country Profile'!V9),Inputs!V14) -> 15
A15: 2.2 | B15: 2 | C15: External financing need (CA deficit + external debt due in 12m) | D15: % of net reserves
A16: 2.3 | B16: 2 | C16: Hot money (non-resident local debt + portfolio due in 1y) | D16: % of net reserves
A17: 2.4 | B17: 2 | C17: Dollarized banks: FX deposits | D17: % of deposits
A18: 2.5 | B18: 2 | C18: Exchange regime and convertibility | D18: level
A19: 2.6 | B19: 2 | C19: Official backstop: support available vs reliance | D19: level
A20: 2.7 | B20: 2 | C20: Access to the dollar banking system | D20: level
A21: 2.8 | B21: 2 | C21: Current account balance | D21: % of GDP | E21: =Inputs!E21-E$91 -> 0.85 | F21: =Inputs!F21-F$91 -> -4.985 | G21: =Inputs!G21-G$91 -> 3.525 | H21: =Inputs!H21-H$91 -> -1.22 | I21: =Inputs!I21-I$91 -> 12.75 | J21: =Inputs!J21-J$91 -> 4.06 | K21: =Inputs!K21-K$91 -> 2.9 | L21: =Inputs!L21-L$91 -> -1.42 | ... V21: =Inputs!V21-V$91 -> -3.25
A22: 2.9 | B22: 2 | C22: Short-term external debt | D22: % of net reserves
A23: 2.10 | B23: 2 | C23: External debt | D23: % of exports of goods and services
A24: 2.11 | B24: 2 | C24: Export concentration: largest commodity or sector | D24: % of exports
A25: 2.12 | B25: 2 | C25: Real exchange rate vs 10-year average | D25: % above average
A26: 3.1 | B26: 3 | C26: Record on investor treatment, past 20 years | D26: level
A27: 3.2 | B27: 3 | C27: Arbitration award compliance | D27: level
A28: 3.3 | B28: 3 | C28: Treaty protection | D28: level
A29: 3.4 | B29: 3 | C29: Direction of change: 3-year change in WGI composite | D29: percentile points
A30: 3.5 | B30: 3 | C30: WGI composite (rule of law, corruption, regulatory quality) | D30: percentile
A31: 3.6 | B31: 3 | C31: Courts and legislature constrain the executive (V-Dem) | D31: index 0-1
A32: 3.7 | B32: 3 | C32: Civil justice and contract enforcement (WJP) | D32: index 0-1
A33: 3.8 | B33: 3 | C33: Budget and data credibility | D33: level
... A50: 5.4 | B50: 5 | C50: Commodity link: real credit growth vs main export price | D50: correlation
A51: 5.5 | B51: 5 | C51: Inflation, 12 months | D51: % | E51: =Inputs!E51+Assumptions!$B$34*E$90 -> 8 | F51: =Inputs!F51+Assumptions!$B$34*F$90 -> 8.5 | G51: =Inputs!G51+Assumptions!$B$34*G$90 -> 5.5 | H51: =Inputs!H51+Assumptions!$B$34*H$90 -> 8.2 | I51: =Inputs!I51+Assumptions!$B$34*I$90 -> 6 | J51: =Inputs!J51+Assumptions!$B$34*J$90 -> 8.5 | K51: =Inputs!K51+Assumptions!$B$34*K$90 -> 8 | L51: =Inputs!L51+Assumptions!$B$34*L$90 -> 8.3 | ... V51: =Inputs!V51+Assumptions!$B$34*V$90 -> 34.5
A52: 5.6 | B52: 5 | C52: Real GDP growth next year | D52: % | E52: =Inputs!E52+E$92 -> 4 | F52: =Inputs!F52+F$92 -> 3.8 | G52: =Inputs!G52+G$92 -> 2 | H52: =Inputs!H52+H$92 -> 2.2 | I52: =Inputs!I52+I$92 -> 0.3 | J52: =Inputs!J52+J$92 -> -1.4 | K52: =Inputs!K52+K$92 -> -0.1 | L52: =Inputs!L52+L$92 -> 4.4 | ... V52: =Inputs!V52+V$92 -> 1
A53: 5.7 | B53: 5 | C53: State-owned banks | D53: % of bank assets
A54: 5.8 | B54: 5 | C54: Lenders outside the banks | D54: level
A55: 5.9 | B55: 5 | C55: Credit-to-GDP gap | D55: pp of GDP
A56: 5.10 | B56: 5 | C56: Non-performing loans, system-wide | D56: % of loans
A57: 5.11 | B57: 5 | C57: Real deposit growth, 12 months | D57: %
A58: 5.12 | B58: 5 | C58: Growth volatility: SD of real GDP growth, 15y (ex 2020-21) | D58: pp
A59: 5.13 | B59: 5 | C59: Real policy rate (two-sided: 0 to +4 scores 0) | D59: %
A60: 5.14 | B60: 5 | C60: GDP per person | D60: US$
A61: 6.1 | B61: 6 | C61: Armed conflict on national territory, past 12 months | D61: level
A62: 6.2 | B62: 6 | C62: Homicide rate | D62: per 100,000
A63: 6.3 | B63: 6 | C63: Gang control and extortion | D63: level
A64: 6.4 | B64: 6 | C64: Attacks on business and staff | D64: level
... A87: 7.13 | B87: 7 | C87: Recovery speed: years for GDP to regain level after last major disaster | D87: years
C89: Stress helpers
C90: Stress depreciation | D90: % | E90: =IFS('Country Profile'!E13="Float",Assumptions!$B$24,'Country Profile'!E13="Managed",Assumptions!$B$25,TRUE,Assumptions!$B$26) -> 15 | F90: =IFS('Country Profile'!F13="Float",Assumptions!$B$24,'Country Profile'!F13="Managed",Assumptions!$B$25,TRUE,Assumptions!$B$26) -> 20 | G90: =IFS('Country Profile'!G13="Float",Assumptions!$B$24,'Country Profile'!G13="Managed",Assumptions!$B$25,TRUE,Assumptions!$B$26) -> 15 | H90: =IFS('Country Profile'!H13="Float",Assumptions!$B$24,'Country Profile'!H13="Managed",Assumptions!$B$25,TRUE,Assumptions!$B$26) -> 20 | I90: =IFS('Country Profile'!I13="Float",Assumptions!$B$24,'Country Profile'!I13="Managed",Assumptions!$B$25,TRUE,Assumptions!$B$26) -> 15 | J90: =IFS('Country Profile'!J13="Float",Assumptions!$B$24,'Country Profile'!J13="Managed",Assumptions!$B$25,TRUE,Assumptions!$B$26) -> 20 | K90: =IFS('Country Profile'!K13="Float",Assumptions!$B$24,'Country Profile'!K13="Managed",Assumptions!$B$25,TRUE,Assumptions!$B$26) -> 20 | L90: =IFS('Country Profile'!L13="Float",Assumptions!$B$24,'Country Profile'!L13="Managed",Assumptions!$B$25,TRUE,Assumptions!$B$26) -> 15 | ... V90: =IFS('Country Profile'!V13="Float",Assumptions!$B$24,'Country Profile'!V13="Managed",Assumptions!$B$25,TRUE,Assumptions!$B$26) -> 15
C91: Export shock | D91: % of GDP | E91: =ABS(IFS('Country Profile'!E11="Commodity",Assumptions!$B$31,'Country Profile'!E11="Tourism",Assumptions!$B$32,TRUE,Assumptions!$B$33))/100*'Country Profile'!E8*Inputs!E24/100 -> 3.15 | F91: =ABS(IFS('Country Profile'!F11="Commodity",Assumptions!$B$31,'Country Profile'!F11="Tourism",Assumptions!$B$32,TRUE,Assumptions!$B$33))/100*'Country Profile'!F8*Inputs!F24/100 -> 1.485 | G91: =ABS(IFS('Country Profile'!G11="Commodity",Assumptions!$B$31,'Country Profile'!G11="Tourism",Assumptions!$B$32,TRUE,Assumptions!$B$33))/100*'Country Profile'!G8*Inputs!G24/100 -> 0.475 | H91: =ABS(IFS('Country Profile'!H11="Commodity",Assumptions!$B$31,'Country Profile'!H11="Tourism",Assumptions!$B$32,TRUE,Assumptions!$B$33))/100*'Country Profile'!H8*Inputs!H24/100 -> 2.72 | I91: =ABS(IFS('Country Profile'!I11="Commodity",Assumptions!$B$31,'Country Profile'!I11="Tourism",Assumptions!$B$32,TRUE,Assumptions!$B$33))/100*'Country Profile'!I8*Inputs!I24/100 -> 5.25 | J91: =ABS(IFS('Country Profile'!J11="Commodity",Assumptions!$B$31,'Country Profile'!J11="Tourism",Assumptions!$B$32,TRUE,Assumptions!$B$33))/100*'Country Profile'!J8*Inputs!J24/100 -> 0.44 | K91: =ABS(IFS('Country Profile'!K11="Commodity",Assumptions!$B$31,'Country Profile'!K11="Tourism",Assumptions!$B$32,TRUE,Assumptions!$B$33))/100*'Country Profile'!K8*Inputs!K24/100 -> 1.1 | L91: =ABS(IFS('Country Profile'!L11="Commodity",Assumptions!$B$31,'Country Profile'!L11="Tourism",Assumptions!$B$32,TRUE,Assumptions!$B$33))/100*'Country Profile'!L8*Inputs!L24/100 -> 0.42 | ... V91: =ABS(IFS('Country Profile'!V11="Commodity",Assumptions!$B$31,'Country Profile'!V11="Tourism",Assumptions!$B$32,TRUE,Assumptions!$B$33))/100*'Country Profile'!V8*Inputs!V24/100 -> 3.75
C92: Growth shock | D92: pp | E92: =Assumptions!$B$27 -> -2 | F92: =Assumptions!$B$27 -> -2 | G92: =Assumptions!$B$27 -> -2 | H92: =Assumptions!$B$27 -> -2 | I92: =Assumptions!$B$27 -> -2 | J92: =Assumptions!$B$27 -> -2 | K92: =Assumptions!$B$27 -> -2 | L92: =Assumptions!$B$27 -> -2 | ... V92: =Assumptions!$B$27 -> -2

Sheet Base Scores
A1: Base Scores: indicator scores on baseline inputs (0 = lowest risk, 100 = highest)
A2: Straight-line interpolation between the Rulebook threshold points; values beyond the ends score 0 or 100.
A4: {=Rulebook!A4:D87} -> ID | B4: Pillar | C4: Indicator | D4: Unit | E4: =Inputs!E4 -> Vietnam | F4: =Inputs!F4 -> Philippines | G4: =Inputs!G4 -> China | H4: =Inputs!H4 -> Malaysia | I4: =Inputs!I4 -> Singapore | J4: =Inputs!J4 -> Japan | K4: =Inputs!K4 -> South Korea | L4: =Inputs!L4 -> India | ... V4: =Inputs!V4 -> Zimbabwe
A5: 1.1 | B5: 1 | C5: Debt service (interest plus principal) | D5: % of revenue | E5: =IF(Inputs!E5="","",LET(d,Rulebook!$L5,x,Inputs!E5*d,ta,Rulebook!$G5*d,tb,Rulebook!$H5*d,tc,Rulebook!$I5*d,te,Rulebook!$J5*d,tf,Rulebook!$K5*d,IFS(x<=ta,0,x<=tb,25*(x-ta)/(tb-ta),x<=tc,25+25*(x-tb)/(tc-tb),x<=te,50+25*(x-tc)/(te-tc),x<tf,75+25*(x-te)/(tf-te),TRUE,100))) -> 12.5 | F5: =IF(Inputs!F5="","",LET(d,Rulebook!$L5,x,Inputs!F5*d,ta,Rulebook!$G5*d,tb,Rulebook!$H5*d,tc,Rulebook!$I5*d,te,Rulebook!$J5*d,tf,Rulebook!$K5*d,IFS(x<=ta,0,x<=tb,25*(x-ta)/(tb-ta),x<=tc,25+25*(x-tb)/(tc-tb),x<=te,50+25*(x-tc)/(te-tc),x<tf,75+25*(x-te)/(tf-te),TRUE,100))) -> 66.666667 | G5: =IF(Inputs!G5="","",LET(d,Rulebook!$L5,x,Inputs!G5*d,ta,Rulebook!$G5*d,tb,Rulebook!$H5*d,tc,Rulebook!$I5*d,te,Rulebook!$J5*d,tf,Rulebook!$K5*d,IFS(x<=ta,0,x<=tb,25*(x-ta)/(tb-ta),x<=tc,25+25*(x-tb)/(tc-tb),x<=te,50+25*(x-tc)/(te-tc),x<tf,75+25*(x-te)/(tf-te),TRUE,100))) -> 5 | H5: =IF(Inputs!H5="","",LET(d,Rulebook!$L5,x,Inputs!H5*d,ta,Rulebook!$G5*d,tb,Rulebook!$H5*d,tc,Rulebook!$I5*d,te,Rulebook!$J5*d,tf,Rulebook!$K5*d,IFS(x<=ta,0,x<=tb,25*(x-ta)/(tb-ta),x<=tc,25+25*(x-tb)/(tc-tb),x<=te,50+25*(x-tc)/(te-tc),x<tf,75+25*(x-te)/(tf-te),TRUE,100))) -> 50 | I5: =IF(Inputs!I5="","",LET(d,Rulebook!$L5,x,Inputs!I5*d,ta,Rulebook!$G5*d,tb,Rulebook!$H5*d,tc,Rulebook!$I5*d,te,Rulebook!$J5*d,tf,Rulebook!$K5*d,IFS(x<=ta,0,x<=tb,25*(x-ta)/(tb-ta),x<=tc,25+25*(x-tb)/(tc-tb),x<=te,50+25*(x-tc)/(te-tc),x<tf,75+25*(x-te)/(tf-te),TRUE,100))) -> 0 | J5: =IF(Inputs!J5="","",LET(d,Rulebook!$L5,x,Inputs!J5*d,ta,Rulebook!$G5*d,tb,Rulebook!$H5*d,tc,Rulebook!$I5*d,te,Rulebook!$J5*d,tf,Rulebook!$K5*d,IFS(x<=ta,0,x<=tb,25*(x-ta)/(tb-ta),x<=tc,25+25*(x-tb)/(tc-tb),x<=te,50+25*(x-tc)/(te-tc),x<tf,75+25*(x-te)/(tf-te),TRUE,100))) -> 50 | K5: =IF(Inputs!K5="","",LET(d,Rulebook!$L5,x,Inputs!K5*d,ta,Rulebook!$G5*d,tb,Rulebook!$H5*d,tc,Rulebook!$I5*d,te,Rulebook!$J5*d,tf,Rulebook!$K5*d,IFS(x<=ta,0,x<=tb,25*(x-ta)/(tb-ta),x<=tc,25+25*(x-tb)/(tc-tb),x<=te,50+25*(x-tc)/(te-tc),x<tf,75+25*(x-te)/(tf-te),TRUE,100))) -> 0 | L5: =IF(Inputs!L5="","",LET(d,Rulebook!$L5,x,Inputs!L5*d,ta,Rulebook!$G5*d,tb,Rulebook!$H5*d,tc,Rulebook!$I5*d,te,Rulebook!$J5*d,tf,Rulebook!$K5*d,IFS(x<=ta,0,x<=tb,25*(x-ta)/(tb-ta),x<=tc,25+25*(x-tb)/(tc-tb),x<=te,50+25*(x-tc)/(te-tc),x<tf,75+25*(x-te)/(tf-te),TRUE,100))) -> 75 | ... V5: =IF(Inputs!V5="","",LET(d,Rulebook!$L5,x,Inputs!V5*d,ta,Rulebook!$G5*d,tb,Rulebook!$H5*d,tc,Rulebook!$I5*d,te,Rulebook!$J5*d,tf,Rulebook!$K5*d,IFS(x<=ta,0,x<=tb,25*(x-ta)/(tb-ta),x<=tc,25+25*(x-tb)/(tc-tb),x<=te,50+25*(x-tc)/(te-tc),x<tf,75+25*(x-te)/(tf-te),TRUE,100))) -> 58.333333
A6: 1.2 | B6: 1 | C6: FX debt service due in next 24 months | D6: % of FX reserves | E6: =IF(Inputs!E6="","",LET(d,Rulebook!$L6,x,Inputs!E6*d,ta,Rulebook!$G6*d,tb,Rulebook!$H6*d,tc,Rulebook!$I6*d,te,Rulebook!$J6*d,tf,Rulebook!$K6*d,IFS(x<=ta,0,x<=tb,25*(x-ta)/(tb-ta),x<=tc,25+25*(x-tb)/(tc-tb),x<=te,50+25*(x-tc)/(te-tc),x<tf,75+25*(x-te)/(tf-te),TRUE,100))) -> 0 | F6: =IF(Inputs!F6="","",LET(d,Rulebook!$L6,x,Inputs!F6*d,ta,Rulebook!$G6*d,tb,Rulebook!$H6*d,tc,Rulebook!$I6*d,te,Rulebook!$J6*d,tf,Rulebook!$K6*d,IFS(x<=ta,0,x<=tb,25*(x-ta)/(tb-ta),x<=tc,25+25*(x-tb)/(tc-tb),x<=te,50+25*(x-tc)/(te-tc),x<tf,75+25*(x-te)/(tf-te),TRUE,100))) -> 8.3333333 | G6: =IF(Inputs!G6="","",LET(d,Rulebook!$L6,x,Inputs!G6*d,ta,Rulebook!$G6*d,tb,Rulebook!$H6*d,tc,Rulebook!$I6*d,te,Rulebook!$J6*d,tf,Rulebook!$K6*d,IFS(x<=ta,0,x<=tb,25*(x-ta)/(tb-ta),x<=tc,25+25*(x-tb)/(tc-tb),x<=te,50+25*(x-tc)/(te-tc),x<tf,75+25*(x-te)/(tf-te),TRUE,100))) -> 0 | H6: =IF(Inputs!H6="","",LET(d,Rulebook!$L6,x,Inputs!H6*d,ta,Rulebook!$G6*d,tb,Rulebook!$H6*d,tc,Rulebook!$I6*d,te,Rulebook!$J6*d,tf,Rulebook!$K6*d,IFS(x<=ta,0,x<=tb,25*(x-ta)/(tb-ta),x<=tc,25+25*(x-tb)/(tc-tb),x<=te,50+25*(x-tc)/(te-tc),x<tf,75+25*(x-te)/(tf-te),TRUE,100))) -> 0 | I6: =IF(Inputs!I6="","",LET(d,Rulebook!$L6,x,Inputs!I6*d,ta,Rulebook!$G6*d,tb,Rulebook!$H6*d,tc,Rulebook!$I6*d,te,Rulebook!$J6*d,tf,Rulebook!$K6*d,IFS(x<=ta,0,x<=tb,25*(x-ta)/(tb-ta),x<=tc,25+25*(x-tb)/(tc-tb),x<=te,50+25*(x-tc)/(te-tc),x<tf,75+25*(x-te)/(tf-te),TRUE,100))) -> 0 | J6: =IF(Inputs!J6="","",LET(d,Rulebook!$L6,x,Inputs!J6*d,ta,Rulebook!$G6*d,tb,Rulebook!$H6*d,tc,Rulebook!$I6*d,te,Rulebook!$J6*d,tf,Rulebook!$K6*d,IFS(x<=ta,0,x<=tb,25*(x-ta)/(tb-ta),x<=tc,25+25*(x-tb)/(tc-tb),x<=te,50+25*(x-tc)/(te-tc),x<tf,75+25*(x-te)/(tf-te),TRUE,100))) -> 0 | K6: =IF(Inputs!K6="","",LET(d,Rulebook!$L6,x,Inputs!K6*d,ta,Rulebook!$G6*d,tb,Rulebook!$H6*d,tc,Rulebook!$I6*d,te,Rulebook!$J6*d,tf,Rulebook!$K6*d,IFS(x<=ta,0,x<=tb,25*(x-ta)/(tb-ta),x<=tc,25+25*(x-tb)/(tc-tb),x<=te,50+25*(x-tc)/(te-tc),x<tf,75+25*(x-te)/(tf-te),TRUE,100))) -> 0 | L6: =IF(Inputs!L6="","",LET(d,Rulebook!$L6,x,Inputs!L6*d,ta,Rulebook!$G6*d,tb,Rulebook!$H6*d,tc,Rulebook!$I6*d,te,Rulebook!$J6*d,tf,Rulebook!$K6*d,IFS(x<=ta,0,x<=tb,25*(x-ta)/(tb-ta),x<=tc,25+25*(x-tb)/(tc-tb),x<=te,50+25*(x-tc)/(te-tc),x<tf,75+25*(x-te)/(tf-te),TRUE,100))) -> 0 | ... V6: =IF(Inputs!V6="","",LET(d,Rulebook!$L6,x,Inputs!V6*d,ta,Rulebook!$G6*d,tb,Rulebook!$H6*d,tc,Rulebook!$I6*d,te,Rulebook!$J6*d,tf,Rulebook!$K6*d,IFS(x<=ta,0,x<=tb,25*(x-ta)/(tb-ta),x<=tc,25+25*(x-tb)/(tc-tb),x<=te,50+25*(x-tc)/(te-tc),x<tf,75+25*(x-te)/(tf-te),TRUE,100))) -> 100
A7: 1.3 | B7: 1 | C7: Gross government debt | D7: % of GDP | E7: =IF(Inputs!E7="","",LET(d,Rulebook!$L7,x,Inputs!E7*d,ta,Rulebook!$G7*d,tb,Rulebook!$H7*d,tc,Rulebook!$I7*d,te,Rulebook!$J7*d,tf,Rulebook!$K7*d,IFS(x<=ta,0,x<=tb,25*(x-ta)/(tb-ta),x<=tc,25+25*(x-tb)/(tc-tb),x<=te,50+25*(x-tc)/(te-tc),x<tf,75+25*(x-te)/(tf-te),TRUE,100))) -> 5 | F7: =IF(Inputs!F7="","",LET(d,Rulebook!$L7,x,Inputs!F7*d,ta,Rulebook!$G7*d,tb,Rulebook!$H7*d,tc,Rulebook!$I7*d,te,Rulebook!$J7*d,tf,Rulebook!$K7*d,IFS(x<=ta,0,x<=tb,25*(x-ta)/(tb-ta),x<=tc,25+25*(x-tb)/(tc-tb),x<=te,50+25*(x-tc)/(te-tc),x<tf,75+25*(x-te)/(tf-te),TRUE,100))) -> 50 | G7: =IF(Inputs!G7="","",LET(d,Rulebook!$L7,x,Inputs!G7*d,ta,Rulebook!$G7*d,tb,Rulebook!$H7*d,tc,Rulebook!$I7*d,te,Rulebook!$J7*d,tf,Rulebook!$K7*d,IFS(x<=ta,0,x<=tb,25*(x-ta)/(tb-ta),x<=tc,25+25*(x-tb)/(tc-tb),x<=te,50+25*(x-tc)/(te-tc),x<tf,75+25*(x-te)/(tf-te),TRUE,100))) -> 100 | H7: =IF(Inputs!H7="","",LET(d,Rulebook!$L7,x,Inputs!H7*d,ta,Rulebook!$G7*d,tb,Rulebook!$H7*d,tc,Rulebook!$I7*d,te,Rulebook!$J7*d,tf,Rulebook!$K7*d,IFS(x<=ta,0,x<=tb,25*(x-ta)/(tb-ta),x<=tc,25+25*(x-tb)/(tc-tb),x<=te,50+25*(x-tc)/(te-tc),x<tf,75+25*(x-te)/(tf-te),TRUE,100))) -> 61.5 | I7: =IF(Inputs!I7="","",LET(d,Rulebook!$L7,x,Inputs!I7*d,ta,Rulebook!$G7*d,tb,Rulebook!$H7*d,tc,Rulebook!$I7*d,te,Rulebook!$J7*d,tf,Rulebook!$K7*d,IFS(x<=ta,0,x<=tb,25*(x-ta)/(tb-ta),x<=tc,25+25*(x-tb)/(tc-tb),x<=te,50+25*(x-tc)/(te-tc),x<tf,75+25*(x-te)/(tf-te),TRUE,100))) -> 100 | J7: =IF(Inputs!J7="","",LET(d,Rulebook!$L7,x,Inputs!J7*d,ta,Rulebook!$G7*d,tb,Rulebook!$H7*d,tc,Rulebook!$I7*d,te,Rulebook!$J7*d,tf,Rulebook!$K7*d,IFS(x<=ta,0,x<=tb,25*(x-ta)/(tb-ta),x<=tc,25+25*(x-tb)/(tc-tb),x<=te,50+25*(x-tc)/(te-tc),x<tf,75+25*(x-te)/(tf-te),TRUE,100))) -> 100 | K7: =IF(Inputs!K7="","",LET(d,Rulebook!$L7,x,Inputs!K7*d,ta,Rulebook!$G7*d,tb,Rulebook!$H7*d,tc,Rulebook!$I7*d,te,Rulebook!$J7*d,tf,Rulebook!$K7*d,IFS(x<=ta,0,x<=tb,25*(x-ta)/(tb-ta),x<=tc,25+25*(x-tb)/(tc-tb),x<=te,50+25*(x-tc)/(te-tc),x<tf,75+25*(x-te)/(tf-te),TRUE,100))) -> 28.833333 | L7: =IF(Inputs!L7="","",LET(d,Rulebook!$L7,x,Inputs!L7*d,ta,Rulebook!$G7*d,tb,Rulebook!$H7*d,tc,Rulebook!$I7*d,te,Rulebook!$J7*d,tf,Rulebook!$K7*d,IFS(x<=ta,0,x<=tb,25*(x-ta)/(tb-ta),x<=tc,25+25*(x-tb)/(tc-tb),x<=te,50+25*(x-tc)/(te-tc),x<tf,75+25*(x-te)/(tf-te),TRUE,100))) -> 78.875 | ... V7: =IF(Inputs!V7="","",LET(d,Rulebook!$L7,x,Inputs!V7*d,ta,Rulebook!$G7*d,tb,Rulebook!$H7*d,tc,Rulebook!$I7*d,te,Rulebook!$J7*d,tf,Rulebook!$K7*d,IFS(x<=ta,0,x<=tb,25*(x-ta)/(tb-ta),x<=tc,25+25*(x-tb)/(tc-tb),x<=te,50+25*(x-tc)/(te-tc),x<tf,75+25*(x-te)/(tf-te),TRUE,100))) -> 68.75
A8: 1.4 | B8: 1 | C8: Gross financing need | D8: % of GDP | E8: =IF(Inputs!E8="","",LET(d,Rulebook!$L8,x,Inputs!E8*d,ta,Rulebook!$G8*d,tb,Rulebook!$H8*d,tc,Rulebook!$I8*d,te,Rulebook!$J8*d,tf,Rulebook!$K8*d,IFS(x<=ta,0,x<=tb,25*(x-ta)/(tb-ta),x<=tc,25+25*(x-tb)/(tc-tb),x<=te,50+25*(x-tc)/(te-tc),x<tf,75+25*(x-te)/(tf-te),TRUE,100))) -> 5 | F8: =IF(Inputs!F8="","",LET(d,Rulebook!$L8,x,Inputs!F8*d,ta,Rulebook!$G8*d,tb,Rulebook!$H8*d,tc,Rulebook!$I8*d,te,Rulebook!$J8*d,tf,Rulebook!$K8*d,IFS(x<=ta,0,x<=tb,25*(x-ta)/(tb-ta),x<=tc,25+25*(x-tb)/(tc-tb),x<=te,50+25*(x-tc)/(te-tc),x<tf,75+25*(x-te)/(tf-te),TRUE,100))) -> 25 | G8: =IF(Inputs!G8="","",LET(d,Rulebook!$L8,x,Inputs!G8*d,ta,Rulebook!$G8*d,tb,Rulebook!$H8*d,tc,Rulebook!$I8*d,te,Rulebook!$J8*d,tf,Rulebook!$K8*d,IFS(x<=ta,0,x<=tb,25*(x-ta)/(tb-ta),x<=tc,25+25*(x-tb)/(tc-tb),x<=te,50+25*(x-tc)/(te-tc),x<tf,75+25*(x-te)/(tf-te),TRUE,100))) -> 65 | H8: =IF(Inputs!H8="","",LET(d,Rulebook!$L8,x,Inputs!H8*d,ta,Rulebook!$G8*d,tb,Rulebook!$H8*d,tc,Rulebook!$I8*d,te,Rulebook!$J8*d,tf,Rulebook!$K8*d,IFS(x<=ta,0,x<=tb,25*(x-ta)/(tb-ta),x<=tc,25+25*(x-tb)/(tc-tb),x<=te,50+25*(x-tc)/(te-tc),x<tf,75+25*(x-te)/(tf-te),TRUE,100))) -> 35 | I8: =IF(Inputs!I8="","",LET(d,Rulebook!$L8,x,Inputs!I8*d,ta,Rulebook!$G8*d,tb,Rulebook!$H8*d,tc,Rulebook!$I8*d,te,Rulebook!$J8*d,tf,Rulebook!$K8*d,IFS(x<=ta,0,x<=tb,25*(x-ta)/(tb-ta),x<=tc,25+25*(x-tb)/(tc-tb),x<=te,50+25*(x-tc)/(te-tc),x<tf,75+25*(x-te)/(tf-te),TRUE,100))) -> 0 | J8: =IF(Inputs!J8="","",LET(d,Rulebook!$L8,x,Inputs!J8*d,ta,Rulebook!$G8*d,tb,Rulebook!$H8*d,tc,Rulebook!$I8*d,te,Rulebook!$J8*d,tf,Rulebook!$K8*d,IFS(x<=ta,0,x<=tb,25*(x-ta)/(tb-ta),x<=tc,25+25*(x-tb)/(tc-tb),x<=te,50+25*(x-tc)/(te-tc),x<tf,75+25*(x-te)/(tf-te),TRUE,100))) -> 100 | K8: =IF(Inputs!K8="","",LET(d,Rulebook!$L8,x,Inputs!K8*d,ta,Rulebook!$G8*d,tb,Rulebook!$H8*d,tc,Rulebook!$I8*d,te,Rulebook!$J8*d,tf,Rulebook!$K8*d,IFS(x<=ta,0,x<=tb,25*(x-ta)/(tb-ta),x<=tc,25+25*(x-tb)/(tc-tb),x<=te,50+25*(x-tc)/(te-tc),x<tf,75+25*(x-te)/(tf-te),TRUE,100))) -> 0 | L8: =IF(Inputs!L8="","",LET(d,Rulebook!$L8,x,Inputs!L8*d,ta,Rulebook!$G8*d,tb,Rulebook!$H8*d,tc,Rulebook!$I8*d,te,Rulebook!$J8*d,tf,Rulebook!$K8*d,IFS(x<=ta,0,x<=tb,25*(x-ta)/(tb-ta),x<=tc,25+25*(x-tb)/(tc-tb),x<=te,50+25*(x-tc)/(te-tc),x<tf,75+25*(x-te)/(tf-te),TRUE,100))) -> 45 | ... V8: =IF(Inputs!V8="","",LET(d,Rulebook!$L8,x,Inputs!V8*d,ta,Rulebook!$G8*d,tb,Rulebook!$H8*d,tc,Rulebook!$I8*d,te,Rulebook!$J8*d,tf,Rulebook!$K8*d,IFS(x<=ta,0,x<=tb,25*(x-ta)/(tb-ta),x<=tc,25+25*(x-tb)/(tc-tb),x<=te,50+25*(x-tc)/(te-tc),x<tf,75+25*(x-te)/(tf-te),TRUE,100))) -> 15
A9: 1.5 | B9: 1 | C9: Foreign-currency share of government debt | D9: % of debt | E9: =IF(Inputs!E9="","",LET(d,Rulebook!$L9,x,Inputs!E9*d,ta,Rulebook!$G9*d,tb,Rulebook!$H9*d,tc,Rulebook!$I9*d,te,Rulebook!$J9*d,tf,Rulebook!$K9*d,IFS(x<=ta,0,x<=tb,25*(x-ta)/(tb-ta),x<=tc,25+25*(x-tb)/(tc-tb),x<=te,50+25*(x-tc)/(te-tc),x<tf,75+25*(x-te)/(tf-te),TRUE,100))) -> 25 | F9: =IF(Inputs!F9="","",LET(d,Rulebook!$L9,x,Inputs!F9*d,ta,Rulebook!$G9*d,tb,Rulebook!$H9*d,tc,Rulebook!$I9*d,te,Rulebook!$J9*d,tf,Rulebook!$K9*d,IFS(x<=ta,0,x<=tb,25*(x-ta)/(tb-ta),x<=tc,25+25*(x-tb)/(tc-tb),x<=te,50+25*(x-tc)/(te-tc),x<tf,75+25*(x-te)/(tf-te),TRUE,100))) -> 18.333333 | G9: =IF(Inputs!G9="","",LET(d,Rulebook!$L9,x,Inputs!G9*d,ta,Rulebook!$G9*d,tb,Rulebook!$H9*d,tc,Rulebook!$I9*d,te,Rulebook!$J9*d,tf,Rulebook!$K9*d,IFS(x<=ta,0,x<=tb,25*(x-ta)/(tb-ta),x<=tc,25+25*(x-tb)/(tc-tb),x<=te,50+25*(x-tc)/(te-tc),x<tf,75+25*(x-te)/(tf-te),TRUE,100))) -> 0 | H9: =IF(Inputs!H9="","",LET(d,Rulebook!$L9,x,Inputs!H9*d,ta,Rulebook!$G9*d,tb,Rulebook!$H9*d,tc,Rulebook!$I9*d,te,Rulebook!$J9*d,tf,Rulebook!$K9*d,IFS(x<=ta,0,x<=tb,25*(x-ta)/(tb-ta),x<=tc,25+25*(x-tb)/(tc-tb),x<=te,50+25*(x-tc)/(te-tc),x<tf,75+25*(x-te)/(tf-te),TRUE,100))) -> 0 | I9: =IF(Inputs!I9="","",LET(d,Rulebook!$L9,x,Inputs!I9*d,ta,Rulebook!$G9*d,tb,Rulebook!$H9*d,tc,Rulebook!$I9*d,te,Rulebook!$J9*d,tf,Rulebook!$K9*d,IFS(x<=ta,0,x<=tb,25*(x-ta)/(tb-ta),x<=tc,25+25*(x-tb)/(tc-tb),x<=te,50+25*(x-tc)/(te-tc),x<tf,75+25*(x-te)/(tf-te),TRUE,100))) -> 0 | J9: =IF(Inputs!J9="","",LET(d,Rulebook!$L9,x,Inputs!J9*d,ta,Rulebook!$G9*d,tb,Rulebook!$H9*d,tc,Rulebook!$I9*d,te,Rulebook!$J9*d,tf,Rulebook!$K9*d,IFS(x<=ta,0,x<=tb,25*(x-ta)/(tb-ta),x<=tc,25+25*(x-tb)/(tc-tb),x<=te,50+25*(x-tc)/(te-tc),x<tf,75+25*(x-te)/(tf-te),TRUE,100))) -> 0 | K9: =IF(Inputs!K9="","",LET(d,Rulebook!$L9,x,Inputs!K9*d,ta,Rulebook!$G9*d,tb,Rulebook!$H9*d,tc,Rulebook!$I9*d,te,Rulebook!$J9*d,tf,Rulebook!$K9*d,IFS(x<=ta,0,x<=tb,25*(x-ta)/(tb-ta),x<=tc,25+25*(x-tb)/(tc-tb),x<=te,50+25*(x-tc)/(te-tc),x<tf,75+25*(x-te)/(tf-te),TRUE,100))) -> 0 | L9: =IF(Inputs!L9="","",LET(d,Rulebook!$L9,x,Inputs!L9*d,ta,Rulebook!$G9*d,tb,Rulebook!$H9*d,tc,Rulebook!$I9*d,te,Rulebook!$J9*d,tf,Rulebook!$K9*d,IFS(x<=ta,0,x<=tb,25*(x-ta)/(tb-ta),x<=tc,25+25*(x-tb)/(tc-tb),x<=te,50+25*(x-tc)/(te-tc),x<tf,75+25*(x-te)/(tf-te),TRUE,100))) -> 0 | ... V9: =IF(Inputs!V9="","",LET(d,Rulebook!$L9,x,Inputs!V9*d,ta,Rulebook!$G9*d,tb,Rulebook!$H9*d,tc,Rulebook!$I9*d,te,Rulebook!$J9*d,tf,Rulebook!$K9*d,IFS(x<=ta,0,x<=tb,25*(x-ta)/(tb-ta),x<=tc,25+25*(x-tb)/(tc-tb),x<=te,50+25*(x-tc)/(te-tc),x<tf,75+25*(x-te)/(tf-te),TRUE,100))) -> 100
A10: 1.6 | B10: 1 | C10: Primary balance gap (actual minus debt-stabilizing) | D10: pp of GDP | E10: =IF(Inputs!E10="","",LET(d,Rulebook!$L10,x,Inputs!E10*d,ta,Rulebook!$G10*d,tb,Rulebook!$H10*d,tc,Rulebook!$I10*d,te,Rulebook!$J10*d,tf,Rulebook!$K10*d,IFS(x<=ta,0,x<=tb,25*(x-ta)/(tb-ta),x<=tc,25+25*(x-tb)/(tc-tb),x<=te,50+25*(x-tc)/(te-tc),x<tf,75+25*(x-te)/(tf-te),TRUE,100))) -> 0 | F10: =IF(Inputs!F10="","",LET(d,Rulebook!$L10,x,Inputs!F10*d,ta,Rulebook!$G10*d,tb,Rulebook!$H10*d,tc,Rulebook!$I10*d,te,Rulebook!$J10*d,tf,Rulebook!$K10*d,IFS(x<=ta,0,x<=tb,25*(x-ta)/(tb-ta),x<=tc,25+25*(x-tb)/(tc-tb),x<=te,50+25*(x-tc)/(te-tc),x<tf,75+25*(x-te)/(tf-te),TRUE,100))) -> 25 | G10: =IF(Inputs!G10="","",LET(d,Rulebook!$L10,x,Inputs!G10*d,ta,Rulebook!$G10*d,tb,Rulebook!$H10*d,tc,Rulebook!$I10*d,te,Rulebook!$J10*d,tf,Rulebook!$K10*d,IFS(x<=ta,0,x<=tb,25*(x-ta)/(tb-ta),x<=tc,25+25*(x-tb)/(tc-tb),x<=te,50+25*(x-tc)/(te-tc),x<tf,75+25*(x-te)/(tf-te),TRUE,100))) -> 91.666667 | H10: =IF(Inputs!H10="","",LET(d,Rulebook!$L10,x,Inputs!H10*d,ta,Rulebook!$G10*d,tb,Rulebook!$H10*d,tc,Rulebook!$I10*d,te,Rulebook!$J10*d,tf,Rulebook!$K10*d,IFS(x<=ta,0,x<=tb,25*(x-ta)/(tb-ta),x<=tc,25+25*(x-tb)/(tc-tb),x<=te,50+25*(x-tc)/(te-tc),x<tf,75+25*(x-te)/(tf-te),TRUE,100))) -> 12.5 | I10: =IF(Inputs!I10="","",LET(d,Rulebook!$L10,x,Inputs!I10*d,ta,Rulebook!$G10*d,tb,Rulebook!$H10*d,tc,Rulebook!$I10*d,te,Rulebook!$J10*d,tf,Rulebook!$K10*d,IFS(x<=ta,0,x<=tb,25*(x-ta)/(tb-ta),x<=tc,25+25*(x-tb)/(tc-tb),x<=te,50+25*(x-tc)/(te-tc),x<tf,75+25*(x-te)/(tf-te),TRUE,100))) -> 0 | J10: =IF(Inputs!J10="","",LET(d,Rulebook!$L10,x,Inputs!J10*d,ta,Rulebook!$G10*d,tb,Rulebook!$H10*d,tc,Rulebook!$I10*d,te,Rulebook!$J10*d,tf,Rulebook!$K10*d,IFS(x<=ta,0,x<=tb,25*(x-ta)/(tb-ta),x<=tc,25+25*(x-tb)/(tc-tb),x<=te,50+25*(x-tc)/(te-tc),x<tf,75+25*(x-te)/(tf-te),TRUE,100))) -> 50 | K10: =IF(Inputs!K10="","",LET(d,Rulebook!$L10,x,Inputs!K10*d,ta,Rulebook!$G10*d,tb,Rulebook!$H10*d,tc,Rulebook!$I10*d,te,Rulebook!$J10*d,tf,Rulebook!$K10*d,IFS(x<=ta,0,x<=tb,25*(x-ta)/(tb-ta),x<=tc,25+25*(x-tb)/(tc-tb),x<=te,50+25*(x-tc)/(te-tc),x<tf,75+25*(x-te)/(tf-te),TRUE,100))) -> 12.5 | L10: =IF(Inputs!L10="","",LET(d,Rulebook!$L10,x,Inputs!L10*d,ta,Rulebook!$G10*d,tb,Rulebook!$H10*d,tc,Rulebook!$I10*d,te,Rulebook!$J10*d,tf,Rulebook!$K10*d,IFS(x<=ta,0,x<=tb,25*(x-ta)/(tb-ta),x<=tc,25+25*(x-tb)/(tc-tb),x<=te,50+25*(x-tc)/(te-tc),x<tf,75+25*(x-te)/(tf-te),TRUE,100))) -> 37.5 | ... V10: =IF(Inputs!V10="","",LET(d,Rulebook!$L10,x,Inputs!V10*d,ta,Rulebook!$G10*d,tb,Rulebook!$H10*d,tc,Rulebook!$I10*d,te,Rulebook!$J10*d,tf,Rulebook!$K10*d,IFS(x<=ta,0,x<=tb,25*(x-ta)/(tb-ta),x<=tc,25+25*(x-tb)/(tc-tb),x<=te,50+25*(x-tc)/(te-tc),x<tf,75+25*(x-te)/(tf-te),TRUE,100))) -> 25
A11: 1.7 | B11: 1 | C11: Change in debt/GDP over five years | D11: pp of GDP | E11: =IF(Inputs!E11="","",LET(d,Rulebook!$L11,x,Inputs!E11*d,ta,Rulebook!$G11*d,tb,Rulebook!$H11*d,tc,Rulebook!$I11*d,te,Rulebook!$J11*d,tf,Rulebook!$K11*d,IFS(x<=ta,0,x<=tb,25*(x-ta)/(tb-ta),x<=tc,25+25*(x-tb)/(tc-tb),x<=te,50+25*(x-tc)/(te-tc),x<tf,75+25*(x-te)/(tf-te),TRUE,100))) -> 0 | F11: =IF(Inputs!F11="","",LET(d,Rulebook!$L11,x,Inputs!F11*d,ta,Rulebook!$G11*d,tb,Rulebook!$H11*d,tc,Rulebook!$I11*d,te,Rulebook!$J11*d,tf,Rulebook!$K11*d,IFS(x<=ta,0,x<=tb,25*(x-ta)/(tb-ta),x<=tc,25+25*(x-tb)/(tc-tb),x<=te,50+25*(x-tc)/(te-tc),x<tf,75+25*(x-te)/(tf-te),TRUE,100))) -> 35 | G11: =IF(Inputs!G11="","",LET(d,Rulebook!$L11,x,Inputs!G11*d,ta,Rulebook!$G11*d,tb,Rulebook!$H11*d,tc,Rulebook!$I11*d,te,Rulebook!$J11*d,tf,Rulebook!$K11*d,IFS(x<=ta,0,x<=tb,25*(x-ta)/(tb-ta),x<=tc,25+25*(x-tb)/(tc-tb),x<=te,50+25*(x-tc)/(te-tc),x<tf,75+25*(x-te)/(tf-te),TRUE,100))) -> 100 | H11: =IF(Inputs!H11="","",LET(d,Rulebook!$L11,x,Inputs!H11*d,ta,Rulebook!$G11*d,tb,Rulebook!$H11*d,tc,Rulebook!$I11*d,te,Rulebook!$J11*d,tf,Rulebook!$K11*d,IFS(x<=ta,0,x<=tb,25*(x-ta)/(tb-ta),x<=tc,25+25*(x-tb)/(tc-tb),x<=te,50+25*(x-tc)/(te-tc),x<tf,75+25*(x-te)/(tf-te),TRUE,100))) -> 32.5 | I11: =IF(Inputs!I11="","",LET(d,Rulebook!$L11,x,Inputs!I11*d,ta,Rulebook!$G11*d,tb,Rulebook!$H11*d,tc,Rulebook!$I11*d,te,Rulebook!$J11*d,tf,Rulebook!$K11*d,IFS(x<=ta,0,x<=tb,25*(x-ta)/(tb-ta),x<=tc,25+25*(x-tb)/(tc-tb),x<=te,50+25*(x-tc)/(te-tc),x<tf,75+25*(x-te)/(tf-te),TRUE,100))) -> 100 | J11: =IF(Inputs!J11="","",LET(d,Rulebook!$L11,x,Inputs!J11*d,ta,Rulebook!$G11*d,tb,Rulebook!$H11*d,tc,Rulebook!$I11*d,te,Rulebook!$J11*d,tf,Rulebook!$K11*d,IFS(x<=ta,0,x<=tb,25*(x-ta)/(tb-ta),x<=tc,25+25*(x-tb)/(tc-tb),x<=te,50+25*(x-tc)/(te-tc),x<tf,75+25*(x-te)/(tf-te),TRUE,100))) -> 0 | K11: =IF(Inputs!K11="","",LET(d,Rulebook!$L11,x,Inputs!K11*d,ta,Rulebook!$G11*d,tb,Rulebook!$H11*d,tc,Rulebook!$I11*d,te,Rulebook!$J11*d,tf,Rulebook!$K11*d,IFS(x<=ta,0,x<=tb,25*(x-ta)/(tb-ta),x<=tc,25+25*(x-tb)/(tc-tb),x<=te,50+25*(x-tc)/(te-tc),x<tf,75+25*(x-te)/(tf-te),TRUE,100))) -> 32 | L11: =IF(Inputs!L11="","",LET(d,Rulebook!$L11,x,Inputs!L11*d,ta,Rulebook!$G11*d,tb,Rulebook!$H11*d,tc,Rulebook!$I11*d,te,Rulebook!$J11*d,tf,Rulebook!$K11*d,IFS(x<=ta,0,x<=tb,25*(x-ta)/(tb-ta),x<=tc,25+25*(x-tb)/(tc-tb),x<=te,50+25*(x-tc)/(te-tc),x<tf,75+25*(x-te)/(tf-te),TRUE,100))) -> 0 | ... V11: =IF(Inputs!V11="","",LET(d,Rulebook!$L11,x,Inputs!V11*d,ta,Rulebook!$G11*d,tb,Rulebook!$H11*d,tc,Rulebook!$I11*d,te,Rulebook!$J11*d,tf,Rulebook!$K11*d,IFS(x<=ta,0,x<=tb,25*(x-ta)/(tb-ta),x<=tc,25+25*(x-tb)/(tc-tb),x<=te,50+25*(x-tc)/(te-tc),x<tf,75+25*(x-te)/(tf-te),TRUE,100))) -> 0
A12: 1.8 | B12: 1 | C12: Default record: restructurings or defaults, past 20 years | D12: count | E12: =IF(Inputs!E12="","",LET(d,Rulebook!$L12,x,Inputs!E12*d,ta,Rulebook!$G12*d,tb,Rulebook!$H12*d,tc,Rulebook!$I12*d,te,Rulebook!$J12*d,tf,Rulebook!$K12*d,IFS(x<=ta,0,x<=tb,25*(x-ta)/(tb-ta),x<=tc,25+25*(x-tb)/(tc-tb),x<=te,50+25*(x-tc)/(te-tc),x<tf,75+25*(x-te)/(tf-te),TRUE,100))) -> 0 | F12: =IF(Inputs!F12="","",LET(d,Rulebook!$L12,x,Inputs!F12*d,ta,Rulebook!$G12*d,tb,Rulebook!$H12*d,tc,Rulebook!$I12*d,te,Rulebook!$J12*d,tf,Rulebook!$K12*d,IFS(x<=ta,0,x<=tb,25*(x-ta)/(tb-ta),x<=tc,25+25*(x-tb)/(tc-tb),x<=te,50+25*(x-tc)/(te-tc),x<tf,75+25*(x-te)/(tf-te),TRUE,100))) -> 0 | G12: =IF(Inputs!G12="","",LET(d,Rulebook!$L12,x,Inputs!G12*d,ta,Rulebook!$G12*d,tb,Rulebook!$H12*d,tc,Rulebook!$I12*d,te,Rulebook!$J12*d,tf,Rulebook!$K12*d,IFS(x<=ta,0,x<=tb,25*(x-ta)/(tb-ta),x<=tc,25+25*(x-tb)/(tc-tb),x<=te,50+25*(x-tc)/(te-tc),x<tf,75+25*(x-te)/(tf-te),TRUE,100))) -> 0 | H12: =IF(Inputs!H12="","",LET(d,Rulebook!$L12,x,Inputs!H12*d,ta,Rulebook!$G12*d,tb,Rulebook!$H12*d,tc,Rulebook!$I12*d,te,Rulebook!$J12*d,tf,Rulebook!$K12*d,IFS(x<=ta,0,x<=tb,25*(x-ta)/(tb-ta),x<=tc,25+25*(x-tb)/(tc-tb),x<=te,50+25*(x-tc)/(te-tc),x<tf,75+25*(x-te)/(tf-te),TRUE,100))) -> 0 | I12: =IF(Inputs!I12="","",LET(d,Rulebook!$L12,x,Inputs!I12*d,ta,Rulebook!$G12*d,tb,Rulebook!$H12*d,tc,Rulebook!$I12*d,te,Rulebook!$J12*d,tf,Rulebook!$K12*d,IFS(x<=ta,0,x<=tb,25*(x-ta)/(tb-ta),x<=tc,25+25*(x-tb)/(tc-tb),x<=te,50+25*(x-tc)/(te-tc),x<tf,75+25*(x-te)/(tf-te),TRUE,100))) -> 0 | J12: =IF(Inputs!J12="","",LET(d,Rulebook!$L12,x,Inputs!J12*d,ta,Rulebook!$G12*d,tb,Rulebook!$H12*d,tc,Rulebook!$I12*d,te,Rulebook!$J12*d,tf,Rulebook!$K12*d,IFS(x<=ta,0,x<=tb,25*(x-ta)/(tb-ta),x<=tc,25+25*(x-tb)/(tc-tb),x<=te,50+25*(x-tc)/(te-tc),x<tf,75+25*(x-te)/(tf-te),TRUE,100))) -> 0 | K12: =IF(Inputs!K12="","",LET(d,Rulebook!$L12,x,Inputs!K12*d,ta,Rulebook!$G12*d,tb,Rulebook!$H12*d,tc,Rulebook!$I12*d,te,Rulebook!$J12*d,tf,Rulebook!$K12*d,IFS(x<=ta,0,x<=tb,25*(x-ta)/(tb-ta),x<=tc,25+25*(x-tb)/(tc-tb),x<=te,50+25*(x-tc)/(te-tc),x<tf,75+25*(x-te)/(tf-te),TRUE,100))) -> 0 | L12: =IF(Inputs!L12="","",LET(d,Rulebook!$L12,x,Inputs!L12*d,ta,Rulebook!$G12*d,tb,Rulebook!$H12*d,tc,Rulebook!$I12*d,te,Rulebook!$J12*d,tf,Rulebook!$K12*d,IFS(x<=ta,0,x<=tb,25*(x-ta)/(tb-ta),x<=tc,25+25*(x-tb)/(tc-tb),x<=te,50+25*(x-tc)/(te-tc),x<tf,75+25*(x-te)/(tf-te),TRUE,100))) -> 0 | ... V12: =IF(Inputs!V12="","",LET(d,Rulebook!$L12,x,Inputs!V12*d,ta,Rulebook!$G12*d,tb,Rulebook!$H12*d,tc,Rulebook!$I12*d,te,Rulebook!$J12*d,tf,Rulebook!$K12*d,IFS(x<=ta,0,x<=tb,25*(x-ta)/(tb-ta),x<=tc,25+25*(x-tb)/(tc-tb),x<=te,50+25*(x-tc)/(te-tc),x<tf,75+25*(x-te)/(tf-te),TRUE,100))) -> 50
A13: 1.9 | B13: 1 | C13: Contingent liabilities and arrears | D13: level | E13: =IF(Inputs!E13="","",LET(d,Rulebook!$L13,x,Inputs!E13*d,ta,Rulebook!$G13*d,tb,Rulebook!$H13*d,tc,Rulebook!$I13*d,te,Rulebook!$J13*d,tf,Rulebook!$K13*d,IFS(x<=ta,0,x<=tb,25*(x-ta)/(tb-ta),x<=tc,25+25*(x-tb)/(tc-tb),x<=te,50+25*(x-tc)/(te-tc),x<tf,75+25*(x-te)/(tf-te),TRUE,100))) -> 50 | F13: =IF(Inputs!F13="","",LET(d,Rulebook!$L13,x,Inputs!F13*d,ta,Rulebook!$G13*d,tb,Rulebook!$H13*d,tc,Rulebook!$I13*d,te,Rulebook!$J13*d,tf,Rulebook!$K13*d,IFS(x<=ta,0,x<=tb,25*(x-ta)/(tb-ta),x<=tc,25+25*(x-tb)/(tc-tb),x<=te,50+25*(x-tc)/(te-tc),x<tf,75+25*(x-te)/(tf-te),TRUE,100))) -> 25 | G13: =IF(Inputs!G13="","",LET(d,Rulebook!$L13,x,Inputs!G13*d,ta,Rulebook!$G13*d,tb,Rulebook!$H13*d,tc,Rulebook!$I13*d,te,Rulebook!$J13*d,tf,Rulebook!$K13*d,IFS(x<=ta,0,x<=tb,25*(x-ta)/(tb-ta),x<=tc,25+25*(x-tb)/(tc-tb),x<=te,50+25*(x-tc)/(te-tc),x<tf,75+25*(x-te)/(tf-te),TRUE,100))) -> 100 | H13: =IF(Inputs!H13="","",LET(d,Rulebook!$L13,x,Inputs!H13*d,ta,Rulebook!$G13*d,tb,Rulebook!$H13*d,tc,Rulebook!$I13*d,te,Rulebook!$J13*d,tf,Rulebook!$K13*d,IFS(x<=ta,0,x<=tb,25*(x-ta)/(tb-ta),x<=tc,25+25*(x-tb)/(tc-tb),x<=te,50+25*(x-tc)/(te-tc),x<tf,75+25*(x-te)/(tf-te),TRUE,100))) -> 50 | I13: =IF(Inputs!I13="","",LET(d,Rulebook!$L13,x,Inputs!I13*d,ta,Rulebook!$G13*d,tb,Rulebook!$H13*d,tc,Rulebook!$I13*d,te,Rulebook!$J13*d,tf,Rulebook!$K13*d,IFS(x<=ta,0,x<=tb,25*(x-ta)/(tb-ta),x<=tc,25+25*(x-tb)/(tc-tb),x<=te,50+25*(x-tc)/(te-tc),x<tf,75+25*(x-te)/(tf-te),TRUE,100))) -> 0 | J13: =IF(Inputs!J13="","",LET(d,Rulebook!$L13,x,Inputs!J13*d,ta,Rulebook!$G13*d,tb,Rulebook!$H13*d,tc,Rulebook!$I13*d,te,Rulebook!$J13*d,tf,Rulebook!$K13*d,IFS(x<=ta,0,x<=tb,25*(x-ta)/(tb-ta),x<=tc,25+25*(x-tb)/(tc-tb),x<=te,50+25*(x-tc)/(te-tc),x<tf,75+25*(x-te)/(tf-te),TRUE,100))) -> 25 | K13: =IF(Inputs!K13="","",LET(d,Rulebook!$L13,x,Inputs!K13*d,ta,Rulebook!$G13*d,tb,Rulebook!$H13*d,tc,Rulebook!$I13*d,te,Rulebook!$J13*d,tf,Rulebook!$K13*d,IFS(x<=ta,0,x<=tb,25*(x-ta)/(tb-ta),x<=tc,25+25*(x-tb)/(tc-tb),x<=te,50+25*(x-tc)/(te-tc),x<tf,75+25*(x-te)/(tf-te),TRUE,100))) -> 50 | L13: =IF(Inputs!L13="","",LET(d,Rulebook!$L13,x,Inputs!L13*d,ta,Rulebook!$G13*d,tb,Rulebook!$H13*d,tc,Rulebook!$I13*d,te,Rulebook!$J13*d,tf,Rulebook!$K13*d,IFS(x<=ta,0,x<=tb,25*(x-ta)/(tb-ta),x<=tc,25+25*(x-tb)/(tc-tb),x<=te,50+25*(x-tc)/(te-tc),x<tf,75+25*(x-te)/(tf-te),TRUE,100))) -> 50 | ... V13: =IF(Inputs!V13="","",LET(d,Rulebook!$L13,x,Inputs!V13*d,ta,Rulebook!$G13*d,tb,Rulebook!$H13*d,tc,Rulebook!$I13*d,te,Rulebook!$J13*d,tf,Rulebook!$K13*d,IFS(x<=ta,0,x<=tb,25*(x-ta)/(tb-ta),x<=tc,25+25*(x-tb)/(tc-tb),x<=te,50+25*(x-tc)/(te-tc),x<tf,75+25*(x-te)/(tf-te),TRUE,100))) -> 100
A14: 2.1 | B14: 2 | C14: Net usable reserves | D14: % of IMF ARA metric | E14: =IF(Inputs!E14="","",LET(d,Rulebook!$L14,x,Inputs!E14*d,ta,Rulebook!$G14*d,tb,Rulebook!$H14*d,tc,Rulebook!$I14*d,te,Rulebook!$J14*d,tf,Rulebook!$K14*d,IFS(x<=ta,0,x<=tb,25*(x-ta)/(tb-ta),x<=tc,25+25*(x-tb)/(tc-tb),x<=te,50+25*(x-tc)/(te-tc),x<tf,75+25*(x-te)/(tf-te),TRUE,100))) -> 75 | F14: =IF(Inputs!F14="","",LET(d,Rulebook!$L14,x,Inputs!F14*d,ta,Rulebook!$G14*d,tb,Rulebook!$H14*d,tc,Rulebook!$I14*d,te,Rulebook!$J14*d,tf,Rulebook!$K14*d,IFS(x<=ta,0,x<=tb,25*(x-ta)/(tb-ta),x<=tc,25+25*(x-tb)/(tc-tb),x<=te,50+25*(x-tc)/(te-tc),x<tf,75+25*(x-te)/(tf-te),TRUE,100))) -> 0 | G14: =IF(Inputs!G14="","",LET(d,Rulebook!$L14,x,Inputs!G14*d,ta,Rulebook!$G14*d,tb,Rulebook!$H14*d,tc,Rulebook!$I14*d,te,Rulebook!$J14*d,tf,Rulebook!$K14*d,IFS(x<=ta,0,x<=tb,25*(x-ta)/(tb-ta),x<=tc,25+25*(x-tb)/(tc-tb),x<=te,50+25*(x-tc)/(te-tc),x<tf,75+25*(x-te)/(tf-te),TRUE,100))) -> 30 | H14: =IF(Inputs!H14="","",LET(d,Rulebook!$L14,x,Inputs!H14*d,ta,Rulebook!$G14*d,tb,Rulebook!$H14*d,tc,Rulebook!$I14*d,te,Rulebook!$J14*d,tf,Rulebook!$K14*d,IFS(x<=ta,0,x<=tb,25*(x-ta)/(tb-ta),x<=tc,25+25*(x-tb)/(tc-tb),x<=te,50+25*(x-tc)/(te-tc),x<tf,75+25*(x-te)/(tf-te),TRUE,100))) -> 40 | I14: =IF(Inputs!I14="","",LET(d,Rulebook!$L14,x,Inputs!I14*d,ta,Rulebook!$G14*d,tb,Rulebook!$H14*d,tc,Rulebook!$I14*d,te,Rulebook!$J14*d,tf,Rulebook!$K14*d,IFS(x<=ta,0,x<=tb,25*(x-ta)/(tb-ta),x<=tc,25+25*(x-tb)/(tc-tb),x<=te,50+25*(x-tc)/(te-tc),x<tf,75+25*(x-te)/(tf-te),TRUE,100))) -> 0 | J14: =IF(Inputs!J14="","",LET(d,Rulebook!$L14,x,Inputs!J14*d,ta,Rulebook!$G14*d,tb,Rulebook!$H14*d,tc,Rulebook!$I14*d,te,Rulebook!$J14*d,tf,Rulebook!$K14*d,IFS(x<=ta,0,x<=tb,25*(x-ta)/(tb-ta),x<=tc,25+25*(x-tb)/(tc-tb),x<=te,50+25*(x-tc)/(te-tc),x<tf,75+25*(x-te)/(tf-te),TRUE,100))) -> 0 | K14: =IF(Inputs!K14="","",LET(d,Rulebook!$L14,x,Inputs!K14*d,ta,Rulebook!$G14*d,tb,Rulebook!$H14*d,tc,Rulebook!$I14*d,te,Rulebook!$J14*d,tf,Rulebook!$K14*d,IFS(x<=ta,0,x<=tb,25*(x-ta)/(tb-ta),x<=tc,25+25*(x-tb)/(tc-tb),x<=te,50+25*(x-tc)/(te-tc),x<tf,75+25*(x-te)/(tf-te),TRUE,100))) -> 50 | L14: =IF(Inputs!L14="","",LET(d,Rulebook!$L14,x,Inputs!L14*d,ta,Rulebook!$G14*d,tb,Rulebook!$H14*d,tc,Rulebook!$I14*d,te,Rulebook!$J14*d,tf,Rulebook!$K14*d,IFS(x<=ta,0,x<=tb,25*(x-ta)/(tb-ta),x<=tc,25+25*(x-tb)/(tc-tb),x<=te,50+25*(x-tc)/(te-tc),x<tf,75+25*(x-te)/(tf-te),TRUE,100))) -> 0 | ... V14: =IF(Inputs!V14="","",LET(d,Rulebook!$L14,x,Inputs!V14*d,ta,Rulebook!$G14*d,tb,Rulebook!$H14*d,tc,Rulebook!$I14*d,te,Rulebook!$J14*d,tf,Rulebook!$K14*d,IFS(x<=ta,0,x<=tb,25*(x-ta)/(tb-ta),x<=tc,25+25*(x-tb)/(tc-tb),x<=te,50+25*(x-tc)/(te-tc),x<tf,75+25*(x-te)/(tf-te),TRUE,100))) -> 100
A15: 2.2 | B15: 2 | C15: External financing need (CA deficit + external debt due in 12m) | D15: % of net reserves | E15: =IF(Inputs!E15="","",LET(d,Rulebook!$L15,x,Inputs!E15*d,ta,Rulebook!$G15*d,tb,Rulebook!$H15*d,tc,Rulebook!$I15*d,te,Rulebook!$J15*d,tf,Rulebook!$K15*d,IFS(x<=ta,0,x<=tb,25*(x-ta)/(tb-ta),x<=tc,25+25*(x-tb)/(tc-tb),x<=te,50+25*(x-tc)/(te-tc),x<tf,75+25*(x-te)/(tf-te),TRUE,100))) -> 0 | F15: =IF(Inputs!F15="","",LET(d,Rulebook!$L15,x,Inputs!F15*d,ta,Rulebook!$G15*d,tb,Rulebook!$H15*d,tc,Rulebook!$I15*d,te,Rulebook!$J15*d,tf,Rulebook!$K15*d,IFS(x<=ta,0,x<=tb,25*(x-ta)/(tb-ta),x<=tc,25+25*(x-tb)/(tc-tb),x<=te,50+25*(x-tc)/(te-tc),x<tf,75+25*(x-te)/(tf-te),TRUE,100))) -> 0 | G15: =IF(Inputs!G15="","",LET(d,Rulebook!$L15,x,Inputs!G15*d,ta,Rulebook!$G15*d,tb,Rulebook!$H15*d,tc,Rulebook!$I15*d,te,Rulebook!$J15*d,tf,Rulebook!$K15*d,IFS(x<=ta,0,x<=tb,25*(x-ta)/(tb-ta),x<=tc,25+25*(x-tb)/(tc-tb),x<=te,50+25*(x-tc)/(te-tc),x<tf,75+25*(x-te)/(tf-te),TRUE,100))) -> 0 | H15: =IF(Inputs!H15="","",LET(d,Rulebook!$L15,x,Inputs!H15*d,ta,Rulebook!$G15*d,tb,Rulebook!$H15*d,tc,Rulebook!$I15*d,te,Rulebook!$J15*d,tf,Rulebook!$K15*d,IFS(x<=ta,0,x<=tb,25*(x-ta)/(tb-ta),x<=tc,25+25*(x-tb)/(tc-tb),x<=te,50+25*(x-tc)/(te-tc),x<tf,75+25*(x-te)/(tf-te),TRUE,100))) -> 10 | I15: =IF(Inputs!I15="","",LET(d,Rulebook!$L15,x,Inputs!I15*d,ta,Rulebook!$G15*d,tb,Rulebook!$H15*d,tc,Rulebook!$I15*d,te,Rulebook!$J15*d,tf,Rulebook!$K15*d,IFS(x<=ta,0,x<=tb,25*(x-ta)/(tb-ta),x<=tc,25+25*(x-tb)/(tc-tb),x<=te,50+25*(x-tc)/(te-tc),x<tf,75+25*(x-te)/(tf-te),TRUE,100))) -> 0 | J15: =IF(Inputs!J15="","",LET(d,Rulebook!$L15,x,Inputs!J15*d,ta,Rulebook!$G15*d,tb,Rulebook!$H15*d,tc,Rulebook!$I15*d,te,Rulebook!$J15*d,tf,Rulebook!$K15*d,IFS(x<=ta,0,x<=tb,25*(x-ta)/(tb-ta),x<=tc,25+25*(x-tb)/(tc-tb),x<=te,50+25*(x-tc)/(te-tc),x<tf,75+25*(x-te)/(tf-te),TRUE,100))) -> 0 | K15: =IF(Inputs!K15="","",LET(d,Rulebook!$L15,x,Inputs!K15*d,ta,Rulebook!$G15*d,tb,Rulebook!$H15*d,tc,Rulebook!$I15*d,te,Rulebook!$J15*d,tf,Rulebook!$K15*d,IFS(x<=ta,0,x<=tb,25*(x-ta)/(tb-ta),x<=tc,25+25*(x-tb)/(tc-tb),x<=te,50+25*(x-tc)/(te-tc),x<tf,75+25*(x-te)/(tf-te),TRUE,100))) -> 0 | L15: =IF(Inputs!L15="","",LET(d,Rulebook!$L15,x,Inputs!L15*d,ta,Rulebook!$G15*d,tb,Rulebook!$H15*d,tc,Rulebook!$I15*d,te,Rulebook!$J15*d,tf,Rulebook!$K15*d,IFS(x<=ta,0,x<=tb,25*(x-ta)/(tb-ta),x<=tc,25+25*(x-tb)/(tc-tb),x<=te,50+25*(x-tc)/(te-tc),x<tf,75+25*(x-te)/(tf-te),TRUE,100))) -> 0 | ... V15: =IF(Inputs!V15="","",LET(d,Rulebook!$L15,x,Inputs!V15*d,ta,Rulebook!$G15*d,tb,Rulebook!$H15*d,tc,Rulebook!$I15*d,te,Rulebook!$J15*d,tf,Rulebook!$K15*d,IFS(x<=ta,0,x<=tb,25*(x-ta)/(tb-ta),x<=tc,25+25*(x-tb)/(tc-tb),x<=te,50+25*(x-tc)/(te-tc),x<tf,75+25*(x-te)/(tf-te),TRUE,100))) -> 100
A16: 2.3 | B16: 2 | C16: Hot money (non-resident local debt + portfolio due in 1y) | D16: % of net reserves | E16: =IF(Inputs!E16="","",LET(d,Rulebook!$L16,x,Inputs!E16*d,ta,Rulebook!$G16*d,tb,Rulebook!$H16*d,tc,Rulebook!$I16*d,te,Rulebook!$J16*d,tf,Rulebook!$K16*d,IFS(x<=ta,0,x<=tb,25*(x-ta)/(tb-ta),x<=tc,25+25*(x-tb)/(tc-tb),x<=te,50+25*(x-tc)/(te-tc),x<tf,75+25*(x-te)/(tf-te),TRUE,100))) -> 0 | F16: =IF(Inputs!F16="","",LET(d,Rulebook!$L16,x,Inputs!F16*d,ta,Rulebook!$G16*d,tb,Rulebook!$H16*d,tc,Rulebook!$I16*d,te,Rulebook!$J16*d,tf,Rulebook!$K16*d,IFS(x<=ta,0,x<=tb,25*(x-ta)/(tb-ta),x<=tc,25+25*(x-tb)/(tc-tb),x<=te,50+25*(x-tc)/(te-tc),x<tf,75+25*(x-te)/(tf-te),TRUE,100))) -> 8.3333333 | G16: =IF(Inputs!G16="","",LET(d,Rulebook!$L16,x,Inputs!G16*d,ta,Rulebook!$G16*d,tb,Rulebook!$H16*d,tc,Rulebook!$I16*d,te,Rulebook!$J16*d,tf,Rulebook!$K16*d,IFS(x<=ta,0,x<=tb,25*(x-ta)/(tb-ta),x<=tc,25+25*(x-tb)/(tc-tb),x<=te,50+25*(x-tc)/(te-tc),x<tf,75+25*(x-te)/(tf-te),TRUE,100))) -> 0 | H16: =IF(Inputs!H16="","",LET(d,Rulebook!$L16,x,Inputs!H16*d,ta,Rulebook!$G16*d,tb,Rulebook!$H16*d,tc,Rulebook!$I16*d,te,Rulebook!$J16*d,tf,Rulebook!$K16*d,IFS(x<=ta,0,x<=tb,25*(x-ta)/(tb-ta),x<=tc,25+25*(x-tb)/(tc-tb),x<=te,50+25*(x-tc)/(te-tc),x<tf,75+25*(x-te)/(tf-te),TRUE,100))) -> 60 | I16: =IF(Inputs!I16="","",LET(d,Rulebook!$L16,x,Inputs!I16*d,ta,Rulebook!$G16*d,tb,Rulebook!$H16*d,tc,Rulebook!$I16*d,te,Rulebook!$J16*d,tf,Rulebook!$K16*d,IFS(x<=ta,0,x<=tb,25*(x-ta)/(tb-ta),x<=tc,25+25*(x-tb)/(tc-tb),x<=te,50+25*(x-tc)/(te-tc),x<tf,75+25*(x-te)/(tf-te),TRUE,100))) -> 0 | J16: =IF(Inputs!J16="","",LET(d,Rulebook!$L16,x,Inputs!J16*d,ta,Rulebook!$G16*d,tb,Rulebook!$H16*d,tc,Rulebook!$I16*d,te,Rulebook!$J16*d,tf,Rulebook!$K16*d,IFS(x<=ta,0,x<=tb,25*(x-ta)/(tb-ta),x<=tc,25+25*(x-tb)/(tc-tb),x<=te,50+25*(x-tc)/(te-tc),x<tf,75+25*(x-te)/(tf-te),TRUE,100))) -> 8.3333333 | K16: =IF(Inputs!K16="","",LET(d,Rulebook!$L16,x,Inputs!K16*d,ta,Rulebook!$G16*d,tb,Rulebook!$H16*d,tc,Rulebook!$I16*d,te,Rulebook!$J16*d,tf,Rulebook!$K16*d,IFS(x<=ta,0,x<=tb,25*(x-ta)/(tb-ta),x<=tc,25+25*(x-tb)/(tc-tb),x<=te,50+25*(x-tc)/(te-tc),x<tf,75+25*(x-te)/(tf-te),TRUE,100))) -> 40 | L16: =IF(Inputs!L16="","",LET(d,Rulebook!$L16,x,Inputs!L16*d,ta,Rulebook!$G16*d,tb,Rulebook!$H16*d,tc,Rulebook!$I16*d,te,Rulebook!$J16*d,tf,Rulebook!$K16*d,IFS(x<=ta,0,x<=tb,25*(x-ta)/(tb-ta),x<=tc,25+25*(x-tb)/(tc-tb),x<=te,50+25*(x-tc)/(te-tc),x<tf,75+25*(x-te)/(tf-te),TRUE,100))) -> 16.666667 | ... V16: =IF(Inputs!V16="","",LET(d,Rulebook!$L16,x,Inputs!V16*d,ta,Rulebook!$G16*d,tb,Rulebook!$H16*d,tc,Rulebook!$I16*d,te,Rulebook!$J16*d,tf,Rulebook!$K16*d,IFS(x<=ta,0,x<=tb,25*(x-ta)/(tb-ta),x<=tc,25+25*(x-tb)/(tc-tb),x<=te,50+25*(x-tc)/(te-tc),x<tf,75+25*(x-te)/(tf-te),TRUE,100))) -> 0
... A58: 5.12 | B58: 5 | C58: Growth volatility: SD of real GDP growth, 15y (ex 2020-21) | D58: pp | E58: =IF(Inputs!E58="","",LET(d,Rulebook!$L58,x,Inputs!E58*d,ta,Rulebook!$G58*d,tb,Rulebook!$H58*d,tc,Rulebook!$I58*d,te,Rulebook!$J58*d,tf,Rulebook!$K58*d,IFS(x<=ta,0,x<=tb,25*(x-ta)/(tb-ta),x<=tc,25+25*(x-tb)/(tc-tb),x<=te,50+25*(x-tc)/(te-tc),x<tf,75+25*(x-te)/(tf-te),TRUE,100))) -> 0 | F58: =IF(Inputs!F58="","",LET(d,Rulebook!$L58,x,Inputs!F58*d,ta,Rulebook!$G58*d,tb,Rulebook!$H58*d,tc,Rulebook!$I58*d,te,Rulebook!$J58*d,tf,Rulebook!$K58*d,IFS(x<=ta,0,x<=tb,25*(x-ta)/(tb-ta),x<=tc,25+25*(x-tb)/(tc-tb),x<=te,50+25*(x-tc)/(te-tc),x<tf,75+25*(x-te)/(tf-te),TRUE,100))) -> 12.5 | G58: =IF(Inputs!G58="","",LET(d,Rulebook!$L58,x,Inputs!G58*d,ta,Rulebook!$G58*d,tb,Rulebook!$H58*d,tc,Rulebook!$I58*d,te,Rulebook!$J58*d,tf,Rulebook!$K58*d,IFS(x<=ta,0,x<=tb,25*(x-ta)/(tb-ta),x<=tc,25+25*(x-tb)/(tc-tb),x<=te,50+25*(x-tc)/(te-tc),x<tf,75+25*(x-te)/(tf-te),TRUE,100))) -> 12.5 | H58: =IF(Inputs!H58="","",LET(d,Rulebook!$L58,x,Inputs!H58*d,ta,Rulebook!$G58*d,tb,Rulebook!$H58*d,tc,Rulebook!$I58*d,te,Rulebook!$J58*d,tf,Rulebook!$K58*d,IFS(x<=ta,0,x<=tb,25*(x-ta)/(tb-ta),x<=tc,25+25*(x-tb)/(tc-tb),x<=te,50+25*(x-tc)/(te-tc),x<tf,75+25*(x-te)/(tf-te),TRUE,100))) -> 0 | I58: =IF(Inputs!I58="","",LET(d,Rulebook!$L58,x,Inputs!I58*d,ta,Rulebook!$G58*d,tb,Rulebook!$H58*d,tc,Rulebook!$I58*d,te,Rulebook!$J58*d,tf,Rulebook!$K58*d,IFS(x<=ta,0,x<=tb,25*(x-ta)/(tb-ta),x<=tc,25+25*(x-tb)/(tc-tb),x<=te,50+25*(x-tc)/(te-tc),x<tf,75+25*(x-te)/(tf-te),TRUE,100))) -> 37.5 | J58: =IF(Inputs!J58="","",LET(d,Rulebook!$L58,x,Inputs!J58*d,ta,Rulebook!$G58*d,tb,Rulebook!$H58*d,tc,Rulebook!$I58*d,te,Rulebook!$J58*d,tf,Rulebook!$K58*d,IFS(x<=ta,0,x<=tb,25*(x-ta)/(tb-ta),x<=tc,25+25*(x-tb)/(tc-tb),x<=te,50+25*(x-tc)/(te-tc),x<tf,75+25*(x-te)/(tf-te),TRUE,100))) -> 0 | K58: =IF(Inputs!K58="","",LET(d,Rulebook!$L58,x,Inputs!K58*d,ta,Rulebook!$G58*d,tb,Rulebook!$H58*d,tc,Rulebook!$I58*d,te,Rulebook!$J58*d,tf,Rulebook!$K58*d,IFS(x<=ta,0,x<=tb,25*(x-ta)/(tb-ta),x<=tc,25+25*(x-tb)/(tc-tb),x<=te,50+25*(x-tc)/(te-tc),x<tf,75+25*(x-te)/(tf-te),TRUE,100))) -> 0 | L58: =IF(Inputs!L58="","",LET(d,Rulebook!$L58,x,Inputs!L58*d,ta,Rulebook!$G58*d,tb,Rulebook!$H58*d,tc,Rulebook!$I58*d,te,Rulebook!$J58*d,tf,Rulebook!$K58*d,IFS(x<=ta,0,x<=tb,25*(x-ta)/(tb-ta),x<=tc,25+25*(x-tb)/(tc-tb),x<=te,50+25*(x-tc)/(te-tc),x<tf,75+25*(x-te)/(tf-te),TRUE,100))) -> 12.5 | ... V58: =IF(Inputs!V58="","",LET(d,Rulebook!$L58,x,Inputs!V58*d,ta,Rulebook!$G58*d,tb,Rulebook!$H58*d,tc,Rulebook!$I58*d,te,Rulebook!$J58*d,tf,Rulebook!$K58*d,IFS(x<=ta,0,x<=tb,25*(x-ta)/(tb-ta),x<=tc,25+25*(x-tb)/(tc-tb),x<=te,50+25*(x-tc)/(te-tc),x<tf,75+25*(x-te)/(tf-te),TRUE,100))) -> 87.5
A59: 5.13 | B59: 5 | C59: Real policy rate (two-sided: 0 to +4 scores 0) | D59: % | E59: =IF(Inputs!E59="","",MAX(LET(d,Rulebook!$L59,x,Inputs!E59*d,ta,Rulebook!$G59*d,tb,Rulebook!$H59*d,tc,Rulebook!$I59*d,te,Rulebook!$J59*d,tf,Rulebook!$K59*d,IFS(x<=ta,0,x<=tb,25*(x-ta)/(tb-ta),x<=tc,25+25*(x-tb)/(tc-tb),x<=te,50+25*(x-tc)/(te-tc),x<tf,75+25*(x-te)/(tf-te),TRUE,100)),LET(d,SIGN(Rulebook!$U59-Rulebook!$Q59),x,Inputs!E59*d,ta,Rulebook!$Q59*d,tb,Rulebook!$R59*d,tc,Rulebook!$S59*d,te,Rulebook!$T59*d,tf,Rulebook!$U59*d,IFS(x<=ta,0,x<=tb,25*(x-ta)/(tb-ta),x<=tc,25+25*(x-tb)/(tc-tb),x<=te,50+25*(x-tc)/(te-tc),x<tf,75+25*(x-te)/(tf-te),TRUE,100)))) -> 0 | F59: =IF(Inputs!F59="","",MAX(LET(d,Rulebook!$L59,x,Inputs!F59*d,ta,Rulebook!$G59*d,tb,Rulebook!$H59*d,tc,Rulebook!$I59*d,te,Rulebook!$J59*d,tf,Rulebook!$K59*d,IFS(x<=ta,0,x<=tb,25*(x-ta)/(tb-ta),x<=tc,25+25*(x-tb)/(tc-tb),x<=te,50+25*(x-tc)/(te-tc),x<tf,75+25*(x-te)/(tf-te),TRUE,100)),LET(d,SIGN(Rulebook!$U59-Rulebook!$Q59),x,Inputs!F59*d,ta,Rulebook!$Q59*d,tb,Rulebook!$R59*d,tc,Rulebook!$S59*d,te,Rulebook!$T59*d,tf,Rulebook!$U59*d,IFS(x<=ta,0,x<=tb,25*(x-ta)/(tb-ta),x<=tc,25+25*(x-tb)/(tc-tb),x<=te,50+25*(x-tc)/(te-tc),x<tf,75+25*(x-te)/(tf-te),TRUE,100)))) -> 0 | G59: =IF(Inputs!G59="","",MAX(LET(d,Rulebook!$L59,x,Inputs!G59*d,ta,Rulebook!$G59*d,tb,Rulebook!$H59*d,tc,Rulebook!$I59*d,te,Rulebook!$J59*d,tf,Rulebook!$K59*d,IFS(x<=ta,0,x<=tb,25*(x-ta)/(tb-ta),x<=tc,25+25*(x-tb)/(tc-tb),x<=te,50+25*(x-tc)/(te-tc),x<tf,75+25*(x-te)/(tf-te),TRUE,100)),LET(d,SIGN(Rulebook!$U59-Rulebook!$Q59),x,Inputs!G59*d,ta,Rulebook!$Q59*d,tb,Rulebook!$R59*d,tc,Rulebook!$S59*d,te,Rulebook!$T59*d,tf,Rulebook!$U59*d,IFS(x<=ta,0,x<=tb,25*(x-ta)/(tb-ta),x<=tc,25+25*(x-tb)/(tc-tb),x<=te,50+25*(x-tc)/(te-tc),x<tf,75+25*(x-te)/(tf-te),TRUE,100)))) -> 0 | H59: =IF(Inputs!H59="","",MAX(LET(d,Rulebook!$L59,x,Inputs!H59*d,ta,Rulebook!$G59*d,tb,Rulebook!$H59*d,tc,Rulebook!$I59*d,te,Rulebook!$J59*d,tf,Rulebook!$K59*d,IFS(x<=ta,0,x<=tb,25*(x-ta)/(tb-ta),x<=tc,25+25*(x-tb)/(tc-tb),x<=te,50+25*(x-tc)/(te-tc),x<tf,75+25*(x-te)/(tf-te),TRUE,100)),LET(d,SIGN(Rulebook!$U59-Rulebook!$Q59),x,Inputs!H59*d,ta,Rulebook!$Q59*d,tb,Rulebook!$R59*d,tc,Rulebook!$S59*d,te,Rulebook!$T59*d,tf,Rulebook!$U59*d,IFS(x<=ta,0,x<=tb,25*(x-ta)/(tb-ta),x<=tc,25+25*(x-tb)/(tc-tb),x<=te,50+25*(x-tc)/(te-tc),x<tf,75+25*(x-te)/(tf-te),TRUE,100)))) -> 0 | I59: =IF(Inputs!I59="","",MAX(LET(d,Rulebook!$L59,x,Inputs!I59*d,ta,Rulebook!$G59*d,tb,Rulebook!$H59*d,tc,Rulebook!$I59*d,te,Rulebook!$J59*d,tf,Rulebook!$K59*d,IFS(x<=ta,0,x<=tb,25*(x-ta)/(tb-ta),x<=tc,25+25*(x-tb)/(tc-tb),x<=te,50+25*(x-tc)/(te-tc),x<tf,75+25*(x-te)/(tf-te),TRUE,100)),LET(d,SIGN(Rulebook!$U59-Rulebook!$Q59),x,Inputs!I59*d,ta,Rulebook!$Q59*d,tb,Rulebook!$R59*d,tc,Rulebook!$S59*d,te,Rulebook!$T59*d,tf,Rulebook!$U59*d,IFS(x<=ta,0,x<=tb,25*(x-ta)/(tb-ta),x<=tc,25+25*(x-tb)/(tc-tb),x<=te,50+25*(x-tc)/(te-tc),x<tf,75+25*(x-te)/(tf-te),TRUE,100)))) -> 0 | J59: =IF(Inputs!J59="","",MAX(LET(d,Rulebook!$L59,x,Inputs!J59*d,ta,Rulebook!$G59*d,tb,Rulebook!$H59*d,tc,Rulebook!$I59*d,te,Rulebook!$J59*d,tf,Rulebook!$K59*d,IFS(x<=ta,0,x<=tb,25*(x-ta)/(tb-ta),x<=tc,25+25*(x-tb)/(tc-tb),x<=te,50+25*(x-tc)/(te-tc),x<tf,75+25*(x-te)/(tf-te),TRUE,100)),LET(d,SIGN(Rulebook!$U59-Rulebook!$Q59),x,Inputs!J59*d,ta,Rulebook!$Q59*d,tb,Rulebook!$R59*d,tc,Rulebook!$S59*d,te,Rulebook!$T59*d,tf,Rulebook!$U59*d,IFS(x<=ta,0,x<=tb,25*(x-ta)/(tb-ta),x<=tc,25+25*(x-tb)/(tc-tb),x<=te,50+25*(x-tc)/(te-tc),x<tf,75+25*(x-te)/(tf-te),TRUE,100)))) -> 30 | K59: =IF(Inputs!K59="","",MAX(LET(d,Rulebook!$L59,x,Inputs!K59*d,ta,Rulebook!$G59*d,tb,Rulebook!$H59*d,tc,Rulebook!$I59*d,te,Rulebook!$J59*d,tf,Rulebook!$K59*d,IFS(x<=ta,0,x<=tb,25*(x-ta)/(tb-ta),x<=tc,25+25*(x-tb)/(tc-tb),x<=te,50+25*(x-tc)/(te-tc),x<tf,75+25*(x-te)/(tf-te),TRUE,100)),LET(d,SIGN(Rulebook!$U59-Rulebook!$Q59),x,Inputs!K59*d,ta,Rulebook!$Q59*d,tb,Rulebook!$R59*d,tc,Rulebook!$S59*d,te,Rulebook!$T59*d,tf,Rulebook!$U59*d,IFS(x<=ta,0,x<=tb,25*(x-ta)/(tb-ta),x<=tc,25+25*(x-tb)/(tc-tb),x<=te,50+25*(x-tc)/(te-tc),x<tf,75+25*(x-te)/(tf-te),TRUE,100)))) -> 0 | L59: =IF(Inputs!L59="","",MAX(LET(d,Rulebook!$L59,x,Inputs!L59*d,ta,Rulebook!$G59*d,tb,Rulebook!$H59*d,tc,Rulebook!$I59*d,te,Rulebook!$J59*d,tf,Rulebook!$K59*d,IFS(x<=ta,0,x<=tb,25*(x-ta)/(tb-ta),x<=tc,25+25*(x-tb)/(tc-tb),x<=te,50+25*(x-tc)/(te-tc),x<tf,75+25*(x-te)/(tf-te),TRUE,100)),LET(d,SIGN(Rulebook!$U59-Rulebook!$Q59),x,Inputs!L59*d,ta,Rulebook!$Q59*d,tb,Rulebook!$R59*d,tc,Rulebook!$S59*d,te,Rulebook!$T59*d,tf,Rulebook!$U59*d,IFS(x<=ta,0,x<=tb,25*(x-ta)/(tb-ta),x<=tc,25+25*(x-tb)/(tc-tb),x<=te,50+25*(x-tc)/(te-tc),x<tf,75+25*(x-te)/(tf-te),TRUE,100)))) -> 0 | ... V59: =IF(Inputs!V59="","",MAX(LET(d,Rulebook!$L59,x,Inputs!V59*d,ta,Rulebook!$G59*d,tb,Rulebook!$H59*d,tc,Rulebook!$I59*d,te,Rulebook!$J59*d,tf,Rulebook!$K59*d,IFS(x<=ta,0,x<=tb,25*(x-ta)/(tb-ta),x<=tc,25+25*(x-tb)/(tc-tb),x<=te,50+25*(x-tc)/(te-tc),x<tf,75+25*(x-te)/(tf-te),TRUE,100)),LET(d,SIGN(Rulebook!$U59-Rulebook!$Q59),x,Inputs!V59*d,ta,Rulebook!$Q59*d,tb,Rulebook!$R59*d,tc,Rulebook!$S59*d,te,Rulebook!$T59*d,tf,Rulebook!$U59*d,IFS(x<=ta,0,x<=tb,25*(x-ta)/(tb-ta),x<=tc,25+25*(x-tb)/(tc-tb),x<=te,50+25*(x-tc)/(te-tc),x<tf,75+25*(x-te)/(tf-te),TRUE,100)))) -> 12.5
A60: 5.14 | B60: 5 | C60: GDP per person | D60: US$ | E60: =IF(Inputs!E60="","",LET(d,Rulebook!$L60,x,Inputs!E60*d,ta,Rulebook!$G60*d,tb,Rulebook!$H60*d,tc,Rulebook!$I60*d,te,Rulebook!$J60*d,tf,Rulebook!$K60*d,IFS(x<=ta,0,x<=tb,25*(x-ta)/(tb-ta),x<=tc,25+25*(x-tb)/(tc-tb),x<=te,50+25*(x-tc)/(te-tc),x<tf,75+25*(x-te)/(tf-te),TRUE,100))) -> 57.142857 | F60: =IF(Inputs!F60="","",LET(d,Rulebook!$L60,x,Inputs!F60*d,ta,Rulebook!$G60*d,tb,Rulebook!$H60*d,tc,Rulebook!$I60*d,te,Rulebook!$J60*d,tf,Rulebook!$K60*d,IFS(x<=ta,0,x<=tb,25*(x-ta)/(tb-ta),x<=tc,25+25*(x-tb)/(tc-tb),x<=te,50+25*(x-tc)/(te-tc),x<tf,75+25*(x-te)/(tf-te),TRUE,100))) -> 62.142857 | G60: =IF(Inputs!G60="","",LET(d,Rulebook!$L60,x,Inputs!G60*d,ta,Rulebook!$G60*d,tb,Rulebook!$H60*d,tc,Rulebook!$I60*d,te,Rulebook!$J60*d,tf,Rulebook!$K60*d,IFS(x<=ta,0,x<=tb,25*(x-ta)/(tb-ta),x<=tc,25+25*(x-tb)/(tc-tb),x<=te,50+25*(x-tc)/(te-tc),x<tf,75+25*(x-te)/(tf-te),TRUE,100))) -> 24.381167 | H60: =IF(Inputs!H60="","",LET(d,Rulebook!$L60,x,Inputs!H60*d,ta,Rulebook!$G60*d,tb,Rulebook!$H60*d,tc,Rulebook!$I60*d,te,Rulebook!$J60*d,tf,Rulebook!$K60*d,IFS(x<=ta,0,x<=tb,25*(x-ta)/(tb-ta),x<=tc,25+25*(x-tb)/(tc-tb),x<=te,50+25*(x-tc)/(te-tc),x<tf,75+25*(x-te)/(tf-te),TRUE,100))) -> 29.166667 | I60: =IF(Inputs!I60="","",LET(d,Rulebook!$L60,x,Inputs!I60*d,ta,Rulebook!$G60*d,tb,Rulebook!$H60*d,tc,Rulebook!$I60*d,te,Rulebook!$J60*d,tf,Rulebook!$K60*d,IFS(x<=ta,0,x<=tb,25*(x-ta)/(tb-ta),x<=tc,25+25*(x-tb)/(tc-tb),x<=te,50+25*(x-tc)/(te-tc),x<tf,75+25*(x-te)/(tf-te),TRUE,100))) -> 0 | J60: =IF(Inputs!J60="","",LET(d,Rulebook!$L60,x,Inputs!J60*d,ta,Rulebook!$G60*d,tb,Rulebook!$H60*d,tc,Rulebook!$I60*d,te,Rulebook!$J60*d,tf,Rulebook!$K60*d,IFS(x<=ta,0,x<=tb,25*(x-ta)/(tb-ta),x<=tc,25+25*(x-tb)/(tc-tb),x<=te,50+25*(x-tc)/(te-tc),x<tf,75+25*(x-te)/(tf-te),TRUE,100))) -> 0 | K60: =IF(Inputs!K60="","",LET(d,Rulebook!$L60,x,Inputs!K60*d,ta,Rulebook!$G60*d,tb,Rulebook!$H60*d,tc,Rulebook!$I60*d,te,Rulebook!$J60*d,tf,Rulebook!$K60*d,IFS(x<=ta,0,x<=tb,25*(x-ta)/(tb-ta),x<=tc,25+25*(x-tb)/(tc-tb),x<=te,50+25*(x-tc)/(te-tc),x<tf,75+25*(x-te)/(tf-te),TRUE,100))) -> 0 | L60: =IF(Inputs!L60="","",LET(d,Rulebook!$L60,x,Inputs!L60*d,ta,Rulebook!$G60*d,tb,Rulebook!$H60*d,tc,Rulebook!$I60*d,te,Rulebook!$J60*d,tf,Rulebook!$K60*d,IFS(x<=ta,0,x<=tb,25*(x-ta)/(tb-ta),x<=tc,25+25*(x-tb)/(tc-tb),x<=te,50+25*(x-tc)/(te-tc),x<tf,75+25*(x-te)/(tf-te),TRUE,100))) -> 72.142857 | ... V60: =IF(Inputs!V60="","",LET(d,Rulebook!$L60,x,Inputs!V60*d,ta,Rulebook!$G60*d,tb,Rulebook!$H60*d,tc,Rulebook!$I60*d,te,Rulebook!$J60*d,tf,Rulebook!$K60*d,IFS(x<=ta,0,x<=tb,25*(x-ta)/(tb-ta),x<=tc,25+25*(x-tb)/(tc-tb),x<=te,50+25*(x-tc)/(te-tc),x<tf,75+25*(x-te)/(tf-te),TRUE,100))) -> 78.333333
A61: 6.1 | B61: 6 | C61: Armed conflict on national territory, past 12 months | D61: level | E61: =IF(Inputs!E61="","",LET(d,Rulebook!$L61,x,Inputs!E61*d,ta,Rulebook!$G61*d,tb,Rulebook!$H61*d,tc,Rulebook!$I61*d,te,Rulebook!$J61*d,tf,Rulebook!$K61*d,IFS(x<=ta,0,x<=tb,25*(x-ta)/(tb-ta),x<=tc,25+25*(x-tb)/(tc-tb),x<=te,50+25*(x-tc)/(te-tc),x<tf,75+25*(x-te)/(tf-te),TRUE,100))) -> 0 | F61: =IF(Inputs!F61="","",LET(d,Rulebook!$L61,x,Inputs!F61*d,ta,Rulebook!$G61*d,tb,Rulebook!$H61*d,tc,Rulebook!$I61*d,te,Rulebook!$J61*d,tf,Rulebook!$K61*d,IFS(x<=ta,0,x<=tb,25*(x-ta)/(tb-ta),x<=tc,25+25*(x-tb)/(tc-tb),x<=te,50+25*(x-tc)/(te-tc),x<tf,75+25*(x-te)/(tf-te),TRUE,100))) -> 50 | G61: =IF(Inputs!G61="","",LET(d,Rulebook!$L61,x,Inputs!G61*d,ta,Rulebook!$G61*d,tb,Rulebook!$H61*d,tc,Rulebook!$I61*d,te,Rulebook!$J61*d,tf,Rulebook!$K61*d,IFS(x<=ta,0,x<=tb,25*(x-ta)/(tb-ta),x<=tc,25+25*(x-tb)/(tc-tb),x<=te,50+25*(x-tc)/(te-tc),x<tf,75+25*(x-te)/(tf-te),TRUE,100))) -> 0 | H61: =IF(Inputs!H61="","",LET(d,Rulebook!$L61,x,Inputs!H61*d,ta,Rulebook!$G61*d,tb,Rulebook!$H61*d,tc,Rulebook!$I61*d,te,Rulebook!$J61*d,tf,Rulebook!$K61*d,IFS(x<=ta,0,x<=tb,25*(x-ta)/(tb-ta),x<=tc,25+25*(x-tb)/(tc-tb),x<=te,50+25*(x-tc)/(te-tc),x<tf,75+25*(x-te)/(tf-te),TRUE,100))) -> 0 | I61: =IF(Inputs!I61="","",LET(d,Rulebook!$L61,x,Inputs!I61*d,ta,Rulebook!$G61*d,tb,Rulebook!$H61*d,tc,Rulebook!$I61*d,te,Rulebook!$J61*d,tf,Rulebook!$K61*d,IFS(x<=ta,0,x<=tb,25*(x-ta)/(tb-ta),x<=tc,25+25*(x-tb)/(tc-tb),x<=te,50+25*(x-tc)/(te-tc),x<tf,75+25*(x-te)/(tf-te),TRUE,100))) -> 0 | J61: =IF(Inputs!J61="","",LET(d,Rulebook!$L61,x,Inputs!J61*d,ta,Rulebook!$G61*d,tb,Rulebook!$H61*d,tc,Rulebook!$I61*d,te,Rulebook!$J61*d,tf,Rulebook!$K61*d,IFS(x<=ta,0,x<=tb,25*(x-ta)/(tb-ta),x<=tc,25+25*(x-tb)/(tc-tb),x<=te,50+25*(x-tc)/(te-tc),x<tf,75+25*(x-te)/(tf-te),TRUE,100))) -> 0 | K61: =IF(Inputs!K61="","",LET(d,Rulebook!$L61,x,Inputs!K61*d,ta,Rulebook!$G61*d,tb,Rulebook!$H61*d,tc,Rulebook!$I61*d,te,Rulebook!$J61*d,tf,Rulebook!$K61*d,IFS(x<=ta,0,x<=tb,25*(x-ta)/(tb-ta),x<=tc,25+25*(x-tb)/(tc-tb),x<=te,50+25*(x-tc)/(te-tc),x<tf,75+25*(x-te)/(tf-te),TRUE,100))) -> 0 | L61: =IF(Inputs!L61="","",LET(d,Rulebook!$L61,x,Inputs!L61*d,ta,Rulebook!$G61*d,tb,Rulebook!$H61*d,tc,Rulebook!$I61*d,te,Rulebook!$J61*d,tf,Rulebook!$K61*d,IFS(x<=ta,0,x<=tb,25*(x-ta)/(tb-ta),x<=tc,25+25*(x-tb)/(tc-tb),x<=te,50+25*(x-tc)/(te-tc),x<tf,75+25*(x-te)/(tf-te),TRUE,100))) -> 50 | ... V61: =IF(Inputs!V61="","",LET(d,Rulebook!$L61,x,Inputs!V61*d,ta,Rulebook!$G61*d,tb,Rulebook!$H61*d,tc,Rulebook!$I61*d,te,Rulebook!$J61*d,tf,Rulebook!$K61*d,IFS(x<=ta,0,x<=tb,25*(x-ta)/(tb-ta),x<=tc,25+25*(x-tb)/(tc-tb),x<=te,50+25*(x-tc)/(te-tc),x<tf,75+25*(x-te)/(tf-te),TRUE,100))) -> 0
A62: 6.2 | B62: 6 | C62: Homicide rate | D62: per 100,000 | E62: =IF(Inputs!E62="","",LET(d,Rulebook!$L62,x,Inputs!E62*d,ta,Rulebook!$G62*d,tb,Rulebook!$H62*d,tc,Rulebook!$I62*d,te,Rulebook!$J62*d,tf,Rulebook!$K62*d,IFS(x<=ta,0,x<=tb,25*(x-ta)/(tb-ta),x<=tc,25+25*(x-tb)/(tc-tb),x<=te,50+25*(x-tc)/(te-tc),x<tf,75+25*(x-te)/(tf-te),TRUE,100))) -> 0 | F62: =IF(Inputs!F62="","",LET(d,Rulebook!$L62,x,Inputs!F62*d,ta,Rulebook!$G62*d,tb,Rulebook!$H62*d,tc,Rulebook!$I62*d,te,Rulebook!$J62*d,tf,Rulebook!$K62*d,IFS(x<=ta,0,x<=tb,25*(x-ta)/(tb-ta),x<=tc,25+25*(x-tb)/(tc-tb),x<=te,50+25*(x-tc)/(te-tc),x<tf,75+25*(x-te)/(tf-te),TRUE,100))) -> 20.833333 | G62: =IF(Inputs!G62="","",LET(d,Rulebook!$L62,x,Inputs!G62*d,ta,Rulebook!$G62*d,tb,Rulebook!$H62*d,tc,Rulebook!$I62*d,te,Rulebook!$J62*d,tf,Rulebook!$K62*d,IFS(x<=ta,0,x<=tb,25*(x-ta)/(tb-ta),x<=tc,25+25*(x-tb)/(tc-tb),x<=te,50+25*(x-tc)/(te-tc),x<tf,75+25*(x-te)/(tf-te),TRUE,100))) -> 0 | H62: =IF(Inputs!H62="","",LET(d,Rulebook!$L62,x,Inputs!H62*d,ta,Rulebook!$G62*d,tb,Rulebook!$H62*d,tc,Rulebook!$I62*d,te,Rulebook!$J62*d,tf,Rulebook!$K62*d,IFS(x<=ta,0,x<=tb,25*(x-ta)/(tb-ta),x<=tc,25+25*(x-tb)/(tc-tb),x<=te,50+25*(x-tc)/(te-tc),x<tf,75+25*(x-te)/(tf-te),TRUE,100))) -> 0 | I62: =IF(Inputs!I62="","",LET(d,Rulebook!$L62,x,Inputs!I62*d,ta,Rulebook!$G62*d,tb,Rulebook!$H62*d,tc,Rulebook!$I62*d,te,Rulebook!$J62*d,tf,Rulebook!$K62*d,IFS(x<=ta,0,x<=tb,25*(x-ta)/(tb-ta),x<=tc,25+25*(x-tb)/(tc-tb),x<=te,50+25*(x-tc)/(te-tc),x<tf,75+25*(x-te)/(tf-te),TRUE,100))) -> 0 | J62: =IF(Inputs!J62="","",LET(d,Rulebook!$L62,x,Inputs!J62*d,ta,Rulebook!$G62*d,tb,Rulebook!$H62*d,tc,Rulebook!$I62*d,te,Rulebook!$J62*d,tf,Rulebook!$K62*d,IFS(x<=ta,0,x<=tb,25*(x-ta)/(tb-ta),x<=tc,25+25*(x-tb)/(tc-tb),x<=te,50+25*(x-tc)/(te-tc),x<tf,75+25*(x-te)/(tf-te),TRUE,100))) -> 0 | K62: =IF(Inputs!K62="","",LET(d,Rulebook!$L62,x,Inputs!K62*d,ta,Rulebook!$G62*d,tb,Rulebook!$H62*d,tc,Rulebook!$I62*d,te,Rulebook!$J62*d,tf,Rulebook!$K62*d,IFS(x<=ta,0,x<=tb,25*(x-ta)/(tb-ta),x<=tc,25+25*(x-tb)/(tc-tb),x<=te,50+25*(x-tc)/(te-tc),x<tf,75+25*(x-te)/(tf-te),TRUE,100))) -> 0 | L62: =IF(Inputs!L62="","",LET(d,Rulebook!$L62,x,Inputs!L62*d,ta,Rulebook!$G62*d,tb,Rulebook!$H62*d,tc,Rulebook!$I62*d,te,Rulebook!$J62*d,tf,Rulebook!$K62*d,IFS(x<=ta,0,x<=tb,25*(x-ta)/(tb-ta),x<=tc,25+25*(x-tb)/(tc-tb),x<=te,50+25*(x-tc)/(te-tc),x<tf,75+25*(x-te)/(tf-te),TRUE,100))) -> 6.6666667 | ... V62: =IF(Inputs!V62="","",LET(d,Rulebook!$L62,x,Inputs!V62*d,ta,Rulebook!$G62*d,tb,Rulebook!$H62*d,tc,Rulebook!$I62*d,te,Rulebook!$J62*d,tf,Rulebook!$K62*d,IFS(x<=ta,0,x<=tb,25*(x-ta)/(tb-ta),x<=tc,25+25*(x-tb)/(tc-tb),x<=te,50+25*(x-tc)/(te-tc),x<tf,75+25*(x-te)/(tf-te),TRUE,100))) -> 25
A63: 6.3 | B63: 6 | C63: Gang control and extortion | D63: level | E63: =IF(Inputs!E63="","",LET(d,Rulebook!$L63,x,Inputs!E63*d,ta,Rulebook!$G63*d,tb,Rulebook!$H63*d,tc,Rulebook!$I63*d,te,Rulebook!$J63*d,tf,Rulebook!$K63*d,IFS(x<=ta,0,x<=tb,25*(x-ta)/(tb-ta),x<=tc,25+25*(x-tb)/(tc-tb),x<=te,50+25*(x-tc)/(te-tc),x<tf,75+25*(x-te)/(tf-te),TRUE,100))) -> 0 | F63: =IF(Inputs!F63="","",LET(d,Rulebook!$L63,x,Inputs!F63*d,ta,Rulebook!$G63*d,tb,Rulebook!$H63*d,tc,Rulebook!$I63*d,te,Rulebook!$J63*d,tf,Rulebook!$K63*d,IFS(x<=ta,0,x<=tb,25*(x-ta)/(tb-ta),x<=tc,25+25*(x-tb)/(tc-tb),x<=te,50+25*(x-tc)/(te-tc),x<tf,75+25*(x-te)/(tf-te),TRUE,100))) -> 25 | G63: =IF(Inputs!G63="","",LET(d,Rulebook!$L63,x,Inputs!G63*d,ta,Rulebook!$G63*d,tb,Rulebook!$H63*d,tc,Rulebook!$I63*d,te,Rulebook!$J63*d,tf,Rulebook!$K63*d,IFS(x<=ta,0,x<=tb,25*(x-ta)/(tb-ta),x<=tc,25+25*(x-tb)/(tc-tb),x<=te,50+25*(x-tc)/(te-tc),x<tf,75+25*(x-te)/(tf-te),TRUE,100))) -> 0 | H63: =IF(Inputs!H63="","",LET(d,Rulebook!$L63,x,Inputs!H63*d,ta,Rulebook!$G63*d,tb,Rulebook!$H63*d,tc,Rulebook!$I63*d,te,Rulebook!$J63*d,tf,Rulebook!$K63*d,IFS(x<=ta,0,x<=tb,25*(x-ta)/(tb-ta),x<=tc,25+25*(x-tb)/(tc-tb),x<=te,50+25*(x-tc)/(te-tc),x<tf,75+25*(x-te)/(tf-te),TRUE,100))) -> 0 | I63: =IF(Inputs!I63="","",LET(d,Rulebook!$L63,x,Inputs!I63*d,ta,Rulebook!$G63*d,tb,Rulebook!$H63*d,tc,Rulebook!$I63*d,te,Rulebook!$J63*d,tf,Rulebook!$K63*d,IFS(x<=ta,0,x<=tb,25*(x-ta)/(tb-ta),x<=tc,25+25*(x-tb)/(tc-tb),x<=te,50+25*(x-tc)/(te-tc),x<tf,75+25*(x-te)/(tf-te),TRUE,100))) -> 0 | J63: =IF(Inputs!J63="","",LET(d,Rulebook!$L63,x,Inputs!J63*d,ta,Rulebook!$G63*d,tb,Rulebook!$H63*d,tc,Rulebook!$I63*d,te,Rulebook!$J63*d,tf,Rulebook!$K63*d,IFS(x<=ta,0,x<=tb,25*(x-ta)/(tb-ta),x<=tc,25+25*(x-tb)/(tc-tb),x<=te,50+25*(x-tc)/(te-tc),x<tf,75+25*(x-te)/(tf-te),TRUE,100))) -> 0 | K63: =IF(Inputs!K63="","",LET(d,Rulebook!$L63,x,Inputs!K63*d,ta,Rulebook!$G63*d,tb,Rulebook!$H63*d,tc,Rulebook!$I63*d,te,Rulebook!$J63*d,tf,Rulebook!$K63*d,IFS(x<=ta,0,x<=tb,25*(x-ta)/(tb-ta),x<=tc,25+25*(x-tb)/(tc-tb),x<=te,50+25*(x-tc)/(te-tc),x<tf,75+25*(x-te)/(tf-te),TRUE,100))) -> 0 | L63: =IF(Inputs!L63="","",LET(d,Rulebook!$L63,x,Inputs!L63*d,ta,Rulebook!$G63*d,tb,Rulebook!$H63*d,tc,Rulebook!$I63*d,te,Rulebook!$J63*d,tf,Rulebook!$K63*d,IFS(x<=ta,0,x<=tb,25*(x-ta)/(tb-ta),x<=tc,25+25*(x-tb)/(tc-tb),x<=te,50+25*(x-tc)/(te-tc),x<tf,75+25*(x-te)/(tf-te),TRUE,100))) -> 25 | ... V63: =IF(Inputs!V63="","",LET(d,Rulebook!$L63,x,Inputs!V63*d,ta,Rulebook!$G63*d,tb,Rulebook!$H63*d,tc,Rulebook!$I63*d,te,Rulebook!$J63*d,tf,Rulebook!$K63*d,IFS(x<=ta,0,x<=tb,25*(x-ta)/(tb-ta),x<=tc,25+25*(x-tb)/(tc-tb),x<=te,50+25*(x-tc)/(te-tc),x<tf,75+25*(x-te)/(tf-te),TRUE,100))) -> 25
A64: 6.4 | B64: 6 | C64: Attacks on business and staff | D64: level | E64: =IF(Inputs!E64="","",LET(d,Rulebook!$L64,x,Inputs!E64*d,ta,Rulebook!$G64*d,tb,Rulebook!$H64*d,tc,Rulebook!$I64*d,te,Rulebook!$J64*d,tf,Rulebook!$K64*d,IFS(x<=ta,0,x<=tb,25*(x-ta)/(tb-ta),x<=tc,25+25*(x-tb)/(tc-tb),x<=te,50+25*(x-tc)/(te-tc),x<tf,75+25*(x-te)/(tf-te),TRUE,100))) -> 0 | F64: =IF(Inputs!F64="","",LET(d,Rulebook!$L64,x,Inputs!F64*d,ta,Rulebook!$G64*d,tb,Rulebook!$H64*d,tc,Rulebook!$I64*d,te,Rulebook!$J64*d,tf,Rulebook!$K64*d,IFS(x<=ta,0,x<=tb,25*(x-ta)/(tb-ta),x<=tc,25+25*(x-tb)/(tc-tb),x<=te,50+25*(x-tc)/(te-tc),x<tf,75+25*(x-te)/(tf-te),TRUE,100))) -> 25 | G64: =IF(Inputs!G64="","",LET(d,Rulebook!$L64,x,Inputs!G64*d,ta,Rulebook!$G64*d,tb,Rulebook!$H64*d,tc,Rulebook!$I64*d,te,Rulebook!$J64*d,tf,Rulebook!$K64*d,IFS(x<=ta,0,x<=tb,25*(x-ta)/(tb-ta),x<=tc,25+25*(x-tb)/(tc-tb),x<=te,50+25*(x-tc)/(te-tc),x<tf,75+25*(x-te)/(tf-te),TRUE,100))) -> 0 | H64: =IF(Inputs!H64="","",LET(d,Rulebook!$L64,x,Inputs!H64*d,ta,Rulebook!$G64*d,tb,Rulebook!$H64*d,tc,Rulebook!$I64*d,te,Rulebook!$J64*d,tf,Rulebook!$K64*d,IFS(x<=ta,0,x<=tb,25*(x-ta)/(tb-ta),x<=tc,25+25*(x-tb)/(tc-tb),x<=te,50+25*(x-tc)/(te-tc),x<tf,75+25*(x-te)/(tf-te),TRUE,100))) -> 0 | I64: =IF(Inputs!I64="","",LET(d,Rulebook!$L64,x,Inputs!I64*d,ta,Rulebook!$G64*d,tb,Rulebook!$H64*d,tc,Rulebook!$I64*d,te,Rulebook!$J64*d,tf,Rulebook!$K64*d,IFS(x<=ta,0,x<=tb,25*(x-ta)/(tb-ta),x<=tc,25+25*(x-tb)/(tc-tb),x<=te,50+25*(x-tc)/(te-tc),x<tf,75+25*(x-te)/(tf-te),TRUE,100))) -> 0 | J64: =IF(Inputs!J64="","",LET(d,Rulebook!$L64,x,Inputs!J64*d,ta,Rulebook!$G64*d,tb,Rulebook!$H64*d,tc,Rulebook!$I64*d,te,Rulebook!$J64*d,tf,Rulebook!$K64*d,IFS(x<=ta,0,x<=tb,25*(x-ta)/(tb-ta),x<=tc,25+25*(x-tb)/(tc-tb),x<=te,50+25*(x-tc)/(te-tc),x<tf,75+25*(x-te)/(tf-te),TRUE,100))) -> 0 | K64: =IF(Inputs!K64="","",LET(d,Rulebook!$L64,x,Inputs!K64*d,ta,Rulebook!$G64*d,tb,Rulebook!$H64*d,tc,Rulebook!$I64*d,te,Rulebook!$J64*d,tf,Rulebook!$K64*d,IFS(x<=ta,0,x<=tb,25*(x-ta)/(tb-ta),x<=tc,25+25*(x-tb)/(tc-tb),x<=te,50+25*(x-tc)/(te-tc),x<tf,75+25*(x-te)/(tf-te),TRUE,100))) -> 0 | L64: =IF(Inputs!L64="","",LET(d,Rulebook!$L64,x,Inputs!L64*d,ta,Rulebook!$G64*d,tb,Rulebook!$H64*d,tc,Rulebook!$I64*d,te,Rulebook!$J64*d,tf,Rulebook!$K64*d,IFS(x<=ta,0,x<=tb,25*(x-ta)/(tb-ta),x<=tc,25+25*(x-tb)/(tc-tb),x<=te,50+25*(x-tc)/(te-tc),x<tf,75+25*(x-te)/(tf-te),TRUE,100))) -> 25 | ... V64: =IF(Inputs!V64="","",LET(d,Rulebook!$L64,x,Inputs!V64*d,ta,Rulebook!$G64*d,tb,Rulebook!$H64*d,tc,Rulebook!$I64*d,te,Rulebook!$J64*d,tf,Rulebook!$K64*d,IFS(x<=ta,0,x<=tb,25*(x-ta)/(tb-ta),x<=tc,25+25*(x-tb)/(tc-tb),x<=te,50+25*(x-tc)/(te-tc),x<tf,75+25*(x-te)/(tf-te),TRUE,100))) -> 25
A65: 6.5 | B65: 6 | C65: State control of territory | D65: level | E65: =IF(Inputs!E65="","",LET(d,Rulebook!$L65,x,Inputs!E65*d,ta,Rulebook!$G65*d,tb,Rulebook!$H65*d,tc,Rulebook!$I65*d,te,Rulebook!$J65*d,tf,Rulebook!$K65*d,IFS(x<=ta,0,x<=tb,25*(x-ta)/(tb-ta),x<=tc,25+25*(x-tb)/(tc-tb),x<=te,50+25*(x-tc)/(te-tc),x<tf,75+25*(x-te)/(tf-te),TRUE,100))) -> 0 | F65: =IF(Inputs!F65="","",LET(d,Rulebook!$L65,x,Inputs!F65*d,ta,Rulebook!$G65*d,tb,Rulebook!$H65*d,tc,Rulebook!$I65*d,te,Rulebook!$J65*d,tf,Rulebook!$K65*d,IFS(x<=ta,0,x<=tb,25*(x-ta)/(tb-ta),x<=tc,25+25*(x-tb)/(tc-tb),x<=te,50+25*(x-tc)/(te-tc),x<tf,75+25*(x-te)/(tf-te),TRUE,100))) -> 25 | G65: =IF(Inputs!G65="","",LET(d,Rulebook!$L65,x,Inputs!G65*d,ta,Rulebook!$G65*d,tb,Rulebook!$H65*d,tc,Rulebook!$I65*d,te,Rulebook!$J65*d,tf,Rulebook!$K65*d,IFS(x<=ta,0,x<=tb,25*(x-ta)/(tb-ta),x<=tc,25+25*(x-tb)/(tc-tb),x<=te,50+25*(x-tc)/(te-tc),x<tf,75+25*(x-te)/(tf-te),TRUE,100))) -> 0 | H65: =IF(Inputs!H65="","",LET(d,Rulebook!$L65,x,Inputs!H65*d,ta,Rulebook!$G65*d,tb,Rulebook!$H65*d,tc,Rulebook!$I65*d,te,Rulebook!$J65*d,tf,Rulebook!$K65*d,IFS(x<=ta,0,x<=tb,25*(x-ta)/(tb-ta),x<=tc,25+25*(x-tb)/(tc-tb),x<=te,50+25*(x-tc)/(te-tc),x<tf,75+25*(x-te)/(tf-te),TRUE,100))) -> 0 | I65: =IF(Inputs!I65="","",LET(d,Rulebook!$L65,x,Inputs!I65*d,ta,Rulebook!$G65*d,tb,Rulebook!$H65*d,tc,Rulebook!$I65*d,te,Rulebook!$J65*d,tf,Rulebook!$K65*d,IFS(x<=ta,0,x<=tb,25*(x-ta)/(tb-ta),x<=tc,25+25*(x-tb)/(tc-tb),x<=te,50+25*(x-tc)/(te-tc),x<tf,75+25*(x-te)/(tf-te),TRUE,100))) -> 0 | J65: =IF(Inputs!J65="","",LET(d,Rulebook!$L65,x,Inputs!J65*d,ta,Rulebook!$G65*d,tb,Rulebook!$H65*d,tc,Rulebook!$I65*d,te,Rulebook!$J65*d,tf,Rulebook!$K65*d,IFS(x<=ta,0,x<=tb,25*(x-ta)/(tb-ta),x<=tc,25+25*(x-tb)/(tc-tb),x<=te,50+25*(x-tc)/(te-tc),x<tf,75+25*(x-te)/(tf-te),TRUE,100))) -> 0 | K65: =IF(Inputs!K65="","",LET(d,Rulebook!$L65,x,Inputs!K65*d,ta,Rulebook!$G65*d,tb,Rulebook!$H65*d,tc,Rulebook!$I65*d,te,Rulebook!$J65*d,tf,Rulebook!$K65*d,IFS(x<=ta,0,x<=tb,25*(x-ta)/(tb-ta),x<=tc,25+25*(x-tb)/(tc-tb),x<=te,50+25*(x-tc)/(te-tc),x<tf,75+25*(x-te)/(tf-te),TRUE,100))) -> 0 | L65: =IF(Inputs!L65="","",LET(d,Rulebook!$L65,x,Inputs!L65*d,ta,Rulebook!$G65*d,tb,Rulebook!$H65*d,tc,Rulebook!$I65*d,te,Rulebook!$J65*d,tf,Rulebook!$K65*d,IFS(x<=ta,0,x<=tb,25*(x-ta)/(tb-ta),x<=tc,25+25*(x-tb)/(tc-tb),x<=te,50+25*(x-tc)/(te-tc),x<tf,75+25*(x-te)/(tf-te),TRUE,100))) -> 25 | ... V65: =IF(Inputs!V65="","",LET(d,Rulebook!$L65,x,Inputs!V65*d,ta,Rulebook!$G65*d,tb,Rulebook!$H65*d,tc,Rulebook!$I65*d,te,Rulebook!$J65*d,tf,Rulebook!$K65*d,IFS(x<=ta,0,x<=tb,25*(x-ta)/(tb-ta),x<=tc,25+25*(x-tb)/(tc-tb),x<=te,50+25*(x-tc)/(te-tc),x<tf,75+25*(x-te)/(tf-te),TRUE,100))) -> 0
A66: 6.6 | B66: 6 | C66: Youth unemployment (15-24) | D66: % | E66: =IF(Inputs!E66="","",LET(d,Rulebook!$L66,x,Inputs!E66*d,ta,Rulebook!$G66*d,tb,Rulebook!$H66*d,tc,Rulebook!$I66*d,te,Rulebook!$J66*d,tf,Rulebook!$K66*d,IFS(x<=ta,0,x<=tb,25*(x-ta)/(tb-ta),x<=tc,25+25*(x-tb)/(tc-tb),x<=te,50+25*(x-tc)/(te-tc),x<tf,75+25*(x-te)/(tf-te),TRUE,100))) -> 0 | F66: =IF(Inputs!F66="","",LET(d,Rulebook!$L66,x,Inputs!F66*d,ta,Rulebook!$G66*d,tb,Rulebook!$H66*d,tc,Rulebook!$I66*d,te,Rulebook!$J66*d,tf,Rulebook!$K66*d,IFS(x<=ta,0,x<=tb,25*(x-ta)/(tb-ta),x<=tc,25+25*(x-tb)/(tc-tb),x<=te,50+25*(x-tc)/(te-tc),x<tf,75+25*(x-te)/(tf-te),TRUE,100))) -> 12.5 | G66: =IF(Inputs!G66="","",LET(d,Rulebook!$L66,x,Inputs!G66*d,ta,Rulebook!$G66*d,tb,Rulebook!$H66*d,tc,Rulebook!$I66*d,te,Rulebook!$J66*d,tf,Rulebook!$K66*d,IFS(x<=ta,0,x<=tb,25*(x-ta)/(tb-ta),x<=tc,25+25*(x-tb)/(tc-tb),x<=te,50+25*(x-tc)/(te-tc),x<tf,75+25*(x-te)/(tf-te),TRUE,100))) -> 45.833333 | H66: =IF(Inputs!H66="","",LET(d,Rulebook!$L66,x,Inputs!H66*d,ta,Rulebook!$G66*d,tb,Rulebook!$H66*d,tc,Rulebook!$I66*d,te,Rulebook!$J66*d,tf,Rulebook!$K66*d,IFS(x<=ta,0,x<=tb,25*(x-ta)/(tb-ta),x<=tc,25+25*(x-tb)/(tc-tb),x<=te,50+25*(x-tc)/(te-tc),x<tf,75+25*(x-te)/(tf-te),TRUE,100))) -> 18.75 | I66: =IF(Inputs!I66="","",LET(d,Rulebook!$L66,x,Inputs!I66*d,ta,Rulebook!$G66*d,tb,Rulebook!$H66*d,tc,Rulebook!$I66*d,te,Rulebook!$J66*d,tf,Rulebook!$K66*d,IFS(x<=ta,0,x<=tb,25*(x-ta)/(tb-ta),x<=tc,25+25*(x-tb)/(tc-tb),x<=te,50+25*(x-tc)/(te-tc),x<tf,75+25*(x-te)/(tf-te),TRUE,100))) -> 0 | J66: =IF(Inputs!J66="","",LET(d,Rulebook!$L66,x,Inputs!J66*d,ta,Rulebook!$G66*d,tb,Rulebook!$H66*d,tc,Rulebook!$I66*d,te,Rulebook!$J66*d,tf,Rulebook!$K66*d,IFS(x<=ta,0,x<=tb,25*(x-ta)/(tb-ta),x<=tc,25+25*(x-tb)/(tc-tb),x<=te,50+25*(x-tc)/(te-tc),x<tf,75+25*(x-te)/(tf-te),TRUE,100))) -> 0 | K66: =IF(Inputs!K66="","",LET(d,Rulebook!$L66,x,Inputs!K66*d,ta,Rulebook!$G66*d,tb,Rulebook!$H66*d,tc,Rulebook!$I66*d,te,Rulebook!$J66*d,tf,Rulebook!$K66*d,IFS(x<=ta,0,x<=tb,25*(x-ta)/(tb-ta),x<=tc,25+25*(x-tb)/(tc-tb),x<=te,50+25*(x-tc)/(te-tc),x<tf,75+25*(x-te)/(tf-te),TRUE,100))) -> 0 | L66: =IF(Inputs!L66="","",LET(d,Rulebook!$L66,x,Inputs!L66*d,ta,Rulebook!$G66*d,tb,Rulebook!$H66*d,tc,Rulebook!$I66*d,te,Rulebook!$J66*d,tf,Rulebook!$K66*d,IFS(x<=ta,0,x<=tb,25*(x-ta)/(tb-ta),x<=tc,25+25*(x-tb)/(tc-tb),x<=te,50+25*(x-tc)/(te-tc),x<tf,75+25*(x-te)/(tf-te),TRUE,100))) -> 41.666667 | ... V66: =IF(Inputs!V66="","",LET(d,Rulebook!$L66,x,Inputs!V66*d,ta,Rulebook!$G66*d,tb,Rulebook!$H66*d,tc,Rulebook!$I66*d,te,Rulebook!$J66*d,tf,Rulebook!$K66*d,IFS(x<=ta,0,x<=tb,25*(x-ta)/(tb-ta),x<=tc,25+25*(x-tb)/(tc-tb),x<=te,50+25*(x-tc)/(te-tc),x<tf,75+25*(x-te)/(tf-te),TRUE,100))) -> 37.5
A67: 6.7 | B67: 6 | C67: Illegal economy: criminal markets score (GOCI) | D67: score 1-10 | E67: =IF(Inputs!E67="","",LET(d,Rulebook!$L67,x,Inputs!E67*d,ta,Rulebook!$G67*d,tb,Rulebook!$H67*d,tc,Rulebook!$I67*d,te,Rulebook!$J67*d,tf,Rulebook!$K67*d,IFS(x<=ta,0,x<=tb,25*(x-ta)/(tb-ta),x<=tc,25+25*(x-tb)/(tc-tb),x<=te,50+25*(x-tc)/(te-tc),x<tf,75+25*(x-te)/(tf-te),TRUE,100))) -> 58.333333 | F67: =IF(Inputs!F67="","",LET(d,Rulebook!$L67,x,Inputs!F67*d,ta,Rulebook!$G67*d,tb,Rulebook!$H67*d,tc,Rulebook!$I67*d,te,Rulebook!$J67*d,tf,Rulebook!$K67*d,IFS(x<=ta,0,x<=tb,25*(x-ta)/(tb-ta),x<=tc,25+25*(x-tb)/(tc-tb),x<=te,50+25*(x-tc)/(te-tc),x<tf,75+25*(x-te)/(tf-te),TRUE,100))) -> 66.666667 | G67: =IF(Inputs!G67="","",LET(d,Rulebook!$L67,x,Inputs!G67*d,ta,Rulebook!$G67*d,tb,Rulebook!$H67*d,tc,Rulebook!$I67*d,te,Rulebook!$J67*d,tf,Rulebook!$K67*d,IFS(x<=ta,0,x<=tb,25*(x-ta)/(tb-ta),x<=tc,25+25*(x-tb)/(tc-tb),x<=te,50+25*(x-tc)/(te-tc),x<tf,75+25*(x-te)/(tf-te),TRUE,100))) -> 68.333333 | H67: =IF(Inputs!H67="","",LET(d,Rulebook!$L67,x,Inputs!H67*d,ta,Rulebook!$G67*d,tb,Rulebook!$H67*d,tc,Rulebook!$I67*d,te,Rulebook!$J67*d,tf,Rulebook!$K67*d,IFS(x<=ta,0,x<=tb,25*(x-ta)/(tb-ta),x<=tc,25+25*(x-tb)/(tc-tb),x<=te,50+25*(x-tc)/(te-tc),x<tf,75+25*(x-te)/(tf-te),TRUE,100))) -> 58.333333 | I67: =IF(Inputs!I67="","",LET(d,Rulebook!$L67,x,Inputs!I67*d,ta,Rulebook!$G67*d,tb,Rulebook!$H67*d,tc,Rulebook!$I67*d,te,Rulebook!$J67*d,tf,Rulebook!$K67*d,IFS(x<=ta,0,x<=tb,25*(x-ta)/(tb-ta),x<=tc,25+25*(x-tb)/(tc-tb),x<=te,50+25*(x-tc)/(te-tc),x<tf,75+25*(x-te)/(tf-te),TRUE,100))) -> 12.5 | J67: =IF(Inputs!J67="","",LET(d,Rulebook!$L67,x,Inputs!J67*d,ta,Rulebook!$G67*d,tb,Rulebook!$H67*d,tc,Rulebook!$I67*d,te,Rulebook!$J67*d,tf,Rulebook!$K67*d,IFS(x<=ta,0,x<=tb,25*(x-ta)/(tb-ta),x<=tc,25+25*(x-tb)/(tc-tb),x<=te,50+25*(x-tc)/(te-tc),x<tf,75+25*(x-te)/(tf-te),TRUE,100))) -> 30 | K67: =IF(Inputs!K67="","",LET(d,Rulebook!$L67,x,Inputs!K67*d,ta,Rulebook!$G67*d,tb,Rulebook!$H67*d,tc,Rulebook!$I67*d,te,Rulebook!$J67*d,tf,Rulebook!$K67*d,IFS(x<=ta,0,x<=tb,25*(x-ta)/(tb-ta),x<=tc,25+25*(x-tb)/(tc-tb),x<=te,50+25*(x-tc)/(te-tc),x<tf,75+25*(x-te)/(tf-te),TRUE,100))) -> 28.333333 | L67: =IF(Inputs!L67="","",LET(d,Rulebook!$L67,x,Inputs!L67*d,ta,Rulebook!$G67*d,tb,Rulebook!$H67*d,tc,Rulebook!$I67*d,te,Rulebook!$J67*d,tf,Rulebook!$K67*d,IFS(x<=ta,0,x<=tb,25*(x-ta)/(tb-ta),x<=tc,25+25*(x-tb)/(tc-tb),x<=te,50+25*(x-tc)/(te-tc),x<tf,75+25*(x-te)/(tf-te),TRUE,100))) -> 56.666667 | ... V67: =IF(Inputs!V67="","",LET(d,Rulebook!$L67,x,Inputs!V67*d,ta,Rulebook!$G67*d,tb,Rulebook!$H67*d,tc,Rulebook!$I67*d,te,Rulebook!$J67*d,tf,Rulebook!$K67*d,IFS(x<=ta,0,x<=tb,25*(x-ta)/(tb-ta),x<=tc,25+25*(x-tb)/(tc-tb),x<=te,50+25*(x-tc)/(te-tc),x<tf,75+25*(x-te)/(tf-te),TRUE,100))) -> 56.666667
A68: 6.8 | B68: 6 | C68: Cyber attacks on state systems | D68: level | E68: =IF(Inputs!E68="","",LET(d,Rulebook!$L68,x,Inputs!E68*d,ta,Rulebook!$G68*d,tb,Rulebook!$H68*d,tc,Rulebook!$I68*d,te,Rulebook!$J68*d,tf,Rulebook!$K68*d,IFS(x<=ta,0,x<=tb,25*(x-ta)/(tb-ta),x<=tc,25+25*(x-tb)/(tc-tb),x<=te,50+25*(x-tc)/(te-tc),x<tf,75+25*(x-te)/(tf-te),TRUE,100))) -> 25 | F68: =IF(Inputs!F68="","",LET(d,Rulebook!$L68,x,Inputs!F68*d,ta,Rulebook!$G68*d,tb,Rulebook!$H68*d,tc,Rulebook!$I68*d,te,Rulebook!$J68*d,tf,Rulebook!$K68*d,IFS(x<=ta,0,x<=tb,25*(x-ta)/(tb-ta),x<=tc,25+25*(x-tb)/(tc-tb),x<=te,50+25*(x-tc)/(te-tc),x<tf,75+25*(x-te)/(tf-te),TRUE,100))) -> 50 | G68: =IF(Inputs!G68="","",LET(d,Rulebook!$L68,x,Inputs!G68*d,ta,Rulebook!$G68*d,tb,Rulebook!$H68*d,tc,Rulebook!$I68*d,te,Rulebook!$J68*d,tf,Rulebook!$K68*d,IFS(x<=ta,0,x<=tb,25*(x-ta)/(tb-ta),x<=tc,25+25*(x-tb)/(tc-tb),x<=te,50+25*(x-tc)/(te-tc),x<tf,75+25*(x-te)/(tf-te),TRUE,100))) -> 25 | H68: =IF(Inputs!H68="","",LET(d,Rulebook!$L68,x,Inputs!H68*d,ta,Rulebook!$G68*d,tb,Rulebook!$H68*d,tc,Rulebook!$I68*d,te,Rulebook!$J68*d,tf,Rulebook!$K68*d,IFS(x<=ta,0,x<=tb,25*(x-ta)/(tb-ta),x<=tc,25+25*(x-tb)/(tc-tb),x<=te,50+25*(x-tc)/(te-tc),x<tf,75+25*(x-te)/(tf-te),TRUE,100))) -> 25 | I68: =IF(Inputs!I68="","",LET(d,Rulebook!$L68,x,Inputs!I68*d,ta,Rulebook!$G68*d,tb,Rulebook!$H68*d,tc,Rulebook!$I68*d,te,Rulebook!$J68*d,tf,Rulebook!$K68*d,IFS(x<=ta,0,x<=tb,25*(x-ta)/(tb-ta),x<=tc,25+25*(x-tb)/(tc-tb),x<=te,50+25*(x-tc)/(te-tc),x<tf,75+25*(x-te)/(tf-te),TRUE,100))) -> 0 | J68: =IF(Inputs!J68="","",LET(d,Rulebook!$L68,x,Inputs!J68*d,ta,Rulebook!$G68*d,tb,Rulebook!$H68*d,tc,Rulebook!$I68*d,te,Rulebook!$J68*d,tf,Rulebook!$K68*d,IFS(x<=ta,0,x<=tb,25*(x-ta)/(tb-ta),x<=tc,25+25*(x-tb)/(tc-tb),x<=te,50+25*(x-tc)/(te-tc),x<tf,75+25*(x-te)/(tf-te),TRUE,100))) -> 25 | K68: =IF(Inputs!K68="","",LET(d,Rulebook!$L68,x,Inputs!K68*d,ta,Rulebook!$G68*d,tb,Rulebook!$H68*d,tc,Rulebook!$I68*d,te,Rulebook!$J68*d,tf,Rulebook!$K68*d,IFS(x<=ta,0,x<=tb,25*(x-ta)/(tb-ta),x<=tc,25+25*(x-tb)/(tc-tb),x<=te,50+25*(x-tc)/(te-tc),x<tf,75+25*(x-te)/(tf-te),TRUE,100))) -> 25 | L68: =IF(Inputs!L68="","",LET(d,Rulebook!$L68,x,Inputs!L68*d,ta,Rulebook!$G68*d,tb,Rulebook!$H68*d,tc,Rulebook!$I68*d,te,Rulebook!$J68*d,tf,Rulebook!$K68*d,IFS(x<=ta,0,x<=tb,25*(x-ta)/(tb-ta),x<=tc,25+25*(x-tb)/(tc-tb),x<=te,50+25*(x-tc)/(te-tc),x<tf,75+25*(x-te)/(tf-te),TRUE,100))) -> 25 | ... V68: =IF(Inputs!V68="","",LET(d,Rulebook!$L68,x,Inputs!V68*d,ta,Rulebook!$G68*d,tb,Rulebook!$H68*d,tc,Rulebook!$I68*d,te,Rulebook!$J68*d,tf,Rulebook!$K68*d,IFS(x<=ta,0,x<=tb,25*(x-ta)/(tb-ta),x<=tc,25+25*(x-tb)/(tc-tb),x<=te,50+25*(x-tc)/(te-tc),x<tf,75+25*(x-te)/(tf-te),TRUE,100))) -> 50
A69: 6.9 | B69: 6 | C69: Political violence trend (ACLED, 12m vs 5y average) | D69: ratio | E69: =IF(Inputs!E69="","",LET(d,Rulebook!$L69,x,Inputs!E69*d,ta,Rulebook!$G69*d,tb,Rulebook!$H69*d,tc,Rulebook!$I69*d,te,Rulebook!$J69*d,tf,Rulebook!$K69*d,IFS(x<=ta,0,x<=tb,25*(x-ta)/(tb-ta),x<=tc,25+25*(x-tb)/(tc-tb),x<=te,50+25*(x-tc)/(te-tc),x<tf,75+25*(x-te)/(tf-te),TRUE,100))) -> 25 | F69: =IF(Inputs!F69="","",LET(d,Rulebook!$L69,x,Inputs!F69*d,ta,Rulebook!$G69*d,tb,Rulebook!$H69*d,tc,Rulebook!$I69*d,te,Rulebook!$J69*d,tf,Rulebook!$K69*d,IFS(x<=ta,0,x<=tb,25*(x-ta)/(tb-ta),x<=tc,25+25*(x-tb)/(tc-tb),x<=te,50+25*(x-tc)/(te-tc),x<tf,75+25*(x-te)/(tf-te),TRUE,100))) -> 12.5 | G69: =IF(Inputs!G69="","",LET(d,Rulebook!$L69,x,Inputs!G69*d,ta,Rulebook!$G69*d,tb,Rulebook!$H69*d,tc,Rulebook!$I69*d,te,Rulebook!$J69*d,tf,Rulebook!$K69*d,IFS(x<=ta,0,x<=tb,25*(x-ta)/(tb-ta),x<=tc,25+25*(x-tb)/(tc-tb),x<=te,50+25*(x-tc)/(te-tc),x<tf,75+25*(x-te)/(tf-te),TRUE,100))) -> 25 | H69: =IF(Inputs!H69="","",LET(d,Rulebook!$L69,x,Inputs!H69*d,ta,Rulebook!$G69*d,tb,Rulebook!$H69*d,tc,Rulebook!$I69*d,te,Rulebook!$J69*d,tf,Rulebook!$K69*d,IFS(x<=ta,0,x<=tb,25*(x-ta)/(tb-ta),x<=tc,25+25*(x-tb)/(tc-tb),x<=te,50+25*(x-tc)/(te-tc),x<tf,75+25*(x-te)/(tf-te),TRUE,100))) -> 25 | I69: =IF(Inputs!I69="","",LET(d,Rulebook!$L69,x,Inputs!I69*d,ta,Rulebook!$G69*d,tb,Rulebook!$H69*d,tc,Rulebook!$I69*d,te,Rulebook!$J69*d,tf,Rulebook!$K69*d,IFS(x<=ta,0,x<=tb,25*(x-ta)/(tb-ta),x<=tc,25+25*(x-tb)/(tc-tb),x<=te,50+25*(x-tc)/(te-tc),x<tf,75+25*(x-te)/(tf-te),TRUE,100))) -> 25 | J69: =IF(Inputs!J69="","",LET(d,Rulebook!$L69,x,Inputs!J69*d,ta,Rulebook!$G69*d,tb,Rulebook!$H69*d,tc,Rulebook!$I69*d,te,Rulebook!$J69*d,tf,Rulebook!$K69*d,IFS(x<=ta,0,x<=tb,25*(x-ta)/(tb-ta),x<=tc,25+25*(x-tb)/(tc-tb),x<=te,50+25*(x-tc)/(te-tc),x<tf,75+25*(x-te)/(tf-te),TRUE,100))) -> 25 | K69: =IF(Inputs!K69="","",LET(d,Rulebook!$L69,x,Inputs!K69*d,ta,Rulebook!$G69*d,tb,Rulebook!$H69*d,tc,Rulebook!$I69*d,te,Rulebook!$J69*d,tf,Rulebook!$K69*d,IFS(x<=ta,0,x<=tb,25*(x-ta)/(tb-ta),x<=tc,25+25*(x-tb)/(tc-tb),x<=te,50+25*(x-tc)/(te-tc),x<tf,75+25*(x-te)/(tf-te),TRUE,100))) -> 25 | L69: =IF(Inputs!L69="","",LET(d,Rulebook!$L69,x,Inputs!L69*d,ta,Rulebook!$G69*d,tb,Rulebook!$H69*d,tc,Rulebook!$I69*d,te,Rulebook!$J69*d,tf,Rulebook!$K69*d,IFS(x<=ta,0,x<=tb,25*(x-ta)/(tb-ta),x<=tc,25+25*(x-tb)/(tc-tb),x<=te,50+25*(x-tc)/(te-tc),x<tf,75+25*(x-te)/(tf-te),TRUE,100))) -> 25 | ... V69: =IF(Inputs!V69="","",LET(d,Rulebook!$L69,x,Inputs!V69*d,ta,Rulebook!$G69*d,tb,Rulebook!$H69*d,tc,Rulebook!$I69*d,te,Rulebook!$J69*d,tf,Rulebook!$K69*d,IFS(x<=ta,0,x<=tb,25*(x-ta)/(tb-ta),x<=tc,25+25*(x-tb)/(tc-tb),x<=te,50+25*(x-tc)/(te-tc),x<tf,75+25*(x-te)/(tf-te),TRUE,100))) -> 25
A70: 6.10 | B70: 6 | C70: Inequality and excluded groups | D70: level | E70: =IF(Inputs!E70="","",LET(d,Rulebook!$L70,x,Inputs!E70*d,ta,Rulebook!$G70*d,tb,Rulebook!$H70*d,tc,Rulebook!$I70*d,te,Rulebook!$J70*d,tf,Rulebook!$K70*d,IFS(x<=ta,0,x<=tb,25*(x-ta)/(tb-ta),x<=tc,25+25*(x-tb)/(tc-tb),x<=te,50+25*(x-tc)/(te-tc),x<tf,75+25*(x-te)/(tf-te),TRUE,100))) -> 25 | F70: =IF(Inputs!F70="","",LET(d,Rulebook!$L70,x,Inputs!F70*d,ta,Rulebook!$G70*d,tb,Rulebook!$H70*d,tc,Rulebook!$I70*d,te,Rulebook!$J70*d,tf,Rulebook!$K70*d,IFS(x<=ta,0,x<=tb,25*(x-ta)/(tb-ta),x<=tc,25+25*(x-tb)/(tc-tb),x<=te,50+25*(x-tc)/(te-tc),x<tf,75+25*(x-te)/(tf-te),TRUE,100))) -> 50 | G70: =IF(Inputs!G70="","",LET(d,Rulebook!$L70,x,Inputs!G70*d,ta,Rulebook!$G70*d,tb,Rulebook!$H70*d,tc,Rulebook!$I70*d,te,Rulebook!$J70*d,tf,Rulebook!$K70*d,IFS(x<=ta,0,x<=tb,25*(x-ta)/(tb-ta),x<=tc,25+25*(x-tb)/(tc-tb),x<=te,50+25*(x-tc)/(te-tc),x<tf,75+25*(x-te)/(tf-te),TRUE,100))) -> 75 | H70: =IF(Inputs!H70="","",LET(d,Rulebook!$L70,x,Inputs!H70*d,ta,Rulebook!$G70*d,tb,Rulebook!$H70*d,tc,Rulebook!$I70*d,te,Rulebook!$J70*d,tf,Rulebook!$K70*d,IFS(x<=ta,0,x<=tb,25*(x-ta)/(tb-ta),x<=tc,25+25*(x-tb)/(tc-tb),x<=te,50+25*(x-tc)/(te-tc),x<tf,75+25*(x-te)/(tf-te),TRUE,100))) -> 50 | I70: =IF(Inputs!I70="","",LET(d,Rulebook!$L70,x,Inputs!I70*d,ta,Rulebook!$G70*d,tb,Rulebook!$H70*d,tc,Rulebook!$I70*d,te,Rulebook!$J70*d,tf,Rulebook!$K70*d,IFS(x<=ta,0,x<=tb,25*(x-ta)/(tb-ta),x<=tc,25+25*(x-tb)/(tc-tb),x<=te,50+25*(x-tc)/(te-tc),x<tf,75+25*(x-te)/(tf-te),TRUE,100))) -> 50 | J70: =IF(Inputs!J70="","",LET(d,Rulebook!$L70,x,Inputs!J70*d,ta,Rulebook!$G70*d,tb,Rulebook!$H70*d,tc,Rulebook!$I70*d,te,Rulebook!$J70*d,tf,Rulebook!$K70*d,IFS(x<=ta,0,x<=tb,25*(x-ta)/(tb-ta),x<=tc,25+25*(x-tb)/(tc-tb),x<=te,50+25*(x-tc)/(te-tc),x<tf,75+25*(x-te)/(tf-te),TRUE,100))) -> 0 | K70: =IF(Inputs!K70="","",LET(d,Rulebook!$L70,x,Inputs!K70*d,ta,Rulebook!$G70*d,tb,Rulebook!$H70*d,tc,Rulebook!$I70*d,te,Rulebook!$J70*d,tf,Rulebook!$K70*d,IFS(x<=ta,0,x<=tb,25*(x-ta)/(tb-ta),x<=tc,25+25*(x-tb)/(tc-tb),x<=te,50+25*(x-tc)/(te-tc),x<tf,75+25*(x-te)/(tf-te),TRUE,100))) -> 0 | L70: =IF(Inputs!L70="","",LET(d,Rulebook!$L70,x,Inputs!L70*d,ta,Rulebook!$G70*d,tb,Rulebook!$H70*d,tc,Rulebook!$I70*d,te,Rulebook!$J70*d,tf,Rulebook!$K70*d,IFS(x<=ta,0,x<=tb,25*(x-ta)/(tb-ta),x<=tc,25+25*(x-tb)/(tc-tb),x<=te,50+25*(x-tc)/(te-tc),x<tf,75+25*(x-te)/(tf-te),TRUE,100))) -> 50 | ... V70: =IF(Inputs!V70="","",LET(d,Rulebook!$L70,x,Inputs!V70*d,ta,Rulebook!$G70*d,tb,Rulebook!$H70*d,tc,Rulebook!$I70*d,te,Rulebook!$J70*d,tf,Rulebook!$K70*d,IFS(x<=ta,0,x<=tb,25*(x-ta)/(tb-ta),x<=tc,25+25*(x-tb)/(tc-tb),x<=te,50+25*(x-tc)/(te-tc),x<tf,75+25*(x-te)/(tf-te),TRUE,100))) -> 50
A71: 6.11 | B71: 6 | C71: Food insecurity: population in IPC phase 3+ | D71: % | E71: =IF(Inputs!E71="","",LET(d,Rulebook!$L71,x,Inputs!E71*d,ta,Rulebook!$G71*d,tb,Rulebook!$H71*d,tc,Rulebook!$I71*d,te,Rulebook!$J71*d,tf,Rulebook!$K71*d,IFS(x<=ta,0,x<=tb,25*(x-ta)/(tb-ta),x<=tc,25+25*(x-tb)/(tc-tb),x<=te,50+25*(x-tc)/(te-tc),x<tf,75+25*(x-te)/(tf-te),TRUE,100))) -> 0 | F71: =IF(Inputs!F71="","",LET(d,Rulebook!$L71,x,Inputs!F71*d,ta,Rulebook!$G71*d,tb,Rulebook!$H71*d,tc,Rulebook!$I71*d,te,Rulebook!$J71*d,tf,Rulebook!$K71*d,IFS(x<=ta,0,x<=tb,25*(x-ta)/(tb-ta),x<=tc,25+25*(x-tb)/(tc-tb),x<=te,50+25*(x-tc)/(te-tc),x<tf,75+25*(x-te)/(tf-te),TRUE,100))) -> 0 | G71: =IF(Inputs!G71="","",LET(d,Rulebook!$L71,x,Inputs!G71*d,ta,Rulebook!$G71*d,tb,Rulebook!$H71*d,tc,Rulebook!$I71*d,te,Rulebook!$J71*d,tf,Rulebook!$K71*d,IFS(x<=ta,0,x<=tb,25*(x-ta)/(tb-ta),x<=tc,25+25*(x-tb)/(tc-tb),x<=te,50+25*(x-tc)/(te-tc),x<tf,75+25*(x-te)/(tf-te),TRUE,100))) -> 0 | H71: =IF(Inputs!H71="","",LET(d,Rulebook!$L71,x,Inputs!H71*d,ta,Rulebook!$G71*d,tb,Rulebook!$H71*d,tc,Rulebook!$I71*d,te,Rulebook!$J71*d,tf,Rulebook!$K71*d,IFS(x<=ta,0,x<=tb,25*(x-ta)/(tb-ta),x<=tc,25+25*(x-tb)/(tc-tb),x<=te,50+25*(x-tc)/(te-tc),x<tf,75+25*(x-te)/(tf-te),TRUE,100))) -> 0 | I71: =IF(Inputs!I71="","",LET(d,Rulebook!$L71,x,Inputs!I71*d,ta,Rulebook!$G71*d,tb,Rulebook!$H71*d,tc,Rulebook!$I71*d,te,Rulebook!$J71*d,tf,Rulebook!$K71*d,IFS(x<=ta,0,x<=tb,25*(x-ta)/(tb-ta),x<=tc,25+25*(x-tb)/(tc-tb),x<=te,50+25*(x-tc)/(te-tc),x<tf,75+25*(x-te)/(tf-te),TRUE,100))) -> 0 | J71: =IF(Inputs!J71="","",LET(d,Rulebook!$L71,x,Inputs!J71*d,ta,Rulebook!$G71*d,tb,Rulebook!$H71*d,tc,Rulebook!$I71*d,te,Rulebook!$J71*d,tf,Rulebook!$K71*d,IFS(x<=ta,0,x<=tb,25*(x-ta)/(tb-ta),x<=tc,25+25*(x-tb)/(tc-tb),x<=te,50+25*(x-tc)/(te-tc),x<tf,75+25*(x-te)/(tf-te),TRUE,100))) -> 0 | K71: =IF(Inputs!K71="","",LET(d,Rulebook!$L71,x,Inputs!K71*d,ta,Rulebook!$G71*d,tb,Rulebook!$H71*d,tc,Rulebook!$I71*d,te,Rulebook!$J71*d,tf,Rulebook!$K71*d,IFS(x<=ta,0,x<=tb,25*(x-ta)/(tb-ta),x<=tc,25+25*(x-tb)/(tc-tb),x<=te,50+25*(x-tc)/(te-tc),x<tf,75+25*(x-te)/(tf-te),TRUE,100))) -> 0 | L71: =IF(Inputs!L71="","",LET(d,Rulebook!$L71,x,Inputs!L71*d,ta,Rulebook!$G71*d,tb,Rulebook!$H71*d,tc,Rulebook!$I71*d,te,Rulebook!$J71*d,tf,Rulebook!$K71*d,IFS(x<=ta,0,x<=tb,25*(x-ta)/(tb-ta),x<=tc,25+25*(x-tb)/(tc-tb),x<=te,50+25*(x-tc)/(te-tc),x<tf,75+25*(x-te)/(tf-te),TRUE,100))) -> 0 | ... V71: =IF(Inputs!V71="","",LET(d,Rulebook!$L71,x,Inputs!V71*d,ta,Rulebook!$G71*d,tb,Rulebook!$H71*d,tc,Rulebook!$I71*d,te,Rulebook!$J71*d,tf,Rulebook!$K71*d,IFS(x<=ta,0,x<=tb,25*(x-ta)/(tb-ta),x<=tc,25+25*(x-tb)/(tc-tb),x<=te,50+25*(x-tc)/(te-tc),x<tf,75+25*(x-te)/(tf-te),TRUE,100))) -> 62.5
... A87: 7.13 | B87: 7 | C87: Recovery speed: years for GDP to regain level after last major disaster | D87: years | E87: =IF(Inputs!E87="","",LET(d,Rulebook!$L87,x,Inputs!E87*d,ta,Rulebook!$G87*d,tb,Rulebook!$H87*d,tc,Rulebook!$I87*d,te,Rulebook!$J87*d,tf,Rulebook!$K87*d,IFS(x<=ta,0,x<=tb,25*(x-ta)/(tb-ta),x<=tc,25+25*(x-tb)/(tc-tb),x<=te,50+25*(x-tc)/(te-tc),x<tf,75+25*(x-te)/(tf-te),TRUE,100))) -> 0 | F87: =IF(Inputs!F87="","",LET(d,Rulebook!$L87,x,Inputs!F87*d,ta,Rulebook!$G87*d,tb,Rulebook!$H87*d,tc,Rulebook!$I87*d,te,Rulebook!$J87*d,tf,Rulebook!$K87*d,IFS(x<=ta,0,x<=tb,25*(x-ta)/(tb-ta),x<=tc,25+25*(x-tb)/(tc-tb),x<=te,50+25*(x-tc)/(te-tc),x<tf,75+25*(x-te)/(tf-te),TRUE,100))) -> 0 | G87: =IF(Inputs!G87="","",LET(d,Rulebook!$L87,x,Inputs!G87*d,ta,Rulebook!$G87*d,tb,Rulebook!$H87*d,tc,Rulebook!$I87*d,te,Rulebook!$J87*d,tf,Rulebook!$K87*d,IFS(x<=ta,0,x<=tb,25*(x-ta)/(tb-ta),x<=tc,25+25*(x-tb)/(tc-tb),x<=te,50+25*(x-tc)/(te-tc),x<tf,75+25*(x-te)/(tf-te),TRUE,100))) -> 0 | H87: =IF(Inputs!H87="","",LET(d,Rulebook!$L87,x,Inputs!H87*d,ta,Rulebook!$G87*d,tb,Rulebook!$H87*d,tc,Rulebook!$I87*d,te,Rulebook!$J87*d,tf,Rulebook!$K87*d,IFS(x<=ta,0,x<=tb,25*(x-ta)/(tb-ta),x<=tc,25+25*(x-tb)/(tc-tb),x<=te,50+25*(x-tc)/(te-tc),x<tf,75+25*(x-te)/(tf-te),TRUE,100))) -> 0 | I87: =IF(Inputs!I87="","",LET(d,Rulebook!$L87,x,Inputs!I87*d,ta,Rulebook!$G87*d,tb,Rulebook!$H87*d,tc,Rulebook!$I87*d,te,Rulebook!$J87*d,tf,Rulebook!$K87*d,IFS(x<=ta,0,x<=tb,25*(x-ta)/(tb-ta),x<=tc,25+25*(x-tb)/(tc-tb),x<=te,50+25*(x-tc)/(te-tc),x<tf,75+25*(x-te)/(tf-te),TRUE,100))) -> 0 | J87: =IF(Inputs!J87="","",LET(d,Rulebook!$L87,x,Inputs!J87*d,ta,Rulebook!$G87*d,tb,Rulebook!$H87*d,tc,Rulebook!$I87*d,te,Rulebook!$J87*d,tf,Rulebook!$K87*d,IFS(x<=ta,0,x<=tb,25*(x-ta)/(tb-ta),x<=tc,25+25*(x-tb)/(tc-tb),x<=te,50+25*(x-tc)/(te-tc),x<tf,75+25*(x-te)/(tf-te),TRUE,100))) -> 25 | K87: =IF(Inputs!K87="","",LET(d,Rulebook!$L87,x,Inputs!K87*d,ta,Rulebook!$G87*d,tb,Rulebook!$H87*d,tc,Rulebook!$I87*d,te,Rulebook!$J87*d,tf,Rulebook!$K87*d,IFS(x<=ta,0,x<=tb,25*(x-ta)/(tb-ta),x<=tc,25+25*(x-tb)/(tc-tb),x<=te,50+25*(x-tc)/(te-tc),x<tf,75+25*(x-te)/(tf-te),TRUE,100))) -> 0 | L87: =IF(Inputs!L87="","",LET(d,Rulebook!$L87,x,Inputs!L87*d,ta,Rulebook!$G87*d,tb,Rulebook!$H87*d,tc,Rulebook!$I87*d,te,Rulebook!$J87*d,tf,Rulebook!$K87*d,IFS(x<=ta,0,x<=tb,25*(x-ta)/(tb-ta),x<=tc,25+25*(x-tb)/(tc-tb),x<=te,50+25*(x-tc)/(te-tc),x<tf,75+25*(x-te)/(tf-te),TRUE,100))) -> 0 | ... V87: =IF(Inputs!V87="","",LET(d,Rulebook!$L87,x,Inputs!V87*d,ta,Rulebook!$G87*d,tb,Rulebook!$H87*d,tc,Rulebook!$I87*d,te,Rulebook!$J87*d,tf,Rulebook!$K87*d,IFS(x<=ta,0,x<=tb,25*(x-ta)/(tb-ta),x<=tc,25+25*(x-tb)/(tc-tb),x<=te,50+25*(x-tc)/(te-tc),x<tf,75+25*(x-te)/(tf-te),TRUE,100))) -> 50

Sheet Stress Scores
A1: Stress Scores: indicator scores on stress-path inputs
A2: Same interpolation as Base Scores, applied to Stress Inputs. Blank where the indicator has no stress path.
A4: {=Rulebook!A4:D87} -> ID | B4: Pillar | C4: Indicator | D4: Unit | E4: =Inputs!E4 -> Vietnam | F4: =Inputs!F4 -> Philippines | G4: =Inputs!G4 -> China | H4: =Inputs!H4 -> Malaysia | I4: =Inputs!I4 -> Singapore | J4: =Inputs!J4 -> Japan | K4: =Inputs!K4 -> South Korea | L4: =Inputs!L4 -> India | ... V4: =Inputs!V4 -> Zimbabwe
A5: 1.1 | B5: 1 | C5: Debt service (interest plus principal) | D5: % of revenue | E5: =IF('Stress Inputs'!E5="","",LET(d,Rulebook!$L5,x,'Stress Inputs'!E5*d,ta,Rulebook!$G5*d,tb,Rulebook!$H5*d,tc,Rulebook!$I5*d,te,Rulebook!$J5*d,tf,Rulebook!$K5*d,IFS(x<=ta,0,x<=tb,25*(x-ta)/(tb-ta),x<=tc,25+25*(x-tb)/(tc-tb),x<=te,50+25*(x-tc)/(te-tc),x<tf,75+25*(x-te)/(tf-te),TRUE,100))) | F5: =IF('Stress Inputs'!F5="","",LET(d,Rulebook!$L5,x,'Stress Inputs'!F5*d,ta,Rulebook!$G5*d,tb,Rulebook!$H5*d,tc,Rulebook!$I5*d,te,Rulebook!$J5*d,tf,Rulebook!$K5*d,IFS(x<=ta,0,x<=tb,25*(x-ta)/(tb-ta),x<=tc,25+25*(x-tb)/(tc-tb),x<=te,50+25*(x-tc)/(te-tc),x<tf,75+25*(x-te)/(tf-te),TRUE,100))) | G5: =IF('Stress Inputs'!G5="","",LET(d,Rulebook!$L5,x,'Stress Inputs'!G5*d,ta,Rulebook!$G5*d,tb,Rulebook!$H5*d,tc,Rulebook!$I5*d,te,Rulebook!$J5*d,tf,Rulebook!$K5*d,IFS(x<=ta,0,x<=tb,25*(x-ta)/(tb-ta),x<=tc,25+25*(x-tb)/(tc-tb),x<=te,50+25*(x-tc)/(te-tc),x<tf,75+25*(x-te)/(tf-te),TRUE,100))) | H5: =IF('Stress Inputs'!H5="","",LET(d,Rulebook!$L5,x,'Stress Inputs'!H5*d,ta,Rulebook!$G5*d,tb,Rulebook!$H5*d,tc,Rulebook!$I5*d,te,Rulebook!$J5*d,tf,Rulebook!$K5*d,IFS(x<=ta,0,x<=tb,25*(x-ta)/(tb-ta),x<=tc,25+25*(x-tb)/(tc-tb),x<=te,50+25*(x-tc)/(te-tc),x<tf,75+25*(x-te)/(tf-te),TRUE,100))) | I5: =IF('Stress Inputs'!I5="","",LET(d,Rulebook!$L5,x,'Stress Inputs'!I5*d,ta,Rulebook!$G5*d,tb,Rulebook!$H5*d,tc,Rulebook!$I5*d,te,Rulebook!$J5*d,tf,Rulebook!$K5*d,IFS(x<=ta,0,x<=tb,25*(x-ta)/(tb-ta),x<=tc,25+25*(x-tb)/(tc-tb),x<=te,50+25*(x-tc)/(te-tc),x<tf,75+25*(x-te)/(tf-te),TRUE,100))) | J5: =IF('Stress Inputs'!J5="","",LET(d,Rulebook!$L5,x,'Stress Inputs'!J5*d,ta,Rulebook!$G5*d,tb,Rulebook!$H5*d,tc,Rulebook!$I5*d,te,Rulebook!$J5*d,tf,Rulebook!$K5*d,IFS(x<=ta,0,x<=tb,25*(x-ta)/(tb-ta),x<=tc,25+25*(x-tb)/(tc-tb),x<=te,50+25*(x-tc)/(te-tc),x<tf,75+25*(x-te)/(tf-te),TRUE,100))) | K5: =IF('Stress Inputs'!K5="","",LET(d,Rulebook!$L5,x,'Stress Inputs'!K5*d,ta,Rulebook!$G5*d,tb,Rulebook!$H5*d,tc,Rulebook!$I5*d,te,Rulebook!$J5*d,tf,Rulebook!$K5*d,IFS(x<=ta,0,x<=tb,25*(x-ta)/(tb-ta),x<=tc,25+25*(x-tb)/(tc-tb),x<=te,50+25*(x-tc)/(te-tc),x<tf,75+25*(x-te)/(tf-te),TRUE,100))) | L5: =IF('Stress Inputs'!L5="","",LET(d,Rulebook!$L5,x,'Stress Inputs'!L5*d,ta,Rulebook!$G5*d,tb,Rulebook!$H5*d,tc,Rulebook!$I5*d,te,Rulebook!$J5*d,tf,Rulebook!$K5*d,IFS(x<=ta,0,x<=tb,25*(x-ta)/(tb-ta),x<=tc,25+25*(x-tb)/(tc-tb),x<=te,50+25*(x-tc)/(te-tc),x<tf,75+25*(x-te)/(tf-te),TRUE,100))) | ... V5: =IF('Stress Inputs'!V5="","",LET(d,Rulebook!$L5,x,'Stress Inputs'!V5*d,ta,Rulebook!$G5*d,tb,Rulebook!$H5*d,tc,Rulebook!$I5*d,te,Rulebook!$J5*d,tf,Rulebook!$K5*d,IFS(x<=ta,0,x<=tb,25*(x-ta)/(tb-ta),x<=tc,25+25*(x-tb)/(tc-tb),x<=te,50+25*(x-tc)/(te-tc),x<tf,75+25*(x-te)/(tf-te),TRUE,100)))
A6: 1.2 | B6: 1 | C6: FX debt service due in next 24 months | D6: % of FX reserves | E6: =IF('Stress Inputs'!E6="","",LET(d,Rulebook!$L6,x,'Stress Inputs'!E6*d,ta,Rulebook!$G6*d,tb,Rulebook!$H6*d,tc,Rulebook!$I6*d,te,Rulebook!$J6*d,tf,Rulebook!$K6*d,IFS(x<=ta,0,x<=tb,25*(x-ta)/(tb-ta),x<=tc,25+25*(x-tb)/(tc-tb),x<=te,50+25*(x-tc)/(te-tc),x<tf,75+25*(x-te)/(tf-te),TRUE,100))) | F6: =IF('Stress Inputs'!F6="","",LET(d,Rulebook!$L6,x,'Stress Inputs'!F6*d,ta,Rulebook!$G6*d,tb,Rulebook!$H6*d,tc,Rulebook!$I6*d,te,Rulebook!$J6*d,tf,Rulebook!$K6*d,IFS(x<=ta,0,x<=tb,25*(x-ta)/(tb-ta),x<=tc,25+25*(x-tb)/(tc-tb),x<=te,50+25*(x-tc)/(te-tc),x<tf,75+25*(x-te)/(tf-te),TRUE,100))) | G6: =IF('Stress Inputs'!G6="","",LET(d,Rulebook!$L6,x,'Stress Inputs'!G6*d,ta,Rulebook!$G6*d,tb,Rulebook!$H6*d,tc,Rulebook!$I6*d,te,Rulebook!$J6*d,tf,Rulebook!$K6*d,IFS(x<=ta,0,x<=tb,25*(x-ta)/(tb-ta),x<=tc,25+25*(x-tb)/(tc-tb),x<=te,50+25*(x-tc)/(te-tc),x<tf,75+25*(x-te)/(tf-te),TRUE,100))) | H6: =IF('Stress Inputs'!H6="","",LET(d,Rulebook!$L6,x,'Stress Inputs'!H6*d,ta,Rulebook!$G6*d,tb,Rulebook!$H6*d,tc,Rulebook!$I6*d,te,Rulebook!$J6*d,tf,Rulebook!$K6*d,IFS(x<=ta,0,x<=tb,25*(x-ta)/(tb-ta),x<=tc,25+25*(x-tb)/(tc-tb),x<=te,50+25*(x-tc)/(te-tc),x<tf,75+25*(x-te)/(tf-te),TRUE,100))) | I6: =IF('Stress Inputs'!I6="","",LET(d,Rulebook!$L6,x,'Stress Inputs'!I6*d,ta,Rulebook!$G6*d,tb,Rulebook!$H6*d,tc,Rulebook!$I6*d,te,Rulebook!$J6*d,tf,Rulebook!$K6*d,IFS(x<=ta,0,x<=tb,25*(x-ta)/(tb-ta),x<=tc,25+25*(x-tb)/(tc-tb),x<=te,50+25*(x-tc)/(te-tc),x<tf,75+25*(x-te)/(tf-te),TRUE,100))) | J6: =IF('Stress Inputs'!J6="","",LET(d,Rulebook!$L6,x,'Stress Inputs'!J6*d,ta,Rulebook!$G6*d,tb,Rulebook!$H6*d,tc,Rulebook!$I6*d,te,Rulebook!$J6*d,tf,Rulebook!$K6*d,IFS(x<=ta,0,x<=tb,25*(x-ta)/(tb-ta),x<=tc,25+25*(x-tb)/(tc-tb),x<=te,50+25*(x-tc)/(te-tc),x<tf,75+25*(x-te)/(tf-te),TRUE,100))) | K6: =IF('Stress Inputs'!K6="","",LET(d,Rulebook!$L6,x,'Stress Inputs'!K6*d,ta,Rulebook!$G6*d,tb,Rulebook!$H6*d,tc,Rulebook!$I6*d,te,Rulebook!$J6*d,tf,Rulebook!$K6*d,IFS(x<=ta,0,x<=tb,25*(x-ta)/(tb-ta),x<=tc,25+25*(x-tb)/(tc-tb),x<=te,50+25*(x-tc)/(te-tc),x<tf,75+25*(x-te)/(tf-te),TRUE,100))) | L6: =IF('Stress Inputs'!L6="","",LET(d,Rulebook!$L6,x,'Stress Inputs'!L6*d,ta,Rulebook!$G6*d,tb,Rulebook!$H6*d,tc,Rulebook!$I6*d,te,Rulebook!$J6*d,tf,Rulebook!$K6*d,IFS(x<=ta,0,x<=tb,25*(x-ta)/(tb-ta),x<=tc,25+25*(x-tb)/(tc-tb),x<=te,50+25*(x-tc)/(te-tc),x<tf,75+25*(x-te)/(tf-te),TRUE,100))) | ... V6: =IF('Stress Inputs'!V6="","",LET(d,Rulebook!$L6,x,'Stress Inputs'!V6*d,ta,Rulebook!$G6*d,tb,Rulebook!$H6*d,tc,Rulebook!$I6*d,te,Rulebook!$J6*d,tf,Rulebook!$K6*d,IFS(x<=ta,0,x<=tb,25*(x-ta)/(tb-ta),x<=tc,25+25*(x-tb)/(tc-tb),x<=te,50+25*(x-tc)/(te-tc),x<tf,75+25*(x-te)/(tf-te),TRUE,100)))
A7: 1.3 | B7: 1 | C7: Gross government debt | D7: % of GDP | E7: =IF('Stress Inputs'!E7="","",LET(d,Rulebook!$L7,x,'Stress Inputs'!E7*d,ta,Rulebook!$G7*d,tb,Rulebook!$H7*d,tc,Rulebook!$I7*d,te,Rulebook!$J7*d,tf,Rulebook!$K7*d,IFS(x<=ta,0,x<=tb,25*(x-ta)/(tb-ta),x<=tc,25+25*(x-tb)/(tc-tb),x<=te,50+25*(x-tc)/(te-tc),x<tf,75+25*(x-te)/(tf-te),TRUE,100))) -> 10.068878 | F7: =IF('Stress Inputs'!F7="","",LET(d,Rulebook!$L7,x,'Stress Inputs'!F7*d,ta,Rulebook!$G7*d,tb,Rulebook!$H7*d,tc,Rulebook!$I7*d,te,Rulebook!$J7*d,tf,Rulebook!$K7*d,IFS(x<=ta,0,x<=tb,25*(x-ta)/(tb-ta),x<=tc,25+25*(x-tb)/(tc-tb),x<=te,50+25*(x-tc)/(te-tc),x<tf,75+25*(x-te)/(tf-te),TRUE,100))) -> 57.02551 | G7: =IF('Stress Inputs'!G7="","",LET(d,Rulebook!$L7,x,'Stress Inputs'!G7*d,ta,Rulebook!$G7*d,tb,Rulebook!$H7*d,tc,Rulebook!$I7*d,te,Rulebook!$J7*d,tf,Rulebook!$K7*d,IFS(x<=ta,0,x<=tb,25*(x-ta)/(tb-ta),x<=tc,25+25*(x-tb)/(tc-tb),x<=te,50+25*(x-tc)/(te-tc),x<tf,75+25*(x-te)/(tf-te),TRUE,100))) -> 100 | H7: =IF('Stress Inputs'!H7="","",LET(d,Rulebook!$L7,x,'Stress Inputs'!H7*d,ta,Rulebook!$G7*d,tb,Rulebook!$H7*d,tc,Rulebook!$I7*d,te,Rulebook!$J7*d,tf,Rulebook!$K7*d,IFS(x<=ta,0,x<=tb,25*(x-ta)/(tb-ta),x<=tc,25+25*(x-tb)/(tc-tb),x<=te,50+25*(x-tc)/(te-tc),x<tf,75+25*(x-te)/(tf-te),TRUE,100))) -> 64.544898 | I7: =IF('Stress Inputs'!I7="","",LET(d,Rulebook!$L7,x,'Stress Inputs'!I7*d,ta,Rulebook!$G7*d,tb,Rulebook!$H7*d,tc,Rulebook!$I7*d,te,Rulebook!$J7*d,tf,Rulebook!$K7*d,IFS(x<=ta,0,x<=tb,25*(x-ta)/(tb-ta),x<=tc,25+25*(x-tb)/(tc-tb),x<=te,50+25*(x-tc)/(te-tc),x<tf,75+25*(x-te)/(tf-te),TRUE,100))) -> 100 | J7: =IF('Stress Inputs'!J7="","",LET(d,Rulebook!$L7,x,'Stress Inputs'!J7*d,ta,Rulebook!$G7*d,tb,Rulebook!$H7*d,tc,Rulebook!$I7*d,te,Rulebook!$J7*d,tf,Rulebook!$K7*d,IFS(x<=ta,0,x<=tb,25*(x-ta)/(tb-ta),x<=tc,25+25*(x-tb)/(tc-tb),x<=te,50+25*(x-tc)/(te-tc),x<tf,75+25*(x-te)/(tf-te),TRUE,100))) -> 100 | K7: =IF('Stress Inputs'!K7="","",LET(d,Rulebook!$L7,x,'Stress Inputs'!K7*d,ta,Rulebook!$G7*d,tb,Rulebook!$H7*d,tc,Rulebook!$I7*d,te,Rulebook!$J7*d,tf,Rulebook!$K7*d,IFS(x<=ta,0,x<=tb,25*(x-ta)/(tb-ta),x<=tc,25+25*(x-tb)/(tc-tb),x<=te,50+25*(x-tc)/(te-tc),x<tf,75+25*(x-te)/(tf-te),TRUE,100))) -> 31.92483 | L7: =IF('Stress Inputs'!L7="","",LET(d,Rulebook!$L7,x,'Stress Inputs'!L7*d,ta,Rulebook!$G7*d,tb,Rulebook!$H7*d,tc,Rulebook!$I7*d,te,Rulebook!$J7*d,tf,Rulebook!$K7*d,IFS(x<=ta,0,x<=tb,25*(x-ta)/(tb-ta),x<=tc,25+25*(x-tb)/(tc-tb),x<=te,50+25*(x-tc)/(te-tc),x<tf,75+25*(x-te)/(tf-te),TRUE,100))) -> 82.53986 | ... V7: =IF('Stress Inputs'!V7="","",LET(d,Rulebook!$L7,x,'Stress Inputs'!V7*d,ta,Rulebook!$G7*d,tb,Rulebook!$H7*d,tc,Rulebook!$I7*d,te,Rulebook!$J7*d,tf,Rulebook!$K7*d,IFS(x<=ta,0,x<=tb,25*(x-ta)/(tb-ta),x<=tc,25+25*(x-tb)/(tc-tb),x<=te,50+25*(x-tc)/(te-tc),x<tf,75+25*(x-te)/(tf-te),TRUE,100))) -> 82.892857
A8: 1.4 | B8: 1 | C8: Gross financing need | D8: % of GDP | E8: =IF('Stress Inputs'!E8="","",LET(d,Rulebook!$L8,x,'Stress Inputs'!E8*d,ta,Rulebook!$G8*d,tb,Rulebook!$H8*d,tc,Rulebook!$I8*d,te,Rulebook!$J8*d,tf,Rulebook!$K8*d,IFS(x<=ta,0,x<=tb,25*(x-ta)/(tb-ta),x<=tc,25+25*(x-tb)/(tc-tb),x<=te,50+25*(x-tc)/(te-tc),x<tf,75+25*(x-te)/(tf-te),TRUE,100))) -> 8.825 | F8: =IF('Stress Inputs'!F8="","",LET(d,Rulebook!$L8,x,'Stress Inputs'!F8*d,ta,Rulebook!$G8*d,tb,Rulebook!$H8*d,tc,Rulebook!$I8*d,te,Rulebook!$J8*d,tf,Rulebook!$K8*d,IFS(x<=ta,0,x<=tb,25*(x-ta)/(tb-ta),x<=tc,25+25*(x-tb)/(tc-tb),x<=te,50+25*(x-tc)/(te-tc),x<tf,75+25*(x-te)/(tf-te),TRUE,100))) -> 29.5 | G8: =IF('Stress Inputs'!G8="","",LET(d,Rulebook!$L8,x,'Stress Inputs'!G8*d,ta,Rulebook!$G8*d,tb,Rulebook!$H8*d,tc,Rulebook!$I8*d,te,Rulebook!$J8*d,tf,Rulebook!$K8*d,IFS(x<=ta,0,x<=tb,25*(x-ta)/(tb-ta),x<=tc,25+25*(x-tb)/(tc-tb),x<=te,50+25*(x-tc)/(te-tc),x<tf,75+25*(x-te)/(tf-te),TRUE,100))) -> 70.61 | H8: =IF('Stress Inputs'!H8="","",LET(d,Rulebook!$L8,x,'Stress Inputs'!H8*d,ta,Rulebook!$G8*d,tb,Rulebook!$H8*d,tc,Rulebook!$I8*d,te,Rulebook!$J8*d,tf,Rulebook!$K8*d,IFS(x<=ta,0,x<=tb,25*(x-ta)/(tb-ta),x<=tc,25+25*(x-tb)/(tc-tb),x<=te,50+25*(x-tc)/(te-tc),x<tf,75+25*(x-te)/(tf-te),TRUE,100))) -> 39.73 | I8: =IF('Stress Inputs'!I8="","",LET(d,Rulebook!$L8,x,'Stress Inputs'!I8*d,ta,Rulebook!$G8*d,tb,Rulebook!$H8*d,tc,Rulebook!$I8*d,te,Rulebook!$J8*d,tf,Rulebook!$K8*d,IFS(x<=ta,0,x<=tb,25*(x-ta)/(tb-ta),x<=tc,25+25*(x-tb)/(tc-tb),x<=te,50+25*(x-tc)/(te-tc),x<tf,75+25*(x-te)/(tf-te),TRUE,100))) -> 0 | J8: =IF('Stress Inputs'!J8="","",LET(d,Rulebook!$L8,x,'Stress Inputs'!J8*d,ta,Rulebook!$G8*d,tb,Rulebook!$H8*d,tc,Rulebook!$I8*d,te,Rulebook!$J8*d,tf,Rulebook!$K8*d,IFS(x<=ta,0,x<=tb,25*(x-ta)/(tb-ta),x<=tc,25+25*(x-tb)/(tc-tb),x<=te,50+25*(x-tc)/(te-tc),x<tf,75+25*(x-te)/(tf-te),TRUE,100))) -> 100 | K8: =IF('Stress Inputs'!K8="","",LET(d,Rulebook!$L8,x,'Stress Inputs'!K8*d,ta,Rulebook!$G8*d,tb,Rulebook!$H8*d,tc,Rulebook!$I8*d,te,Rulebook!$J8*d,tf,Rulebook!$K8*d,IFS(x<=ta,0,x<=tb,25*(x-ta)/(tb-ta),x<=tc,25+25*(x-tb)/(tc-tb),x<=te,50+25*(x-tc)/(te-tc),x<tf,75+25*(x-te)/(tf-te),TRUE,100))) -> 4.1825 | L8: =IF('Stress Inputs'!L8="","",LET(d,Rulebook!$L8,x,'Stress Inputs'!L8*d,ta,Rulebook!$G8*d,tb,Rulebook!$H8*d,tc,Rulebook!$I8*d,te,Rulebook!$J8*d,tf,Rulebook!$K8*d,IFS(x<=ta,0,x<=tb,25*(x-ta)/(tb-ta),x<=tc,25+25*(x-tb)/(tc-tb),x<=te,50+25*(x-tc)/(te-tc),x<tf,75+25*(x-te)/(tf-te),TRUE,100))) -> 50.0775 | ... V8: =IF('Stress Inputs'!V8="","",LET(d,Rulebook!$L8,x,'Stress Inputs'!V8*d,ta,Rulebook!$G8*d,tb,Rulebook!$H8*d,tc,Rulebook!$I8*d,te,Rulebook!$J8*d,tf,Rulebook!$K8*d,IFS(x<=ta,0,x<=tb,25*(x-ta)/(tb-ta),x<=tc,25+25*(x-tb)/(tc-tb),x<=te,50+25*(x-tc)/(te-tc),x<tf,75+25*(x-te)/(tf-te),TRUE,100))) -> 19.875
A9: 1.5 | B9: 1 | C9: Foreign-currency share of government debt | D9: % of debt | E9: =IF('Stress Inputs'!E9="","",LET(d,Rulebook!$L9,x,'Stress Inputs'!E9*d,ta,Rulebook!$G9*d,tb,Rulebook!$H9*d,tc,Rulebook!$I9*d,te,Rulebook!$J9*d,tf,Rulebook!$K9*d,IFS(x<=ta,0,x<=tb,25*(x-ta)/(tb-ta),x<=tc,25+25*(x-tb)/(tc-tb),x<=te,50+25*(x-tc)/(te-tc),x<tf,75+25*(x-te)/(tf-te),TRUE,100))) | F9: =IF('Stress Inputs'!F9="","",LET(d,Rulebook!$L9,x,'Stress Inputs'!F9*d,ta,Rulebook!$G9*d,tb,Rulebook!$H9*d,tc,Rulebook!$I9*d,te,Rulebook!$J9*d,tf,Rulebook!$K9*d,IFS(x<=ta,0,x<=tb,25*(x-ta)/(tb-ta),x<=tc,25+25*(x-tb)/(tc-tb),x<=te,50+25*(x-tc)/(te-tc),x<tf,75+25*(x-te)/(tf-te),TRUE,100))) | G9: =IF('Stress Inputs'!G9="","",LET(d,Rulebook!$L9,x,'Stress Inputs'!G9*d,ta,Rulebook!$G9*d,tb,Rulebook!$H9*d,tc,Rulebook!$I9*d,te,Rulebook!$J9*d,tf,Rulebook!$K9*d,IFS(x<=ta,0,x<=tb,25*(x-ta)/(tb-ta),x<=tc,25+25*(x-tb)/(tc-tb),x<=te,50+25*(x-tc)/(te-tc),x<tf,75+25*(x-te)/(tf-te),TRUE,100))) | H9: =IF('Stress Inputs'!H9="","",LET(d,Rulebook!$L9,x,'Stress Inputs'!H9*d,ta,Rulebook!$G9*d,tb,Rulebook!$H9*d,tc,Rulebook!$I9*d,te,Rulebook!$J9*d,tf,Rulebook!$K9*d,IFS(x<=ta,0,x<=tb,25*(x-ta)/(tb-ta),x<=tc,25+25*(x-tb)/(tc-tb),x<=te,50+25*(x-tc)/(te-tc),x<tf,75+25*(x-te)/(tf-te),TRUE,100))) | I9: =IF('Stress Inputs'!I9="","",LET(d,Rulebook!$L9,x,'Stress Inputs'!I9*d,ta,Rulebook!$G9*d,tb,Rulebook!$H9*d,tc,Rulebook!$I9*d,te,Rulebook!$J9*d,tf,Rulebook!$K9*d,IFS(x<=ta,0,x<=tb,25*(x-ta)/(tb-ta),x<=tc,25+25*(x-tb)/(tc-tb),x<=te,50+25*(x-tc)/(te-tc),x<tf,75+25*(x-te)/(tf-te),TRUE,100))) | J9: =IF('Stress Inputs'!J9="","",LET(d,Rulebook!$L9,x,'Stress Inputs'!J9*d,ta,Rulebook!$G9*d,tb,Rulebook!$H9*d,tc,Rulebook!$I9*d,te,Rulebook!$J9*d,tf,Rulebook!$K9*d,IFS(x<=ta,0,x<=tb,25*(x-ta)/(tb-ta),x<=tc,25+25*(x-tb)/(tc-tb),x<=te,50+25*(x-tc)/(te-tc),x<tf,75+25*(x-te)/(tf-te),TRUE,100))) | K9: =IF('Stress Inputs'!K9="","",LET(d,Rulebook!$L9,x,'Stress Inputs'!K9*d,ta,Rulebook!$G9*d,tb,Rulebook!$H9*d,tc,Rulebook!$I9*d,te,Rulebook!$J9*d,tf,Rulebook!$K9*d,IFS(x<=ta,0,x<=tb,25*(x-ta)/(tb-ta),x<=tc,25+25*(x-tb)/(tc-tb),x<=te,50+25*(x-tc)/(te-tc),x<tf,75+25*(x-te)/(tf-te),TRUE,100))) | L9: =IF('Stress Inputs'!L9="","",LET(d,Rulebook!$L9,x,'Stress Inputs'!L9*d,ta,Rulebook!$G9*d,tb,Rulebook!$H9*d,tc,Rulebook!$I9*d,te,Rulebook!$J9*d,tf,Rulebook!$K9*d,IFS(x<=ta,0,x<=tb,25*(x-ta)/(tb-ta),x<=tc,25+25*(x-tb)/(tc-tb),x<=te,50+25*(x-tc)/(te-tc),x<tf,75+25*(x-te)/(tf-te),TRUE,100))) | ... V9: =IF('Stress Inputs'!V9="","",LET(d,Rulebook!$L9,x,'Stress Inputs'!V9*d,ta,Rulebook!$G9*d,tb,Rulebook!$H9*d,tc,Rulebook!$I9*d,te,Rulebook!$J9*d,tf,Rulebook!$K9*d,IFS(x<=ta,0,x<=tb,25*(x-ta)/(tb-ta),x<=tc,25+25*(x-tb)/(tc-tb),x<=te,50+25*(x-tc)/(te-tc),x<tf,75+25*(x-te)/(tf-te),TRUE,100)))
A10: 1.6 | B10: 1 | C10: Primary balance gap (actual minus debt-stabilizing) | D10: pp of GDP | E10: =IF('Stress Inputs'!E10="","",LET(d,Rulebook!$L10,x,'Stress Inputs'!E10*d,ta,Rulebook!$G10*d,tb,Rulebook!$H10*d,tc,Rulebook!$I10*d,te,Rulebook!$J10*d,tf,Rulebook!$K10*d,IFS(x<=ta,0,x<=tb,25*(x-ta)/(tb-ta),x<=tc,25+25*(x-tb)/(tc-tb),x<=te,50+25*(x-tc)/(te-tc),x<tf,75+25*(x-te)/(tf-te),TRUE,100))) -> 23.125 | F10: =IF('Stress Inputs'!F10="","",LET(d,Rulebook!$L10,x,'Stress Inputs'!F10*d,ta,Rulebook!$G10*d,tb,Rulebook!$H10*d,tc,Rulebook!$I10*d,te,Rulebook!$J10*d,tf,Rulebook!$K10*d,IFS(x<=ta,0,x<=tb,25*(x-ta)/(tb-ta),x<=tc,25+25*(x-tb)/(tc-tb),x<=te,50+25*(x-tc)/(te-tc),x<tf,75+25*(x-te)/(tf-te),TRUE,100))) -> 68.333333 | G10: =IF('Stress Inputs'!G10="","",LET(d,Rulebook!$L10,x,'Stress Inputs'!G10*d,ta,Rulebook!$G10*d,tb,Rulebook!$H10*d,tc,Rulebook!$I10*d,te,Rulebook!$J10*d,tf,Rulebook!$K10*d,IFS(x<=ta,0,x<=tb,25*(x-ta)/(tb-ta),x<=tc,25+25*(x-tb)/(tc-tb),x<=te,50+25*(x-tc)/(te-tc),x<tf,75+25*(x-te)/(tf-te),TRUE,100))) -> 100 | H10: =IF('Stress Inputs'!H10="","",LET(d,Rulebook!$L10,x,'Stress Inputs'!H10*d,ta,Rulebook!$G10*d,tb,Rulebook!$H10*d,tc,Rulebook!$I10*d,te,Rulebook!$J10*d,tf,Rulebook!$K10*d,IFS(x<=ta,0,x<=tb,25*(x-ta)/(tb-ta),x<=tc,25+25*(x-tb)/(tc-tb),x<=te,50+25*(x-tc)/(te-tc),x<tf,75+25*(x-te)/(tf-te),TRUE,100))) -> 63.833333 | I10: =IF('Stress Inputs'!I10="","",LET(d,Rulebook!$L10,x,'Stress Inputs'!I10*d,ta,Rulebook!$G10*d,tb,Rulebook!$H10*d,tc,Rulebook!$I10*d,te,Rulebook!$J10*d,tf,Rulebook!$K10*d,IFS(x<=ta,0,x<=tb,25*(x-ta)/(tb-ta),x<=tc,25+25*(x-tb)/(tc-tb),x<=te,50+25*(x-tc)/(te-tc),x<tf,75+25*(x-te)/(tf-te),TRUE,100))) -> 66.25 | J10: =IF('Stress Inputs'!J10="","",LET(d,Rulebook!$L10,x,'Stress Inputs'!J10*d,ta,Rulebook!$G10*d,tb,Rulebook!$H10*d,tc,Rulebook!$I10*d,te,Rulebook!$J10*d,tf,Rulebook!$K10*d,IFS(x<=ta,0,x<=tb,25*(x-ta)/(tb-ta),x<=tc,25+25*(x-tb)/(tc-tb),x<=te,50+25*(x-tc)/(te-tc),x<tf,75+25*(x-te)/(tf-te),TRUE,100))) -> 100 | K10: =IF('Stress Inputs'!K10="","",LET(d,Rulebook!$L10,x,'Stress Inputs'!K10*d,ta,Rulebook!$G10*d,tb,Rulebook!$H10*d,tc,Rulebook!$I10*d,te,Rulebook!$J10*d,tf,Rulebook!$K10*d,IFS(x<=ta,0,x<=tb,25*(x-ta)/(tb-ta),x<=tc,25+25*(x-tb)/(tc-tb),x<=te,50+25*(x-tc)/(te-tc),x<tf,75+25*(x-te)/(tf-te),TRUE,100))) -> 54.708333 | L10: =IF('Stress Inputs'!L10="","",LET(d,Rulebook!$L10,x,'Stress Inputs'!L10*d,ta,Rulebook!$G10*d,tb,Rulebook!$H10*d,tc,Rulebook!$I10*d,te,Rulebook!$J10*d,tf,Rulebook!$K10*d,IFS(x<=ta,0,x<=tb,25*(x-ta)/(tb-ta),x<=tc,25+25*(x-tb)/(tc-tb),x<=te,50+25*(x-tc)/(te-tc),x<tf,75+25*(x-te)/(tf-te),TRUE,100))) -> 86.291667 | ... V10: =IF('Stress Inputs'!V10="","",LET(d,Rulebook!$L10,x,'Stress Inputs'!V10*d,ta,Rulebook!$G10*d,tb,Rulebook!$H10*d,tc,Rulebook!$I10*d,te,Rulebook!$J10*d,tf,Rulebook!$K10*d,IFS(x<=ta,0,x<=tb,25*(x-ta)/(tb-ta),x<=tc,25+25*(x-tb)/(tc-tb),x<=te,50+25*(x-tc)/(te-tc),x<tf,75+25*(x-te)/(tf-te),TRUE,100))) -> 74.583333
A11: 1.7 | B11: 1 | C11: Change in debt/GDP over five years | D11: pp of GDP | E11: =IF('Stress Inputs'!E11="","",LET(d,Rulebook!$L11,x,'Stress Inputs'!E11*d,ta,Rulebook!$G11*d,tb,Rulebook!$H11*d,tc,Rulebook!$I11*d,te,Rulebook!$J11*d,tf,Rulebook!$K11*d,IFS(x<=ta,0,x<=tb,25*(x-ta)/(tb-ta),x<=tc,25+25*(x-tb)/(tc-tb),x<=te,50+25*(x-tc)/(te-tc),x<tf,75+25*(x-te)/(tf-te),TRUE,100))) -> 10.206633 | F11: =IF('Stress Inputs'!F11="","",LET(d,Rulebook!$L11,x,'Stress Inputs'!F11*d,ta,Rulebook!$G11*d,tb,Rulebook!$H11*d,tc,Rulebook!$I11*d,te,Rulebook!$J11*d,tf,Rulebook!$K11*d,IFS(x<=ta,0,x<=tb,25*(x-ta)/(tb-ta),x<=tc,25+25*(x-tb)/(tc-tb),x<=te,50+25*(x-tc)/(te-tc),x<tf,75+25*(x-te)/(tf-te),TRUE,100))) -> 63.102041 | G11: =IF('Stress Inputs'!G11="","",LET(d,Rulebook!$L11,x,'Stress Inputs'!G11*d,ta,Rulebook!$G11*d,tb,Rulebook!$H11*d,tc,Rulebook!$I11*d,te,Rulebook!$J11*d,tf,Rulebook!$K11*d,IFS(x<=ta,0,x<=tb,25*(x-ta)/(tb-ta),x<=tc,25+25*(x-tb)/(tc-tb),x<=te,50+25*(x-tc)/(te-tc),x<tf,75+25*(x-te)/(tf-te),TRUE,100))) -> 100 | H11: =IF('Stress Inputs'!H11="","",LET(d,Rulebook!$L11,x,'Stress Inputs'!H11*d,ta,Rulebook!$G11*d,tb,Rulebook!$H11*d,tc,Rulebook!$I11*d,te,Rulebook!$J11*d,tf,Rulebook!$K11*d,IFS(x<=ta,0,x<=tb,25*(x-ta)/(tb-ta),x<=tc,25+25*(x-tb)/(tc-tb),x<=te,50+25*(x-tc)/(te-tc),x<tf,75+25*(x-te)/(tf-te),TRUE,100))) -> 44.679592 | I11: =IF('Stress Inputs'!I11="","",LET(d,Rulebook!$L11,x,'Stress Inputs'!I11*d,ta,Rulebook!$G11*d,tb,Rulebook!$H11*d,tc,Rulebook!$I11*d,te,Rulebook!$J11*d,tf,Rulebook!$K11*d,IFS(x<=ta,0,x<=tb,25*(x-ta)/(tb-ta),x<=tc,25+25*(x-tb)/(tc-tb),x<=te,50+25*(x-tc)/(te-tc),x<tf,75+25*(x-te)/(tf-te),TRUE,100))) -> 100 | J11: =IF('Stress Inputs'!J11="","",LET(d,Rulebook!$L11,x,'Stress Inputs'!J11*d,ta,Rulebook!$G11*d,tb,Rulebook!$H11*d,tc,Rulebook!$I11*d,te,Rulebook!$J11*d,tf,Rulebook!$K11*d,IFS(x<=ta,0,x<=tb,25*(x-ta)/(tb-ta),x<=tc,25+25*(x-tb)/(tc-tb),x<=te,50+25*(x-tc)/(te-tc),x<tf,75+25*(x-te)/(tf-te),TRUE,100))) -> 0 | K11: =IF('Stress Inputs'!K11="","",LET(d,Rulebook!$L11,x,'Stress Inputs'!K11*d,ta,Rulebook!$G11*d,tb,Rulebook!$H11*d,tc,Rulebook!$I11*d,te,Rulebook!$J11*d,tf,Rulebook!$K11*d,IFS(x<=ta,0,x<=tb,25*(x-ta)/(tb-ta),x<=tc,25+25*(x-tb)/(tc-tb),x<=te,50+25*(x-tc)/(te-tc),x<tf,75+25*(x-te)/(tf-te),TRUE,100))) -> 41.27449 | L11: =IF('Stress Inputs'!L11="","",LET(d,Rulebook!$L11,x,'Stress Inputs'!L11*d,ta,Rulebook!$G11*d,tb,Rulebook!$H11*d,tc,Rulebook!$I11*d,te,Rulebook!$J11*d,tf,Rulebook!$K11*d,IFS(x<=ta,0,x<=tb,25*(x-ta)/(tb-ta),x<=tc,25+25*(x-tb)/(tc-tb),x<=te,50+25*(x-tc)/(te-tc),x<tf,75+25*(x-te)/(tf-te),TRUE,100))) -> 3.1594388 | ... V11: =IF('Stress Inputs'!V11="","",LET(d,Rulebook!$L11,x,'Stress Inputs'!V11*d,ta,Rulebook!$G11*d,tb,Rulebook!$H11*d,tc,Rulebook!$I11*d,te,Rulebook!$J11*d,tf,Rulebook!$K11*d,IFS(x<=ta,0,x<=tb,25*(x-ta)/(tb-ta),x<=tc,25+25*(x-tb)/(tc-tb),x<=te,50+25*(x-tc)/(te-tc),x<tf,75+25*(x-te)/(tf-te),TRUE,100))) -> 0
A12: 1.8 | B12: 1 | C12: Default record: restructurings or defaults, past 20 years | D12: count | E12: =IF('Stress Inputs'!E12="","",LET(d,Rulebook!$L12,x,'Stress Inputs'!E12*d,ta,Rulebook!$G12*d,tb,Rulebook!$H12*d,tc,Rulebook!$I12*d,te,Rulebook!$J12*d,tf,Rulebook!$K12*d,IFS(x<=ta,0,x<=tb,25*(x-ta)/(tb-ta),x<=tc,25+25*(x-tb)/(tc-tb),x<=te,50+25*(x-tc)/(te-tc),x<tf,75+25*(x-te)/(tf-te),TRUE,100))) | F12: =IF('Stress Inputs'!F12="","",LET(d,Rulebook!$L12,x,'Stress Inputs'!F12*d,ta,Rulebook!$G12*d,tb,Rulebook!$H12*d,tc,Rulebook!$I12*d,te,Rulebook!$J12*d,tf,Rulebook!$K12*d,IFS(x<=ta,0,x<=tb,25*(x-ta)/(tb-ta),x<=tc,25+25*(x-tb)/(tc-tb),x<=te,50+25*(x-tc)/(te-tc),x<tf,75+25*(x-te)/(tf-te),TRUE,100))) | G12: =IF('Stress Inputs'!G12="","",LET(d,Rulebook!$L12,x,'Stress Inputs'!G12*d,ta,Rulebook!$G12*d,tb,Rulebook!$H12*d,tc,Rulebook!$I12*d,te,Rulebook!$J12*d,tf,Rulebook!$K12*d,IFS(x<=ta,0,x<=tb,25*(x-ta)/(tb-ta),x<=tc,25+25*(x-tb)/(tc-tb),x<=te,50+25*(x-tc)/(te-tc),x<tf,75+25*(x-te)/(tf-te),TRUE,100))) | H12: =IF('Stress Inputs'!H12="","",LET(d,Rulebook!$L12,x,'Stress Inputs'!H12*d,ta,Rulebook!$G12*d,tb,Rulebook!$H12*d,tc,Rulebook!$I12*d,te,Rulebook!$J12*d,tf,Rulebook!$K12*d,IFS(x<=ta,0,x<=tb,25*(x-ta)/(tb-ta),x<=tc,25+25*(x-tb)/(tc-tb),x<=te,50+25*(x-tc)/(te-tc),x<tf,75+25*(x-te)/(tf-te),TRUE,100))) | I12: =IF('Stress Inputs'!I12="","",LET(d,Rulebook!$L12,x,'Stress Inputs'!I12*d,ta,Rulebook!$G12*d,tb,Rulebook!$H12*d,tc,Rulebook!$I12*d,te,Rulebook!$J12*d,tf,Rulebook!$K12*d,IFS(x<=ta,0,x<=tb,25*(x-ta)/(tb-ta),x<=tc,25+25*(x-tb)/(tc-tb),x<=te,50+25*(x-tc)/(te-tc),x<tf,75+25*(x-te)/(tf-te),TRUE,100))) | J12: =IF('Stress Inputs'!J12="","",LET(d,Rulebook!$L12,x,'Stress Inputs'!J12*d,ta,Rulebook!$G12*d,tb,Rulebook!$H12*d,tc,Rulebook!$I12*d,te,Rulebook!$J12*d,tf,Rulebook!$K12*d,IFS(x<=ta,0,x<=tb,25*(x-ta)/(tb-ta),x<=tc,25+25*(x-tb)/(tc-tb),x<=te,50+25*(x-tc)/(te-tc),x<tf,75+25*(x-te)/(tf-te),TRUE,100))) | K12: =IF('Stress Inputs'!K12="","",LET(d,Rulebook!$L12,x,'Stress Inputs'!K12*d,ta,Rulebook!$G12*d,tb,Rulebook!$H12*d,tc,Rulebook!$I12*d,te,Rulebook!$J12*d,tf,Rulebook!$K12*d,IFS(x<=ta,0,x<=tb,25*(x-ta)/(tb-ta),x<=tc,25+25*(x-tb)/(tc-tb),x<=te,50+25*(x-tc)/(te-tc),x<tf,75+25*(x-te)/(tf-te),TRUE,100))) | L12: =IF('Stress Inputs'!L12="","",LET(d,Rulebook!$L12,x,'Stress Inputs'!L12*d,ta,Rulebook!$G12*d,tb,Rulebook!$H12*d,tc,Rulebook!$I12*d,te,Rulebook!$J12*d,tf,Rulebook!$K12*d,IFS(x<=ta,0,x<=tb,25*(x-ta)/(tb-ta),x<=tc,25+25*(x-tb)/(tc-tb),x<=te,50+25*(x-tc)/(te-tc),x<tf,75+25*(x-te)/(tf-te),TRUE,100))) | ... V12: =IF('Stress Inputs'!V12="","",LET(d,Rulebook!$L12,x,'Stress Inputs'!V12*d,ta,Rulebook!$G12*d,tb,Rulebook!$H12*d,tc,Rulebook!$I12*d,te,Rulebook!$J12*d,tf,Rulebook!$K12*d,IFS(x<=ta,0,x<=tb,25*(x-ta)/(tb-ta),x<=tc,25+25*(x-tb)/(tc-tb),x<=te,50+25*(x-tc)/(te-tc),x<tf,75+25*(x-te)/(tf-te),TRUE,100)))
